Workbook

Sheet Akseptasi
B2: Nama | C2: SITI HAFSAH
B3: Tanggal Lahir | C3: 28057 | E3: =DATEDIF(C3,C21,"Y")&"Tahun "&DATEDIF(C3,C21,"YM")&"bulan "&DATEDIF(C3,C21,"MD")&"hari" -> 50Tahun 0bulan 4hari
B4: NIP | C4: 1968012220071012004
B5: Gaji Pokok | C5: 4254800 | D5: 1 | E5: =C5*D5 -> 4254800
B6: Uang Makan | C6: 550000 | D6: 0.9 | E6: =C6*D6 -> 495000
B7: Tunjangan Rutin per 1 Bulan | C7: 3761240 | D7: 0.9 | E7: =C7*D7 -> 3385116
B8: Tunjangan Rutin per 3 Bulan | C8: 0 | D8: 0.5 | E8: =C8*D8 -> 0
B9: Tunjangan Lain Rutin per 1 Bulan | C9: 0 | D9: 0.8 | E9: =C9*D9 -> 0
E10: =SUM(E5:E9) -> 8134916 | F10: 0.7 | G10: =E10*F10 -> 5694441.2
B12: TMT Bekerja | C12: 39083
B13: TMT Pensiun (BUP) | C13: 2036
B14: THT | C14: 78600000 | F14: 0.75 | G14: =C14*F14 -> 58950000
B15: Pensiun | C15: 4600000 | F15: 0.9 | G15: =C15*F15 -> 4140000
B17: Tenor (Bulan): | C17: 180 | I17: Tri Nett 200 | J17: Dekade Nett 200 | K17: dibawah 200
B18: Price Saat Aktif: | C18: 0.0925 | E18: Sesuaikan Pricing yang Berlaku | H18: Rate Masa Aktif | I18: 9.25% | J18: 9.50% | K18: 10.50%
B19: Price Saat Pensiun: | C19: 0.105 | E19: Sesuaikan Pricing yang Berlaku | H19: Rate Masa Pensiun | I19: 10.50% | J19: 10.50% | K19: 11.50%
B21: Proyeksi Cair | C21: =NOW()+7 -> 46323.502
B22: Start Angsuran | C22: 46327
B23: Selesai Angsuran | C23: =EDATE(C22,C17-1) -> 51775 | E23: =DATEDIF(C3,C23,"Y")&"Tahun "&DATEDIF(C3,C23,"YM")&"bulan "&DATEDIF(C3,C23,"MD")&"hari" -> 64Tahun 11bulan 7hari | G23: (Setting Usia Jatuh Tempo Maks 74 Thn 4 bln x hari)
B25: Biaya Asuransi | C25: 39998267 | E25: Isi Dari Hasil Kalkulator Asuransi
B27: Buka Blokir Yang Lama | C27: 0
B28: Pelunasan Yang Lama | C28: =C65 -> 0
B30: Plafond Pra Pensiun | C30: =Simulasi!B10 -> 480000000
B31: Estimasi Taksasi MMQ | C31: =(2%*C30)+C30 -> 489600000 | E31: =ROUNDUP(C31,-6) -> 490000000
B40: Fasilitas Eksisting (Dilunasi/Tidak Dilunasi)
B41: Nama | C41: =C2 -> SITI HAFSAH
B42: Produk | C42: Mitraguna
B43: Akad Pembiayaan | C43: Murabahah
B44: Jenis Pelunasan | C44: Pelunasan di Percepat (Top Up Lunas Maju)
B45: Margin Dibayar | C45: n + 1 + Sisa Atribusi
B47: No. Loan | C47: LD2400931674 | E47: LD2206703248
B48: CIF | C48: 92236837 | E48: 80844000
B49: No. Rek Debet | C49: 7256353231 | E49: 7104565675
B50: Tanggal Cair | C50: 45300 | E50: 44628
B51: Tanggal Jatuh Tempo | C51: 47423 | E51: 48639
B52: Jangka Waktu Pembiayaan | C52: 70 | E52: 132
B53: Jangka Waktu Telah Dijalani | C53: 28
B54: Tunggakan | C54: 0
B55: Plafond Awal
B56: OS Pokok Pembiayaan
B57: Sisa Margin/Ujrah
B58: Margin Pelunasan | C58: 0
B59: Diskon Margin/Ujrah | C59: =C57-C58 -> 0 | E59: =E57-E58 -> 0
B60: Jenis Atribusi | C60: YA
B61: Biaya Atribusi Awal | C61: 0 | E61: 0
B62: Nilai Atribusi Per Bulan | C62: =C61/C52 -> 0 | E62: =E61/E52 -> 0
B63: Sisa Nilai Atribusi | C63: =C61-(C62*C53) -> 0 | E63: =E61-(E62*E53) -> 0
B64: Pelunasan | C64: =C56+C58+C63 -> 0 | E64: =E56+E58+E63 -> 0
B65: Total Pelunasan | C65: =C64+E64 -> 0

Sheet Simulasi
A1: SIMULASI NOS MITRAGUNA PRIMA+
A2: INPUT | D2: HIDE S.D Kol. W
A3: Tipe Produk: | B3: Prapen 10 Tahun | C3: =MID(B3,8,1) -> 1 | G3: AKTIF | H3: angsuran set | I3: cek angsuran maks akhir
A4: Status Payroll: | B4: Payroll | C4: =MID(B4,1,1) -> P | F4: P | G4: =MIN((B16-B19)*C16,0.7*(B16-B19)) -> 5694441.2 | H4: =B18-B19 -> 0 | I4: =IF($B$18=0,G4,MIN(G4,H4)) -> 5694441.2
A5: Tgl Proyeksi cair: | B5: =NOW()+7 -> 46323.502 | F5: C | G5: =MIN((B16-B19-B20)*C16,0.8*(B16-B19-B20)) -> 5694441.2 | H5: =B18-B19-B20 -> 0 | I5: =IF($B$18=0,G5,MIN(G5,H5)) -> 5694441.2
A6: Tgl Lahir: | B6: =Akseptasi!C3 -> 28057 | F6: N | G6: =MIN((B16-B19-B20)*C16,0.5*(B16-B19-B20)) -> 4067458 | H6: =B18-B19-B20 -> 0 | I6: =IF($B$18=0,G6,MIN(G6,H6)) -> 4067458
A7: TMT Bekerja: | B7: =Akseptasi!C12 -> 39083 | C7: =DATE(B8,MONTH(B6)+1,1) -> 49980 | F7: Pensiun Angs | G7: =B17*C17 -> 4140000 | H7: =G7 -> 4140000 | I7: =IF($B$18=0,G7,MIN(G7,H7)) -> 4140000
A8: Tahun BUP: | B8: =Akseptasi!C13 -> 2036 | C8: =ROUND((C7-B5)/30.5,0) -> 120 | D8: masa aktif
A9: Tanggal BUP: | B9: =C7 -> 49980 | C9: =C8/12 -> 10 | G9: 0.7
A10: Plafond Pengajuan: | B10: 480000000 | G10: 0.8
A11: Tenor (Bulan): | B11: =Akseptasi!C17 -> 180 | D11: =8*12 -> 96 | G11: 0.5
A12: Price Saat Aktif: | B12: =Akseptasi!C18 -> 0.0925 | D12: 7 | F12: 1. No Atribusi
A13: Price Saat Pensiun: | B13: =Akseptasi!C19 -> 0.105 | D13: =D11+D12 -> 103 | F13: 2. Atribusi Asuransi
A14: Tipe Atribusi: | B14: 2. Atribusi Asuransi | C14: =LEFT(B14,1) -> 2 | F14: 3. Atribusi Asuransi + Pinalti
A15: Tgl Pensiun: | B15: Murabahah
A16: Gaji Saat Ini (70%): | B16: =Akseptasi!E10 -> 8134916 | C16: =MID(A16,16,3) -> 70%
A17: Manfaat pensiun (90%) | B17: =Akseptasi!C15 -> 4600000 | C17: =MID(A17,18,3) -> 90% | X17: Minimal Angs Aktif
A18: =IF(C3="3","Wajib diisi 0","Set Angsuran Maks Aktif(Khusus Prapen 10 Tahun)") -> Set Angsuran Maks Aktif(Khusus Prapen 10 Tahun) | B18: 0 | X18: =IF(B18=0,0,$B$34/12*$B$31) -> 0
A19: Angsuran BSI: | B19: 0
A20: Angsuran Selain BSI: | B20: 0
A21: Biaya Asuransi: | B21: =Akseptasi!C25 -> 39998267
A22: Rate asuransi | B22: =15000000/(100000000+15000000) -> 0.13043478
A23: Biaya Pinalti: | B23: 0
A29: OUTPUT | E29: 1 | F29: 3
A30: Maksimal Plafon: | B30: =IF(IF($C$3="1",E30,F30)>800000000,800000000,IF($C$3="1",E30,F30)) -> 495000000 | D30: plaf mak | E30: ='Rumus Plafond + Atrib PP10 (2)'!C18 -> 495000000 | F30: =IF(C14="1",'Rumus Plafond + Atrib PP3'!C20,'Rumus Plafond + Atrib PP3'!C36) -> 178000000
A31: Plafond disetujui: | B31: =IF($C$3="1",E31,F31) -> 480000000 | D31: plaf mak atrb | E31: ='Rumus Plafond + Atrib PP10 (2)'!P3 -> 480000000 | F31: ='Rumus Plafond + Atrib PP3'!P3 -> 178000000
A32: ="Angs. Saat Aktif: DSR "&TEXT(C32,"00,0%") -> Angs. Saat Aktif: DSR 70,0% | B32: =IF($C$3="1",E32,F32) -> 5694441 | C32: =IFERROR((B32+B19)/B16,"") -> 0.69999998 | E32: ='Rumus Plafond + Atrib PP10 (2)'!C6 -> 5694441 | F32: ='Rumus Plafond + Atrib PP3'!V7 -> 1604295.9
A33: =IF(C33>0.9,"DSR>90%, ubah angs aktif/tenor","Angs. Saat Pensiun: DSR "&TEXT(C33,"00,0%")) -> Angs. Saat Pensiun: DSR 89,6% | B33: =IF(IF($C$3="1",E33,F33)<0,"LUNAS <PENSIUN",IF($C$3="1",E33,F33)) -> 4121876.7 | C33: =IFERROR(B33/B17,"") -> 0.89606016 | E33: ='Rumus Plafond + Atrib PP10 (2)'!V15 -> 4121876.7 | F33: ='Rumus Plafond + Atrib PP3'!V17 -> 4092900
A34: Price Atrib Pra Pensiun: | B34: =IF($C$3="1",E34,F34) -> 0.10805531 | E34: ='Rumus Plafond + Atrib PP10 (2)'!V5 -> 0.10805531 | F34: ='Rumus Plafond + Atrib PP3'!V6 -> 0.10748062
A35: Price Atrib Pasca Pensiun: | B35: =IF($C$3="1",E35,F35) -> 0.11936993 | E35: ='Rumus Plafond + Atrib PP10 (2)'!V14 -> 0.11936993 | F35: ='Rumus Plafond + Atrib PP3'!V16 -> 0.1401
A36: Biaya Atribusi Nasabah: | B36: =IF(C14="1",0,B21+B23) -> 39998267 | D36: plaf mak atrb2 | E36: ='Rumus Plafond + Atrib PP10 (2)'!C50 -> 455000000
A37: Nominal Blokir PPTB | B37: =IF(C3="3",(C8*B32)+2*B33,"blokir sesuai MP") -> blokir sesuai MP
A38: Cash on hand PPTB | B38: =IFERROR(B31-B37,"khusus PPTB") -> khusus PPTB
A39: Simulasi Pembiayaan lain (mitraguna, griya, dll)
A40: Maksimal Plafon: | B40: {=-PV(B12/12,C8,IF(B18=0,B16*_xlfn.IFS(C4="P",70%,C4="C",80%,C4="N",50%),B18))} -> 4.4476452e+08
A41: Angsuran mitraguna | B41: =-PMT(B12/12,C8,B31) -> 6145570.7
A42: Sisa masa aktif | B42: =C8 -> 120

Sheet Rumus Plafond + Atrib PP10 (2)
B1: DATA DIKETAHUI PP10th-Non Payroll | G1: Atrib & Non-Atrib | H1: fx=C18-I3 | I1: fx=K3-J3 | J1: fx=$C$25/12*C18 | K1: fx=$C$6 | O1: Jika plafon lebih besar, maka bisa digunakan untuk menghitung angsuran | AG1: cek EPR | AH1: 0.086947336
B2: Gaji Aktif | C2: =Simulasi!B16 -> 8134916 | G2: tenor ke- | H2: pokok/plafon disetujui | I2: angsuran pokok | J2: angsuran margin | K2: total angsuran | O2: tenor ke- | P2: pokok/plafon disetujui | Q2: angsuran pokok | R2: angsuran margin | S2: total angsuran | U2: Kalkulasi Angsuran Aktif | AB2: 180 | AG2: rate net | AH2: atribusi | AI2: pokok+atrib | AJ2: atrib | AK2: margin net | AL2: Y on Pokok
B3: Manf Pens | C3: =Simulasi!B17 -> 4600000 | G3: 0 | H3: =C18 -> 495000000 | O3: 0 | P3: =IF(Simulasi!C14="1",MIN('Rumus Plafond + Atrib PP10 (2)'!C14,'Rumus Plafond + Atrib PP10 (2)'!C18),MIN('Rumus Plafond + Atrib PP10 (2)'!C14,'Rumus Plafond + Atrib PP10 (2)'!C45)) -> 480000000 | U3: Margin | V3: =P3*Simulasi!$B$12/12 -> 3700000 | Z3: 7000000 | AA3: 0.105 | AB3: 48 | AC3: =ROUNDDOWN(-PV(AA3/12,AB3,Z3,AC4,0)/10^6,0)*10^6 -> 450000000 | AH3: =SUM(AH4:AH183) -> 1.1166916e+08 | AI3: =P3+AJ3 -> 519998267 | AJ3: =$C$13 -> 39998267
B4: DBR Aktif | C4: =Simulasi!C16 -> 70% | G4: 1 | H4: =H3-I4 -> 493385184 | I4: =K4-J4 -> 1614816 | J4: =IF(G4<=$C$9,H3*$C$25/12,H3*$C$35/12) -> 4079625 | K4: =IFERROR(IF(G4<=$C$8,IF(G4<=$C$9,$C$6,$C$36),0),0) -> 5694441 | O4: 1 | P4: =P3-Q4 -> 4.7862777e+08 | Q4: =S4-R4 -> 1372228.4 | R4: =IF(O4<=$C$9,P3*$V$5/12,P3*$V$14/12) -> 4322212.6 | S4: =IFERROR(IF(O4<=$C$8,IF(O4<=$C$9,$C$6,$V$15),0),0) -> 5694441 | U4: Atrib per bln | V4: =D13 -> 222212.59 | Z4: 3590602.7 | AA4: 0.115 | AB4: =AB2-AB3 -> 132 | AC4: =-PV(AA4/12,AB4,Z4,0,0) -> 2.6828571e+08 | AF4: 1 | AG4: =$AH$1/12*AI3 -> 3767705.3 | AH4: =R4-AG4 -> 554507.25 | AI4: =AI3-Q4-AH4 -> 5.1807153e+08 | AJ4: =AJ3-AH4 -> 39443760
B5: DSR Pensiun | C5: =Simulasi!C17 -> 90% | G5: 2 | H5: =H4-I5 -> 4.9175706e+08 | I5: =K5-J5 -> 1628124.8 | J5: =IF(G5<=$C$9,H4*$C$25/12,H4*$C$35/12) -> 4066316.2 | K5: =IFERROR(IF(G5<=$C$8,IF(G5<=$C$9,$C$6,$C$36),0),0) -> 5694441 | O5: 2 | P5: =P4-Q5 -> 4.7724319e+08 | Q5: =S5-R5 -> 1384584.8 | R5: =IF(O5<=$C$9,P4*$V$5/12,P4*$V$14/12) -> 4309856.2 | S5: =IFERROR(IF(O5<=$C$8,IF(O5<=$C$9,$C$6,$V$15),0),0) -> 5694441 | U5: Rate | V5: =(V3+V4)/P3*12+IF($D$13>0,0.01,0) -> 0.10805531 | AF5: 2 | AG5: =$AH$1/12*AI4 -> 3753745 | AH5: =R5-AG5 -> 556111.24 | AI5: =AI4-Q5-AH5 -> 5.1613084e+08 | AJ5: =AJ4-AH5 -> 38887649
B6: Akseptasi Aktif | C6: =ROUNDDOWN(VLOOKUP(Simulasi!C4,Simulasi!$F$4:$I$6,4,FALSE), ) -> 5694441 | D6: fx=C2*C4 | G6: 3 | H6: =H5-I6 -> 4.9011552e+08 | I6: =K6-J6 -> 1641543.2 | J6: =IF(G6<=$C$9,H5*$C$25/12,H5*$C$35/12) -> 4052897.8 | K6: =IFERROR(IF(G6<=$C$8,IF(G6<=$C$9,$C$6,$C$36),0),0) -> 5694441 | O6: 3 | P6: =P5-Q6 -> 4.7584613e+08 | Q6: =S6-R6 -> 1397052.4 | R6: =IF(O6<=$C$9,P5*$V$5/12,P5*$V$14/12) -> 4297388.6 | S6: =IFERROR(IF(O6<=$C$8,IF(O6<=$C$9,$C$6,$V$15),0),0) -> 5694441 | AF6: 3 | AG6: =$AH$1/12*AI5 -> 3739683.4 | AH6: =R6-AG6 -> 557705.13 | AI6: =AI5-Q6-AH6 -> 5.1417608e+08 | AJ6: =AJ5-AH6 -> 38329943
B7: Akseptasi Pensiun | C7: =Simulasi!I7 -> 4140000 | D7: fx=C3*C5 | E7: sisa | G7: 4 | H7: =H6-I7 -> 4.8846044e+08 | I7: =K7-J7 -> 1655072.3 | J7: =IF(G7<=$C$9,H6*$C$25/12,H6*$C$35/12) -> 4039368.7 | K7: =IFERROR(IF(G7<=$C$8,IF(G7<=$C$9,$C$6,$C$36),0),0) -> 5694441 | O7: 4 | P7: =P6-Q7 -> 4.744365e+08 | Q7: =S7-R7 -> 1409632.3 | R7: =IF(O7<=$C$9,P6*$V$5/12,P6*$V$14/12) -> 4284808.7 | S7: =IFERROR(IF(O7<=$C$8,IF(O7<=$C$9,$C$6,$V$15),0),0) -> 5694441 | U7: Kalkulasi Angsuran Pensiun | AA7: 83 bulan | AB7: 3550000 | AC7: 321000000 | AF7: 4 | AG7: =$AH$1/12*AI6 -> 3725520 | AH7: =R7-AG7 -> 559288.63 | AI7: =AI6-Q7-AH7 -> 5.1220716e+08 | AJ7: =AJ6-AH7 -> 37770655
B8: Tenor | C8: =Simulasi!B11 -> 180 | E8: =VLOOKUP(C8,G4:H183,2,FALSE) -> -9.2666596e-08 | G8: 5 | H8: =H7-I8 -> 4.8679173e+08 | I8: =K8-J8 -> 1668712.8 | J8: =IF(G8<=$C$9,H7*$C$25/12,H7*$C$35/12) -> 4025728.2 | K8: =IFERROR(IF(G8<=$C$8,IF(G8<=$C$9,$C$6,$C$36),0),0) -> 5694441 | O8: 5 | P8: =P7-Q8 -> 4.7301418e+08 | Q8: =S8-R8 -> 1422325.5 | R8: =IF(O8<=$C$9,P7*$V$5/12,P7*$V$14/12) -> 4272115.5 | S8: =IFERROR(IF(O8<=$C$8,IF(O8<=$C$9,$C$6,$V$15),0),0) -> 5694441 | U8: Sisa OS Pensiun | V8: =VLOOKUP(C9,O4:P183,2,FALSE) -> 1.8556462e+08 | X8: 2694655.2 | AF8: 5 | AG8: =$AH$1/12*AI7 -> 3711254 | AH8: =R8-AG8 -> 560861.48 | AI8: =AI7-Q8-AH8 -> 5.1022397e+08 | AJ8: =AJ7-AH8 -> 37209793
B9: Aktif | C9: =Simulasi!C8 -> 120 | G9: 6 | H9: =H8-I9 -> 4.8510927e+08 | I9: =K9-J9 -> 1682465.8 | J9: =IF(G9<=$C$9,H8*$C$25/12,H8*$C$35/12) -> 4011975.2 | K9: =IFERROR(IF(G9<=$C$8,IF(G9<=$C$9,$C$6,$C$36),0),0) -> 5694441 | O9: 6 | P9: =P8-Q9 -> 4.7157904e+08 | Q9: =S9-R9 -> 1435133 | R9: =IF(O9<=$C$9,P8*$V$5/12,P8*$V$14/12) -> 4259308 | S9: =IFERROR(IF(O9<=$C$8,IF(O9<=$C$9,$C$6,$V$15),0),0) -> 5694441 | U9: Atribusi per bulan | V9: =C13/C8 -> 222212.59 | X9: =PV(V10/12,V11,-X8,0,0) -> 1.2536837e+08 | AF9: 6 | AG9: =$AH$1/12*AI8 -> 3696884.6 | AH9: =R9-AG9 -> 562423.39 | AI9: =AI8-Q9-AH9 -> 5.0822641e+08 | AJ9: =AJ8-AH9 -> 36647370
B10: Pensiun | C10: =C8-C9 -> 60 | D10: jk atrib | G10: 7 | H10: =H9-I10 -> 4.8341293e+08 | I10: =K10-J10 -> 1696332.1 | J10: =IF(G10<=$C$9,H9*$C$25/12,H9*$C$35/12) -> 3998108.9 | K10: =IFERROR(IF(G10<=$C$8,IF(G10<=$C$9,$C$6,$C$36),0),0) -> 5694441 | O10: 7 | P10: =P9-Q10 -> 4.7013099e+08 | Q10: =S10-R10 -> 1448055.8 | R10: =IF(O10<=$C$9,P9*$V$5/12,P9*$V$14/12) -> 4246385.2 | S10: =IFERROR(IF(O10<=$C$8,IF(O10<=$C$9,$C$6,$V$15),0),0) -> 5694441 | U10: Rate Awal | V10: =Simulasi!$B$13 -> 0.105 | AF10: 7 | AG10: =$AH$1/12*AI9 -> 3682411.1 | AH10: =R10-AG10 -> 563974.1 | AI10: =AI9-Q10-AH10 -> 5.0621438e+08 | AJ10: =AJ9-AH10 -> 36083396
B11: rate aktif | C11: =Simulasi!B12+IF($D$13>0,0.001,0) -> 0.0935 | D11: ini udah oke, di NOS di plus 0,001 utk aktif | G11: 8 | H11: =H10-I11 -> 4.8170262e+08 | I11: =K11-J11 -> 1710312.7 | J11: =IF(G11<=$C$9,H10*$C$25/12,H10*$C$35/12) -> 3984128.3 | K11: =IFERROR(IF(G11<=$C$8,IF(G11<=$C$9,$C$6,$C$36),0),0) -> 5694441 | O11: 8 | P11: =P10-Q11 -> 4.6866989e+08 | Q11: =S11-R11 -> 1461095 | R11: =IF(O11<=$C$9,P10*$V$5/12,P10*$V$14/12) -> 4233346 | S11: =IFERROR(IF(O11<=$C$8,IF(O11<=$C$9,$C$6,$V$15),0),0) -> 5694441 | U11: Periode pensiun | V11: =C10 -> 60 | AF11: 8 | AG11: =$AH$1/12*AI10 -> 3667832.7 | AH11: =R11-AG11 -> 565513.31 | AI11: =AI10-Q11-AH11 -> 5.0418778e+08 | AJ11: =AJ10-AH11 -> 35517882
B12: rate pensiun | C12: =Simulasi!B13+IF($D$13>0,0.01,0) -> 0.115 | D12: ini udah oke, di NOS di plus 0,01 utk pensiun | G12: 9 | H12: =H11-I12 -> 4.7997821e+08 | I12: =K12-J12 -> 1724408.6 | J12: =IF(G12<=$C$9,H11*$C$25/12,H11*$C$35/12) -> 3970032.4 | K12: =IFERROR(IF(G12<=$C$8,IF(G12<=$C$9,$C$6,$C$36),0),0) -> 5694441 | O12: 9 | P12: =P11-Q12 -> 4.6719564e+08 | Q12: =S12-R12 -> 1474251.6 | R12: =IF(O12<=$C$9,P11*$V$5/12,P11*$V$14/12) -> 4220189.4 | S12: =IFERROR(IF(O12<=$C$8,IF(O12<=$C$9,$C$6,$V$15),0),0) -> 5694441 | U12: Angsuran | V12: =V10/12*V8 -> 1623690.5 | AF12: 9 | AG12: =$AH$1/12*AI11 -> 3653148.7 | AH12: =R12-AG12 -> 567040.73 | AI12: =AI11-Q12-AH12 -> 5.0214648e+08 | AJ12: =AJ11-AH12 -> 34950842
B13: Nominal Atribusi | C13: =IF(Simulasi!$C$14="2",Simulasi!B21,0) -> 39998267 | D13: =C13/C8 -> 222212.59 | G13: 10 | H13: =H12-I13 -> 4.7823959e+08 | I13: =K13-J13 -> 1738620.6 | J13: =IF(G13<=$C$9,H12*$C$25/12,H12*$C$35/12) -> 3955820.4 | K13: =IFERROR(IF(G13<=$C$8,IF(G13<=$C$9,$C$6,$C$36),0),0) -> 5694441 | O13: 10 | P13: =P12-Q13 -> 4.6570811e+08 | Q13: =S13-R13 -> 1487526.7 | R13: =IF(O13<=$C$9,P12*$V$5/12,P12*$V$14/12) -> 4206914.3 | S13: =IFERROR(IF(O13<=$C$8,IF(O13<=$C$9,$C$6,$V$15),0),0) -> 5694441 | U13: Final | V13: =V9+V12 -> 1845903 | AF13: 10 | AG13: =$AH$1/12*AI12 -> 3638358.3 | AH13: =R13-AG13 -> 568556.08 | AI13: =AI12-Q13-AH13 -> 5.000904e+08 | AJ13: =AJ12-AH13 -> 34382286
B14: Plafon Pengajuan | C14: =Simulasi!B10 -> 480000000 | G14: 11 | H14: =H13-I14 -> 4.7648664e+08 | I14: =K14-J14 -> 1752949.7 | J14: =IF(G14<=$C$9,H13*$C$25/12,H13*$C$35/12) -> 3941491.3 | K14: =IFERROR(IF(G14<=$C$8,IF(G14<=$C$9,$C$6,$C$36),0),0) -> 5694441 | O14: 11 | P14: =P13-Q14 -> 4.6420719e+08 | Q14: =S14-R14 -> 1500921.3 | R14: =IF(O14<=$C$9,P13*$V$5/12,P13*$V$14/12) -> 4193519.7 | S14: =IFERROR(IF(O14<=$C$8,IF(O14<=$C$9,$C$6,$V$15),0),0) -> 5694441 | U14: Rate Atrib | V14: =V13/V8*12+IF($D$13>0,0,0) -> 0.11936993 | AF14: 11 | AG14: =$AH$1/12*AI13 -> 3623460.7 | AH14: =R14-AG14 -> 570059.06 | AI14: =AI13-Q14-AH14 -> 4.9801942e+08 | AJ14: =AJ13-AH14 -> 33812227
A15: 1. | B15: SKEMA NO ATRIB Plafon MaksImal dihitung dengan menghitung plafon maksimal saat pensiun dan plafond maksimal saat aktif secara bersamaan | G15: 12 | H15: =H14-I15 -> 4.7471924e+08 | I15: =K15-J15 -> 1767396.9 | J15: =IF(G15<=$C$9,H14*$C$25/12,H14*$C$35/12) -> 3927044.1 | K15: =IFERROR(IF(G15<=$C$8,IF(G15<=$C$9,$C$6,$C$36),0),0) -> 5694441 | O15: 12 | P15: =P14-Q15 -> 4.6269276e+08 | Q15: =S15-R15 -> 1514436.5 | R15: =IF(O15<=$C$9,P14*$V$5/12,P14*$V$14/12) -> 4180004.5 | S15: =IFERROR(IF(O15<=$C$8,IF(O15<=$C$9,$C$6,$V$15),0),0) -> 5694441 | U15: Angsuran Final Pen | V15: =PMT(V14/12,V11,-V8,0,0) -> 4121876.7 | AF15: 12 | AG15: =$AH$1/12*AI14 -> 3608455.2 | AH15: =R15-AG15 -> 571549.37 | AI15: =AI14-Q15-AH15 -> 4.9593343e+08 | AJ15: =AJ14-AH15 -> 33240677
G16: 13 | H16: =H15-I16 -> 4.7293728e+08 | I16: =K16-J16 -> 1781963.2 | J16: =IF(G16<=$C$9,H15*$C$25/12,H15*$C$35/12) -> 3912477.8 | K16: =IFERROR(IF(G16<=$C$8,IF(G16<=$C$9,$C$6,$C$36),0),0) -> 5694441 | O16: 13 | P16: =P15-Q16 -> 4.6116468e+08 | Q16: =S16-R16 -> 1528073.4 | R16: =IF(O16<=$C$9,P15*$V$5/12,P15*$V$14/12) -> 4166367.6 | S16: =IFERROR(IF(O16<=$C$8,IF(O16<=$C$9,$C$6,$V$15),0),0) -> 5694441 | AF16: 13 | AG16: =$AH$1/12*AI15 -> 3593340.9 | AH16: =R16-AG16 -> 573026.71 | AI16: =AI15-Q16-AH16 -> 4.9383233e+08 | AJ16: =AJ15-AH16 -> 32667651
B17: Plafon Maksimal Pensiun | C17: =-PV(C12/12,C10,C7-D13, ,0) -> 1.7814111e+08 | D17: fx=-PV(C12/12;C10;C7;;0) | G17: 14 | H17: =H16-I17 -> 4.7114063e+08 | I17: =K17-J17 -> 1796649.6 | J17: =IF(G17<=$C$9,H16*$C$25/12,H16*$C$35/12) -> 3897791.4 | K17: =IFERROR(IF(G17<=$C$8,IF(G17<=$C$9,$C$6,$C$36),0),0) -> 5694441 | O17: 14 | P17: =P16-Q17 -> 4.5962285e+08 | Q17: =S17-R17 -> 1541833.1 | R17: =IF(O17<=$C$9,P16*$V$5/12,P16*$V$14/12) -> 4152607.9 | S17: =IFERROR(IF(O17<=$C$8,IF(O17<=$C$9,$C$6,$V$15),0),0) -> 5694441 | U17: Cek sisa OS | V17: =VLOOKUP(C8,O4:P183,2,FALSE) -> -7.962808e-08 | AF17: 14 | AG17: =$AH$1/12*AI16 -> 3578117.2 | AH17: =R17-AG17 -> 574490.76 | AI17: =AI16-Q17-AH17 -> 4.9171601e+08 | AJ17: =AJ16-AH17 -> 32093160
B18: Plafon Aktif | C18: =(ROUNDDOWN(-PV(C11/12,C9,C6-D13,C17,0)/10^6, )*10^6) -> 495000000 | D18: fx=ROUNDDOWN(-PV(C11/12;C9;C6;C17;0)/10^6;)*10^6 | G18: 15 | H18: =H17-I18 -> 4.6932917e+08 | I18: =K18-J18 -> 1811457 | J18: =IF(G18<=$C$9,H17*$C$25/12,H17*$C$35/12) -> 3882984 | K18: =IFERROR(IF(G18<=$C$8,IF(G18<=$C$9,$C$6,$C$36),0),0) -> 5694441 | O18: 15 | P18: =P17-Q18 -> 4.5806713e+08 | Q18: =S18-R18 -> 1555716.7 | R18: =IF(O18<=$C$9,P17*$V$5/12,P17*$V$14/12) -> 4138724.3 | S18: =IFERROR(IF(O18<=$C$8,IF(O18<=$C$9,$C$6,$V$15),0),0) -> 5694441 | AF18: 15 | AG18: =$AH$1/12*AI17 -> 3562783.1 | AH18: =R18-AG18 -> 575941.21 | AI18: =AI17-Q18-AH18 -> 4.8958435e+08 | AJ18: =AJ17-AH18 -> 31517219
G19: 16 | H19: =H18-I19 -> 4.6750279e+08 | I19: =K19-J19 -> 1826386.4 | J19: =IF(G19<=$C$9,H18*$C$25/12,H18*$C$35/12) -> 3868054.6 | K19: =IFERROR(IF(G19<=$C$8,IF(G19<=$C$9,$C$6,$C$36),0),0) -> 5694441 | O19: 16 | P19: =P18-Q19 -> 4.5649741e+08 | Q19: =S19-R19 -> 1569725.3 | R19: =IF(O19<=$C$9,P18*$V$5/12,P18*$V$14/12) -> 4124715.7 | S19: =IFERROR(IF(O19<=$C$8,IF(O19<=$C$9,$C$6,$V$15),0),0) -> 5694441 | AF19: 16 | AG19: =$AH$1/12*AI18 -> 3547337.9 | AH19: =R19-AG19 -> 577377.76 | AI19: =AI18-Q19-AH19 -> 4.8743725e+08 | AJ19: =AJ18-AH19 -> 30939841
A20: 2 | B20: Mencari Rate Atribusi Aktif | G20: 17 | H20: =H19-I20 -> 4.6566135e+08 | I20: =K20-J20 -> 1841438.9 | J20: =IF(G20<=$C$9,H19*$C$25/12,H19*$C$35/12) -> 3853002.1 | K20: =IFERROR(IF(G20<=$C$8,IF(G20<=$C$9,$C$6,$C$36),0),0) -> 5694441 | O20: 17 | P20: =P19-Q20 -> 4.5491355e+08 | Q20: =S20-R20 -> 1583860.1 | R20: =IF(O20<=$C$9,P19*$V$5/12,P19*$V$14/12) -> 4110580.9 | S20: =IFERROR(IF(O20<=$C$8,IF(O20<=$C$9,$C$6,$V$15),0),0) -> 5694441 | U20: Cfm | AF20: 17 | AG20: =$AH$1/12*AI19 -> 3531780.9 | AH20: =R20-AG20 -> 578800.07 | AI20: =AI19-Q20-AH20 -> 4.8527459e+08 | AJ20: =AJ19-AH20 -> 30361041
B21: Perhitungan dengan menggunakan margin + biaya atrib per bulan | G21: 18 | H21: =H20-I21 -> 4.6380473e+08 | I21: =K21-J21 -> 1856615.4 | J21: =IF(G21<=$C$9,H20*$C$25/12,H20*$C$35/12) -> 3837825.6 | K21: =IFERROR(IF(G21<=$C$8,IF(G21<=$C$9,$C$6,$C$36),0),0) -> 5694441 | O21: 18 | P21: =P20-Q21 -> 4.5331543e+08 | Q21: =S21-R21 -> 1598122.1 | R21: =IF(O21<=$C$9,P20*$V$5/12,P20*$V$14/12) -> 4096318.9 | S21: =IFERROR(IF(O21<=$C$8,IF(O21<=$C$9,$C$6,$V$15),0),0) -> 5694441 | U21: Penambahan atr aktif | V21: =1% -> 0.01 | AF21: 18 | AG21: =$AH$1/12*AI20 -> 3516111.1 | AH21: =R21-AG21 -> 580207.82 | AI21: =AI20-Q21-AH21 -> 4.8309626e+08 | AJ21: =AJ20-AH21 -> 29780833
B22: Rate Margin | C22: =(C11)/12*C18 -> 3856875 | D22: fx=C11/12*C18 | G22: 19 | H22: =H21-I22 -> 4.6193282e+08 | I22: =K22-J22 -> 1871917 | J22: =IF(G22<=$C$9,H21*$C$25/12,H21*$C$35/12) -> 3822524 | K22: =IFERROR(IF(G22<=$C$8,IF(G22<=$C$9,$C$6,$C$36),0),0) -> 5694441 | O22: 19 | P22: =P21-Q22 -> 4.5170291e+08 | Q22: =S22-R22 -> 1612512.6 | R22: =IF(O22<=$C$9,P21*$V$5/12,P21*$V$14/12) -> 4081928.4 | S22: =IFERROR(IF(O22<=$C$8,IF(O22<=$C$9,$C$6,$V$15),0),0) -> 5694441 | U22: penambahan atr pensiun | V22: 0 | AF22: 19 | AG22: =$AH$1/12*AI21 -> 3500327.7 | AH22: =R22-AG22 -> 581600.69 | AI22: =AI21-Q22-AH22 -> 4.8090215e+08 | AJ22: =AJ21-AH22 -> 29199232
B23: Atribusi per Bulan | C23: =C13/C8 -> 222212.59 | D23: fx=C13/C8 | G23: 20 | H23: =H22-I23 -> 4.6004547e+08 | I23: =K23-J23 -> 1887344.7 | J23: =IF(G23<=$C$9,H22*$C$25/12,H22*$C$35/12) -> 3807096.3 | K23: =IFERROR(IF(G23<=$C$8,IF(G23<=$C$9,$C$6,$C$36),0),0) -> 5694441 | O23: 20 | P23: =P22-Q23 -> 4.5007588e+08 | Q23: =S23-R23 -> 1627032.6 | R23: =IF(O23<=$C$9,P22*$V$5/12,P22*$V$14/12) -> 4067408.4 | S23: =IFERROR(IF(O23<=$C$8,IF(O23<=$C$9,$C$6,$V$15),0),0) -> 5694441 | AF23: 20 | AG23: =$AH$1/12*AI22 -> 3484430 | AH23: =R23-AG23 -> 582978.33 | AI23: =AI22-Q23-AH23 -> 4.7869213e+08 | AJ23: =AJ22-AH23 -> 28616254
B24: Margin + Atribusi | C24: =C22+C23 -> 4079087.6 | D24: fx=C22+C23 | G24: 21 | H24: =H23-I24 -> 4.5814257e+08 | I24: =K24-J24 -> 1902899.6 | J24: =IF(G24<=$C$9,H23*$C$25/12,H23*$C$35/12) -> 3791541.4 | K24: =IFERROR(IF(G24<=$C$8,IF(G24<=$C$9,$C$6,$C$36),0),0) -> 5694441 | O24: 21 | P24: =P23-Q24 -> 4.484342e+08 | Q24: =S24-R24 -> 1641683.4 | R24: =IF(O24<=$C$9,P23*$V$5/12,P23*$V$14/12) -> 4052757.6 | S24: =IFERROR(IF(O24<=$C$8,IF(O24<=$C$9,$C$6,$V$15),0),0) -> 5694441 | AF24: 21 | AG24: =$AH$1/12*AI23 -> 3468417.2 | AH24: =R24-AG24 -> 584340.42 | AI24: =AI23-Q24-AH24 -> 4.7646611e+08 | AJ24: =AJ23-AH24 -> 28031913
B25: Rate Atrib Aktif | C25: =ROUNDUP(C24/C18*12,4) -> 0.0989 | D25: fx=ROUNDUP(C24/C18*12;4) | G25: 22 | H25: =H24-I25 -> 4.5622399e+08 | I25: =K25-J25 -> 1918582.6 | J25: =IF(G25<=$C$9,H24*$C$25/12,H24*$C$35/12) -> 3775858.4 | K25: =IFERROR(IF(G25<=$C$8,IF(G25<=$C$9,$C$6,$C$36),0),0) -> 5694441 | O25: 22 | P25: =P24-Q25 -> 4.4677773e+08 | Q25: =S25-R25 -> 1656466.1 | R25: =IF(O25<=$C$9,P24*$V$5/12,P24*$V$14/12) -> 4037974.9 | S25: =IFERROR(IF(O25<=$C$8,IF(O25<=$C$9,$C$6,$V$15),0),0) -> 5694441 | AF25: 22 | AG25: =$AH$1/12*AI24 -> 3452288.3 | AH25: =R25-AG25 -> 585686.6 | AI25: =AI24-Q25-AH25 -> 4.7422396e+08 | AJ25: =AJ24-AH25 -> 27446227
G26: 23 | H26: =H25-I26 -> 4.542896e+08 | I26: =K26-J26 -> 1934394.9 | J26: =IF(G26<=$C$9,H25*$C$25/12,H25*$C$35/12) -> 3760046.1 | K26: =IFERROR(IF(G26<=$C$8,IF(G26<=$C$9,$C$6,$C$36),0),0) -> 5694441 | O26: 23 | P26: =P25-Q26 -> 4.4510635e+08 | Q26: =S26-R26 -> 1671382 | R26: =IF(O26<=$C$9,P25*$V$5/12,P25*$V$14/12) -> 4023059 | S26: =IFERROR(IF(O26<=$C$8,IF(O26<=$C$9,$C$6,$V$15),0),0) -> 5694441 | AF26: 23 | AG26: =$AH$1/12*AI25 -> 3436042.5 | AH26: =R26-AG26 -> 587016.54 | AI26: =AI25-Q26-AH26 -> 4.7196556e+08 | AJ26: =AJ25-AH26 -> 26859210
A27: 3 | B27: Buat jadwal angsuran terlebih dulu untuk mengetahui OS saat memasuki pensiun --> | G27: 24 | H27: =H26-I27 -> 4.5233926e+08 | I27: =K27-J27 -> 1950337.6 | J27: =IF(G27<=$C$9,H26*$C$25/12,H26*$C$35/12) -> 3744103.4 | K27: =IFERROR(IF(G27<=$C$8,IF(G27<=$C$9,$C$6,$C$36),0),0) -> 5694441 | O27: 24 | P27: =P26-Q27 -> 4.4341992e+08 | Q27: =S27-R27 -> 1686432.1 | R27: =IF(O27<=$C$9,P26*$V$5/12,P26*$V$14/12) -> 4008008.9 | S27: =IFERROR(IF(O27<=$C$8,IF(O27<=$C$9,$C$6,$V$15),0),0) -> 5694441 | AF27: 24 | AG27: =$AH$1/12*AI26 -> 3419679 | AH27: =R27-AG27 -> 588329.88 | AI27: =AI26-Q27-AH27 -> 4.696908e+08 | AJ27: =AJ26-AH27 -> 26270880
B28: Sisa OS saat pensiun | C28: =VLOOKUP(C9,G:H,2,FALSE) -> 1.6628891e+08 | D28: fx=H57 | G28: 25 | H28: =H27-I28 -> 4.5037285e+08 | I28: =K28-J28 -> 1966411.6 | J28: =IF(G28<=$C$9,H27*$C$25/12,H27*$C$35/12) -> 3728029.4 | K28: =IFERROR(IF(G28<=$C$8,IF(G28<=$C$9,$C$6,$C$36),0),0) -> 5694441 | O28: 25 | P28: =P27-Q28 -> 4.417183e+08 | Q28: =S28-R28 -> 1701617.8 | R28: =IF(O28<=$C$9,P27*$V$5/12,P27*$V$14/12) -> 3992823.2 | S28: =IFERROR(IF(O28<=$C$8,IF(O28<=$C$9,$C$6,$V$15),0),0) -> 5694441 | AF28: 25 | AG28: =$AH$1/12*AI27 -> 3403197 | AH28: =R28-AG28 -> 589626.25 | AI28: =AI27-Q28-AH28 -> 4.6739955e+08 | AJ28: =AJ27-AH28 -> 25681254
G29: 26 | H29: =H28-I29 -> 4.4839023e+08 | I29: =K29-J29 -> 1982618.1 | J29: =IF(G29<=$C$9,H28*$C$25/12,H28*$C$35/12) -> 3711822.9 | K29: =IFERROR(IF(G29<=$C$8,IF(G29<=$C$9,$C$6,$C$36),0),0) -> 5694441 | O29: 26 | P29: =P28-Q29 -> 4.4000136e+08 | Q29: =S29-R29 -> 1716940.2 | R29: =IF(O29<=$C$9,P28*$V$5/12,P28*$V$14/12) -> 3977500.8 | S29: =IFERROR(IF(O29<=$C$8,IF(O29<=$C$9,$C$6,$V$15),0),0) -> 5694441 | AF29: 26 | AG29: =$AH$1/12*AI28 -> 3386595.5 | AH29: =R29-AG29 -> 590905.31 | AI29: =AI28-Q29-AH29 -> 4.6509171e+08 | AJ29: =AJ28-AH29 -> 25090349
A30: 4 | B30: Mencari Rate Atribusi Pensiun | G30: 27 | H30: =H29-I30 -> 4.4639127e+08 | I30: =K30-J30 -> 1998958.2 | J30: =IF(G30<=$C$9,H29*$C$25/12,H29*$C$35/12) -> 3695482.8 | K30: =IFERROR(IF(G30<=$C$8,IF(G30<=$C$9,$C$6,$C$36),0),0) -> 5694441 | O30: 27 | P30: =P29-Q30 -> 4.3826896e+08 | Q30: =S30-R30 -> 1732400.5 | R30: =IF(O30<=$C$9,P29*$V$5/12,P29*$V$14/12) -> 3962040.5 | S30: =IFERROR(IF(O30<=$C$8,IF(O30<=$C$9,$C$6,$V$15),0),0) -> 5694441 | AF30: 27 | AG30: =$AH$1/12*AI29 -> 3369873.8 | AH30: =R30-AG30 -> 592166.69 | AI30: =AI29-Q30-AH30 -> 4.6276714e+08 | AJ30: =AJ29-AH30 -> 24498182
B31: Perhitungan dengan menggunakan margin dan atribusi per bulan | G31: 28 | H31: =H30-I31 -> 4.4437584e+08 | I31: =K31-J31 -> 2015433 | J31: =IF(G31<=$C$9,H30*$C$25/12,H30*$C$35/12) -> 3679008 | K31: =IFERROR(IF(G31<=$C$8,IF(G31<=$C$9,$C$6,$C$36),0),0) -> 5694441 | O31: 28 | P31: =P30-Q31 -> 4.3652096e+08 | Q31: =S31-R31 -> 1748000.1 | R31: =IF(O31<=$C$9,P30*$V$5/12,P30*$V$14/12) -> 3946440.9 | S31: =IFERROR(IF(O31<=$C$8,IF(O31<=$C$9,$C$6,$V$15),0),0) -> 5694441 | AF31: 28 | AG31: =$AH$1/12*AI30 -> 3353030.9 | AH31: =R31-AG31 -> 593410.01 | AI31: =AI30-Q31-AH31 -> 4.6042573e+08 | AJ31: =AJ30-AH31 -> 23904772
B32: Rate Margin 10,5% | C32: =(C12)/12*C28 -> 1593602.1 | D32: fx=C12/12*C28 | G32: 29 | H32: =H31-I32 -> 4.4234379e+08 | I32: =K32-J32 -> 2032043.5 | J32: =IF(G32<=$C$9,H31*$C$25/12,H31*$C$35/12) -> 3662397.5 | K32: =IFERROR(IF(G32<=$C$8,IF(G32<=$C$9,$C$6,$C$36),0),0) -> 5694441 | O32: 29 | P32: =P31-Q32 -> 4.3475722e+08 | Q32: =S32-R32 -> 1763740.2 | R32: =IF(O32<=$C$9,P31*$V$5/12,P31*$V$14/12) -> 3930700.8 | S32: =IFERROR(IF(O32<=$C$8,IF(O32<=$C$9,$C$6,$V$15),0),0) -> 5694441 | AF32: 29 | AG32: =$AH$1/12*AI31 -> 3336065.9 | AH32: =R32-AG32 -> 594634.9 | AI32: =AI31-Q32-AH32 -> 4.5806736e+08 | AJ32: =AJ31-AH32 -> 23310137
B33: Atribusi per Bulan | C33: =C13/C8 -> 222212.59 | D33: fx=C13/C8 | G33: 30 | H33: =H32-I33 -> 4.40295e+08 | I33: =K33-J33 -> 2048790.9 | J33: =IF(G33<=$C$9,H32*$C$25/12,H32*$C$35/12) -> 3645650.1 | K33: =IFERROR(IF(G33<=$C$8,IF(G33<=$C$9,$C$6,$C$36),0),0) -> 5694441 | O33: 30 | P33: =P32-Q33 -> 4.329776e+08 | Q33: =S33-R33 -> 1779622 | R33: =IF(O33<=$C$9,P32*$V$5/12,P32*$V$14/12) -> 3914819 | S33: =IFERROR(IF(O33<=$C$8,IF(O33<=$C$9,$C$6,$V$15),0),0) -> 5694441 | AF33: 30 | AG33: =$AH$1/12*AI32 -> 3318978 | AH33: =R33-AG33 -> 595840.98 | AI33: =AI32-Q33-AH33 -> 4.5569189e+08 | AJ33: =AJ32-AH33 -> 22714296
B34: Margin + Atribusi | C34: =C32+C33 -> 1815814.7 | D34: fx=C32+C33 | G34: 31 | H34: =H33-I34 -> 4.3822933e+08 | I34: =K34-J34 -> 2065676.4 | J34: =IF(G34<=$C$9,H33*$C$25/12,H33*$C$35/12) -> 3628764.6 | K34: =IFERROR(IF(G34<=$C$8,IF(G34<=$C$9,$C$6,$C$36),0),0) -> 5694441 | O34: 31 | P34: =P33-Q34 -> 4.3118195e+08 | Q34: =S34-R34 -> 1795646.8 | R34: =IF(O34<=$C$9,P33*$V$5/12,P33*$V$14/12) -> 3898794.2 | S34: =IFERROR(IF(O34<=$C$8,IF(O34<=$C$9,$C$6,$V$15),0),0) -> 5694441 | AF34: 31 | AG34: =$AH$1/12*AI33 -> 3301766.4 | AH34: =R34-AG34 -> 597027.86 | AI34: =AI33-Q34-AH34 -> 4.5329922e+08 | AJ34: =AJ33-AH34 -> 22117268
B35: Rate Atribusi Pensiun | C35: =ROUNDUP(C34/C28*12,4) -> 0.1311 | D35: fx=ROUNDUP(C34/C28*12;4) | G35: 32 | H35: =H34-I35 -> 4.3614662e+08 | I35: =K35-J35 -> 2082701 | J35: =IF(G35<=$C$9,H34*$C$25/12,H34*$C$35/12) -> 3611740 | K35: =IFERROR(IF(G35<=$C$8,IF(G35<=$C$9,$C$6,$C$36),0),0) -> 5694441 | O35: 32 | P35: =P34-Q35 -> 4.2937013e+08 | Q35: =S35-R35 -> 1811815.9 | R35: =IF(O35<=$C$9,P34*$V$5/12,P34*$V$14/12) -> 3882625.1 | S35: =IFERROR(IF(O35<=$C$8,IF(O35<=$C$9,$C$6,$V$15),0),0) -> 5694441 | AF35: 32 | AG35: =$AH$1/12*AI34 -> 3284430 | AH35: =R35-AG35 -> 598195.15 | AI35: =AI34-Q35-AH35 -> 4.5088921e+08 | AJ35: =AJ34-AH35 -> 21519073
B36: Angsuran Pensiun | C36: =PMT(C35/12,C10,-C28,0,0) -> 3792954.1 | D36: fx=PMT(C35/12;C10;-C28;0;0) | G36: 33 | H36: =H35-I36 -> 4.3404676e+08 | I36: =K36-J36 -> 2099865.9 | J36: =IF(G36<=$C$9,H35*$C$25/12,H35*$C$35/12) -> 3594575.1 | K36: =IFERROR(IF(G36<=$C$8,IF(G36<=$C$9,$C$6,$C$36),0),0) -> 5694441 | O36: 33 | P36: =P35-Q36 -> 4.27542e+08 | Q36: =S36-R36 -> 1828130.6 | R36: =IF(O36<=$C$9,P35*$V$5/12,P35*$V$14/12) -> 3866310.4 | S36: =IFERROR(IF(O36<=$C$8,IF(O36<=$C$9,$C$6,$V$15),0),0) -> 5694441 | AF36: 33 | AG36: =$AH$1/12*AI35 -> 3266968 | AH36: =R36-AG36 -> 599342.46 | AI36: =AI35-Q36-AH36 -> 4.4846173e+08 | AJ36: =AJ35-AH36 -> 20919731
C37: **angsuran pensiun melebihi 90% akseptasi Manfaat Pensiun, sehingga harus mengihitung ulang plafond aktif dan pensiun untuk skenario atribusi | G37: 34 | H37: =H36-I37 -> 4.3192959e+08 | I37: =K37-J37 -> 2117172.3 | J37: =IF(G37<=$C$9,H36*$C$25/12,H36*$C$35/12) -> 3577268.7 | K37: =IFERROR(IF(G37<=$C$8,IF(G37<=$C$9,$C$6,$C$36),0),0) -> 5694441 | O37: 34 | P37: =P36-Q37 -> 4.2569741e+08 | Q37: =S37-R37 -> 1844592.2 | R37: =IF(O37<=$C$9,P36*$V$5/12,P36*$V$14/12) -> 3849848.8 | S37: =IFERROR(IF(O37<=$C$8,IF(O37<=$C$9,$C$6,$V$15),0),0) -> 5694441 | AF37: 34 | AG37: =$AH$1/12*AI36 -> 3249379.4 | AH37: =R37-AG37 -> 600469.38 | AI37: =AI36-Q37-AH37 -> 4.4601667e+08 | AJ37: =AJ36-AH37 -> 20319261
G38: 35 | H38: =H37-I38 -> 4.2979497e+08 | I38: =K38-J38 -> 2134621.3 | J38: =IF(G38<=$C$9,H37*$C$25/12,H37*$C$35/12) -> 3559819.7 | K38: =IFERROR(IF(G38<=$C$8,IF(G38<=$C$9,$C$6,$C$36),0),0) -> 5694441 | O38: 35 | P38: =P37-Q38 -> 4.2383621e+08 | Q38: =S38-R38 -> 1861202 | R38: =IF(O38<=$C$9,P37*$V$5/12,P37*$V$14/12) -> 3833239 | S38: =IFERROR(IF(O38<=$C$8,IF(O38<=$C$9,$C$6,$V$15),0),0) -> 5694441 | AF38: 35 | AG38: =$AH$1/12*AI37 -> 3231663.5 | AH38: =R38-AG38 -> 601575.52 | AI38: =AI37-Q38-AH38 -> 4.4355389e+08 | AJ38: =AJ37-AH38 -> 19717686
A39: 5 | B39: SKEMA ATRIB Menghitung ulang menggunakan rate atribusi aktif dan pensiun pada langkah (2) dan (4) kemudian mencari plafond maksimal aktif dan pensiun menggunakan skenario Atribusi | G39: 36 | H39: =H38-I39 -> 4.2764275e+08 | I39: =K39-J39 -> 2152214.2 | J39: =IF(G39<=$C$9,H38*$C$25/12,H38*$C$35/12) -> 3542226.8 | K39: =IFERROR(IF(G39<=$C$8,IF(G39<=$C$9,$C$6,$C$36),0),0) -> 5694441 | O39: 36 | P39: =P38-Q39 -> 4.2195825e+08 | Q39: =S39-R39 -> 1877961.4 | R39: =IF(O39<=$C$9,P38*$V$5/12,P38*$V$14/12) -> 3816479.6 | S39: =IFERROR(IF(O39<=$C$8,IF(O39<=$C$9,$C$6,$V$15),0),0) -> 5694441 | AF39: 36 | AG39: =$AH$1/12*AI38 -> 3213819.1 | AH39: =R39-AG39 -> 602660.45 | AI39: =AI38-Q39-AH39 -> 4.4107327e+08 | AJ39: =AJ38-AH39 -> 19115025
G40: 37 | H40: =H39-I40 -> 4.254728e+08 | I40: =K40-J40 -> 2169952 | J40: =IF(G40<=$C$9,H39*$C$25/12,H39*$C$35/12) -> 3524489 | K40: =IFERROR(IF(G40<=$C$8,IF(G40<=$C$9,$C$6,$C$36),0),0) -> 5694441 | O40: 37 | P40: =P39-Q40 -> 4.2006338e+08 | Q40: =S40-R40 -> 1894871.7 | R40: =IF(O40<=$C$9,P39*$V$5/12,P39*$V$14/12) -> 3799569.3 | S40: =IFERROR(IF(O40<=$C$8,IF(O40<=$C$9,$C$6,$V$15),0),0) -> 5694441 | AF40: 37 | AG40: =$AH$1/12*AI39 -> 3195845.5 | AH40: =R40-AG40 -> 603723.76 | AI40: =AI39-Q40-AH40 -> 4.3857468e+08 | AJ40: =AJ39-AH40 -> 18511302
G41: 38 | H41: =H40-I41 -> 4.2328496e+08 | I41: =K41-J41 -> 2187836 | J41: =IF(G41<=$C$9,H40*$C$25/12,H40*$C$35/12) -> 3506605 | K41: =IFERROR(IF(G41<=$C$8,IF(G41<=$C$9,$C$6,$C$36),0),0) -> 5694441 | O41: 38 | P41: =P40-Q41 -> 4.1815144e+08 | Q41: =S41-R41 -> 1911934.3 | R41: =IF(O41<=$C$9,P40*$V$5/12,P40*$V$14/12) -> 3782506.7 | S41: =IFERROR(IF(O41<=$C$8,IF(O41<=$C$9,$C$6,$V$15),0),0) -> 5694441 | AF41: 38 | AG41: =$AH$1/12*AI40 -> 3177741.7 | AH41: =R41-AG41 -> 604765.03 | AI41: =AI40-Q41-AH41 -> 4.3605798e+08 | AJ41: =AJ40-AH41 -> 17906537
B42: Rate Atrib Aktif | C42: =C25+IF($D$13>0,0.01,0) -> 0.1089 | D42: fx=C25 | G42: 39 | H42: =H41-I42 -> 4.210791e+08 | I42: =K42-J42 -> 2205867.4 | J42: =IF(G42<=$C$9,H41*$C$25/12,H41*$C$35/12) -> 3488573.6 | K42: =IFERROR(IF(G42<=$C$8,IF(G42<=$C$9,$C$6,$C$36),0),0) -> 5694441 | O42: 39 | P42: =P41-Q42 -> 4.1622229e+08 | Q42: =S42-R42 -> 1929150.5 | R42: =IF(O42<=$C$9,P41*$V$5/12,P41*$V$14/12) -> 3765290.5 | S42: =IFERROR(IF(O42<=$C$8,IF(O42<=$C$9,$C$6,$V$15),0),0) -> 5694441 | AF42: 39 | AG42: =$AH$1/12*AI41 -> 3159506.6 | AH42: =R42-AG42 -> 605783.84 | AI42: =AI41-Q42-AH42 -> 4.3352304e+08 | AJ42: =AJ41-AH42 -> 17300753
B43: Rate Atrib Pensiun | C43: =C35+IF($D$13>0,0.01,0) -> 0.1411 | D43: fx=C35 | G43: 40 | H43: =H42-I43 -> 4.1885505e+08 | I43: =K43-J43 -> 2224047.5 | J43: =IF(G43<=$C$9,H42*$C$25/12,H42*$C$35/12) -> 3470393.5 | K43: =IFERROR(IF(G43<=$C$8,IF(G43<=$C$9,$C$6,$C$36),0),0) -> 5694441 | O43: 40 | P43: =P42-Q43 -> 4.1427577e+08 | Q43: =S43-R43 -> 1946521.8 | R43: =IF(O43<=$C$9,P42*$V$5/12,P42*$V$14/12) -> 3747919.2 | S43: =IFERROR(IF(O43<=$C$8,IF(O43<=$C$9,$C$6,$V$15),0),0) -> 5694441 | AF43: 40 | AG43: =$AH$1/12*AI42 -> 3141139.5 | AH43: =R43-AG43 -> 606779.74 | AI43: =AI42-Q43-AH43 -> 4.3096974e+08 | AJ43: =AJ42-AH43 -> 16693973
B44: Plafon Maksimal Pensiun | C44: =-PV(C43/12,C10,C7-D13,0,0) -> 1.6796287e+08 | D44: fx=-PV(C43/12;C10;C7;0;0) | G44: 41 | H44: =H43-I44 -> 4.1661267e+08 | I44: =K44-J44 -> 2242377.3 | J44: =IF(G44<=$C$9,H43*$C$25/12,H43*$C$35/12) -> 3452063.7 | K44: =IFERROR(IF(G44<=$C$8,IF(G44<=$C$9,$C$6,$C$36),0),0) -> 5694441 | O44: 41 | P44: =P43-Q44 -> 4.1231172e+08 | Q44: =S44-R44 -> 1964049.4 | R44: =IF(O44<=$C$9,P43*$V$5/12,P43*$V$14/12) -> 3730391.6 | S44: =IFERROR(IF(O44<=$C$8,IF(O44<=$C$9,$C$6,$V$15),0),0) -> 5694441 | AF44: 41 | AG44: =$AH$1/12*AI43 -> 3122639.3 | AH44: =R44-AG44 -> 607752.3 | AI44: =AI43-Q44-AH44 -> 4.2839794e+08 | AJ44: =AJ43-AH44 -> 16086221
B45: Plafond Maksimal Aktif | C45: =C18 -> 495000000 | D45: fx=ROUNDDOWN(-PV(C42/12;C9;C6;C44;0)/10^6;0)*10^6 | G45: 42 | H45: =H44-I45 -> 4.1435181e+08 | I45: =K45-J45 -> 2260858.2 | J45: =IF(G45<=$C$9,H44*$C$25/12,H44*$C$35/12) -> 3433582.8 | K45: =IFERROR(IF(G45<=$C$8,IF(G45<=$C$9,$C$6,$C$36),0),0) -> 5694441 | O45: 42 | P45: =P44-Q45 -> 4.1032998e+08 | Q45: =S45-R45 -> 1981734.9 | R45: =IF(O45<=$C$9,P44*$V$5/12,P44*$V$14/12) -> 3712706.1 | S45: =IFERROR(IF(O45<=$C$8,IF(O45<=$C$9,$C$6,$V$15),0),0) -> 5694441 | AF45: 42 | AG45: =$AH$1/12*AI44 -> 3104005 | AH45: =R45-AG45 -> 608701.08 | AI45: =AI44-Q45-AH45 -> 4.258075e+08 | AJ45: =AJ44-AH45 -> 15477520
B46: ATRIBUSI | G46: 43 | H46: =H45-I46 -> 4.1207232e+08 | I46: =K46-J46 -> 2279491.5 | J46: =IF(G46<=$C$9,H45*$C$25/12,H45*$C$35/12) -> 3414949.5 | K46: =IFERROR(IF(G46<=$C$8,IF(G46<=$C$9,$C$6,$C$36),0),0) -> 5694441 | O46: 43 | P46: =P45-Q46 -> 4.0833041e+08 | Q46: =S46-R46 -> 1999579.7 | R46: =IF(O46<=$C$9,P45*$V$5/12,P45*$V$14/12) -> 3694861.3 | S46: =IFERROR(IF(O46<=$C$8,IF(O46<=$C$9,$C$6,$V$15),0),0) -> 5694441 | AF46: 43 | AG46: =$AH$1/12*AI45 -> 3085235.7 | AH46: =R46-AG46 -> 609625.62 | AI46: =AI45-Q46-AH46 -> 4.231983e+08 | AJ46: =AJ45-AH46 -> 14867894
B47: Rate Aktif (plafon atrib) | C47: =C42 -> 0.1089 | D47: ANGS MAKS ATR AKTIF | E47: =C6-C23 -> 5472228.4 | G47: 44 | H47: =H46-I47 -> 4.0977404e+08 | I47: =K47-J47 -> 2298278.3 | J47: =IF(G47<=$C$9,H46*$C$25/12,H46*$C$35/12) -> 3396162.7 | K47: =IFERROR(IF(G47<=$C$8,IF(G47<=$C$9,$C$6,$C$36),0),0) -> 5694441 | O47: 44 | P47: =P46-Q47 -> 4.0631282e+08 | Q47: =S47-R47 -> 2017585.1 | R47: =IF(O47<=$C$9,P46*$V$5/12,P46*$V$14/12) -> 3676855.9 | S47: =IFERROR(IF(O47<=$C$8,IF(O47<=$C$9,$C$6,$V$15),0),0) -> 5694441 | AF47: 44 | AG47: =$AH$1/12*AI46 -> 3066330.4 | AH47: =R47-AG47 -> 610525.47 | AI47: =AI46-Q47-AH47 -> 4.2057019e+08 | AJ47: =AJ46-AH47 -> 14257369
B48: Rate Pensiun (plafon atrib) | C48: =C43 -> 0.1411 | D48: ANGS MAKS ATR PENSIUN | E48: =C7-C23 -> 3917787.4 | G48: 45 | H48: =H47-I48 -> 4.0745682e+08 | I48: =K48-J48 -> 2317219.9 | J48: =IF(G48<=$C$9,H47*$C$25/12,H47*$C$35/12) -> 3377221.1 | K48: =IFERROR(IF(G48<=$C$8,IF(G48<=$C$9,$C$6,$C$36),0),0) -> 5694441 | O48: 45 | P48: =P47-Q48 -> 4.0427707e+08 | Q48: =S48-R48 -> 2035752.7 | R48: =IF(O48<=$C$9,P47*$V$5/12,P47*$V$14/12) -> 3658688.3 | S48: =IFERROR(IF(O48<=$C$8,IF(O48<=$C$9,$C$6,$V$15),0),0) -> 5694441 | AF48: 45 | AG48: =$AH$1/12*AI47 -> 3047288.1 | AH48: =R48-AG48 -> 611400.17 | AI48: =AI47-Q48-AH48 -> 4.1792304e+08 | AJ48: =AJ47-AH48 -> 13645968
B49: Plafon mak pensiun | C49: =-PV(C48/12,C10,E48,0,0) -> 1.6796287e+08 | D49: "=PV(RATE;TENOR;PMT) | G49: 46 | H49: =H48-I49 -> 4.0512051e+08 | I49: =K49-J49 -> 2336317.7 | J49: =IF(G49<=$C$9,H48*$C$25/12,H48*$C$35/12) -> 3358123.3 | K49: =IFERROR(IF(G49<=$C$8,IF(G49<=$C$9,$C$6,$C$36),0),0) -> 5694441 | O49: 46 | P49: =P48-Q49 -> 4.0222298e+08 | Q49: =S49-R49 -> 2054083.9 | R49: =IF(O49<=$C$9,P48*$V$5/12,P48*$V$14/12) -> 3640357.1 | S49: =IFERROR(IF(O49<=$C$8,IF(O49<=$C$9,$C$6,$V$15),0),0) -> 5694441 | AF49: 46 | AG49: =$AH$1/12*AI48 -> 3028107.9 | AH49: =R49-AG49 -> 612249.26 | AI49: =AI48-Q49-AH49 -> 4.152567e+08 | AJ49: =AJ48-AH49 -> 13033719
B50: Plafon maks prapen | C50: =ROUNDDOWN(-PV(C47/12,C9,E47,C49,0)/10^6,0)*10^6 -> 455000000 | G50: 47 | H50: =H49-I50 -> 4.0276493e+08 | I50: =K50-J50 -> 2355572.8 | J50: =IF(G50<=$C$9,H49*$C$25/12,H49*$C$35/12) -> 3338868.2 | K50: =IFERROR(IF(G50<=$C$8,IF(G50<=$C$9,$C$6,$C$36),0),0) -> 5694441 | O50: 47 | P50: =P49-Q50 -> 4.001504e+08 | Q50: =S50-R50 -> 2072580.1 | R50: =IF(O50<=$C$9,P49*$V$5/12,P49*$V$14/12) -> 3621860.9 | S50: =IFERROR(IF(O50<=$C$8,IF(O50<=$C$9,$C$6,$V$15),0),0) -> 5694441 | AF50: 47 | AG50: =$AH$1/12*AI49 -> 3008788.7 | AH50: =R50-AG50 -> 613072.25 | AI50: =AI49-Q50-AH50 -> 4.1257105e+08 | AJ50: =AJ49-AH50 -> 12420647
G51: 48 | H51: =H50-I51 -> 4.0038995e+08 | I51: =K51-J51 -> 2374986.7 | J51: =IF(G51<=$C$9,H50*$C$25/12,H50*$C$35/12) -> 3319454.3 | K51: =IFERROR(IF(G51<=$C$8,IF(G51<=$C$9,$C$6,$C$36),0),0) -> 5694441 | O51: 48 | P51: =P50-Q51 -> 3.9805916e+08 | Q51: =S51-R51 -> 2091242.8 | R51: =IF(O51<=$C$9,P50*$V$5/12,P50*$V$14/12) -> 3603198.2 | S51: =IFERROR(IF(O51<=$C$8,IF(O51<=$C$9,$C$6,$V$15),0),0) -> 5694441 | AF51: 48 | AG51: =$AH$1/12*AI50 -> 2989329.5 | AH51: =R51-AG51 -> 613868.67 | AI51: =AI50-Q51-AH51 -> 4.0986594e+08 | AJ51: =AJ50-AH51 -> 11806778
G52: 49 | H52: =H51-I52 -> 3.9799539e+08 | I52: =K52-J52 -> 2394560.5 | J52: =IF(G52<=$C$9,H51*$C$25/12,H51*$C$35/12) -> 3299880.5 | K52: =IFERROR(IF(G52<=$C$8,IF(G52<=$C$9,$C$6,$C$36),0),0) -> 5694441 | O52: 49 | P52: =P51-Q52 -> 3.9594909e+08 | Q52: =S52-R52 -> 2110073.7 | R52: =IF(O52<=$C$9,P51*$V$5/12,P51*$V$14/12) -> 3584367.3 | S52: =IFERROR(IF(O52<=$C$8,IF(O52<=$C$9,$C$6,$V$15),0),0) -> 5694441 | AF52: 49 | AG52: =$AH$1/12*AI51 -> 2969729.3 | AH52: =R52-AG52 -> 614638.03 | AI52: =AI51-Q52-AH52 -> 4.0714123e+08 | AJ52: =AJ51-AH52 -> 11192140
G53: 50 | H53: =H52-I53 -> 3.9558109e+08 | I53: =K53-J53 -> 2414295.7 | J53: =IF(G53<=$C$9,H52*$C$25/12,H52*$C$35/12) -> 3280145.3 | K53: =IFERROR(IF(G53<=$C$8,IF(G53<=$C$9,$C$6,$C$36),0),0) -> 5694441 | O53: 50 | P53: =P52-Q53 -> 3.9382001e+08 | Q53: =S53-R53 -> 2129074.1 | R53: =IF(O53<=$C$9,P52*$V$5/12,P52*$V$14/12) -> 3565366.9 | S53: =IFERROR(IF(O53<=$C$8,IF(O53<=$C$9,$C$6,$V$15),0),0) -> 5694441 | AF53: 50 | AG53: =$AH$1/12*AI52 -> 2949987.1 | AH53: =R53-AG53 -> 615379.84 | AI53: =AI52-Q53-AH53 -> 4.0439677e+08 | AJ53: =AJ52-AH53 -> 10576760
G54: 51 | H54: =H53-I54 -> 3.931469e+08 | I54: =K54-J54 -> 2434193.5 | J54: =IF(G54<=$C$9,H53*$C$25/12,H53*$C$35/12) -> 3260247.5 | K54: =IFERROR(IF(G54<=$C$8,IF(G54<=$C$9,$C$6,$C$36),0),0) -> 5694441 | O54: 51 | P54: =P53-Q54 -> 3.9167177e+08 | Q54: =S54-R54 -> 2148245.5 | R54: =IF(O54<=$C$9,P53*$V$5/12,P53*$V$14/12) -> 3546195.5 | S54: =IFERROR(IF(O54<=$C$8,IF(O54<=$C$9,$C$6,$V$15),0),0) -> 5694441 | AF54: 51 | AG54: =$AH$1/12*AI53 -> 2930101.9 | AH54: =R54-AG54 -> 616093.61 | AI54: =AI53-Q54-AH54 -> 4.0163243e+08 | AJ54: =AJ53-AH54 -> 9960666.8
G55: 52 | H55: =H54-I55 -> 3.9069264e+08 | I55: =K55-J55 -> 2454255.3 | J55: =IF(G55<=$C$9,H54*$C$25/12,H54*$C$35/12) -> 3240185.7 | K55: =IFERROR(IF(G55<=$C$8,IF(G55<=$C$9,$C$6,$C$36),0),0) -> 5694441 | O55: 52 | P55: =P54-Q55 -> 3.8950418e+08 | Q55: =S55-R55 -> 2167589.7 | R55: =IF(O55<=$C$9,P54*$V$5/12,P54*$V$14/12) -> 3526851.3 | S55: =IFERROR(IF(O55<=$C$8,IF(O55<=$C$9,$C$6,$V$15),0),0) -> 5694441 | AF55: 52 | AG55: =$AH$1/12*AI54 -> 2910072.5 | AH55: =R55-AG55 -> 616778.82 | AI55: =AI54-Q55-AH55 -> 3.9884807e+08 | AJ55: =AJ54-AH55 -> 9343888
G56: 53 | H56: =H55-I56 -> 3.8821816e+08 | I56: =K56-J56 -> 2474482.5 | J56: =IF(G56<=$C$9,H55*$C$25/12,H55*$C$35/12) -> 3219958.5 | K56: =IFERROR(IF(G56<=$C$8,IF(G56<=$C$9,$C$6,$C$36),0),0) -> 5694441 | O56: 53 | P56: =P55-Q56 -> 3.8731707e+08 | Q56: =S56-R56 -> 2187108 | R56: =IF(O56<=$C$9,P55*$V$5/12,P55*$V$14/12) -> 3507333 | S56: =IFERROR(IF(O56<=$C$8,IF(O56<=$C$9,$C$6,$V$15),0),0) -> 5694441 | AF56: 53 | AG56: =$AH$1/12*AI55 -> 2889898.1 | AH56: =R56-AG56 -> 617434.97 | AI56: =AI55-Q56-AH56 -> 3.9604352e+08 | AJ56: =AJ55-AH56 -> 8726453
G57: 54 | H57: =H56-I57 -> 3.8572328e+08 | I57: =K57-J57 -> 2494876.3 | J57: =IF(G57<=$C$9,H56*$C$25/12,H56*$C$35/12) -> 3199564.7 | K57: =IFERROR(IF(G57<=$C$8,IF(G57<=$C$9,$C$6,$C$36),0),0) -> 5694441 | O57: 54 | P57: =P56-Q57 -> 3.8511027e+08 | Q57: =S57-R57 -> 2206802 | R57: =IF(O57<=$C$9,P56*$V$5/12,P56*$V$14/12) -> 3487639 | S57: =IFERROR(IF(O57<=$C$8,IF(O57<=$C$9,$C$6,$V$15),0),0) -> 5694441 | AF57: 54 | AG57: =$AH$1/12*AI56 -> 2869577.4 | AH57: =R57-AG57 -> 618061.55 | AI57: =AI56-Q57-AH57 -> 3.9321866e+08 | AJ57: =AJ56-AH57 -> 8108391.5
G58: 55 | H58: =H57-I58 -> 3.8320784e+08 | I58: =K58-J58 -> 2515438.3 | J58: =IF(G58<=$C$9,H57*$C$25/12,H57*$C$35/12) -> 3179002.7 | K58: =IFERROR(IF(G58<=$C$8,IF(G58<=$C$9,$C$6,$C$36),0),0) -> 5694441 | O58: 55 | P58: =P57-Q58 -> 3.8288359e+08 | Q58: =S58-R58 -> 2226673.4 | R58: =IF(O58<=$C$9,P57*$V$5/12,P57*$V$14/12) -> 3467767.6 | S58: =IFERROR(IF(O58<=$C$8,IF(O58<=$C$9,$C$6,$V$15),0),0) -> 5694441 | AF58: 55 | AG58: =$AH$1/12*AI57 -> 2849109.6 | AH58: =R58-AG58 -> 618658.02 | AI58: =AI57-Q58-AH58 -> 3.9037333e+08 | AJ58: =AJ57-AH58 -> 7489733.5
A59: 6 | B59: Buat jadwal angsuran terlebih dulu untuk mengetahui OS saat memasuki pensiun --> | G59: 56 | H59: =H58-I59 -> 3.8067167e+08 | I59: =K59-J59 -> 2536169.7 | J59: =IF(G59<=$C$9,H58*$C$25/12,H58*$C$35/12) -> 3158271.3 | K59: =IFERROR(IF(G59<=$C$8,IF(G59<=$C$9,$C$6,$C$36),0),0) -> 5694441 | O59: 56 | P59: =P58-Q59 -> 3.8063687e+08 | Q59: =S59-R59 -> 2246723.7 | R59: =IF(O59<=$C$9,P58*$V$5/12,P58*$V$14/12) -> 3447717.3 | S59: =IFERROR(IF(O59<=$C$8,IF(O59<=$C$9,$C$6,$V$15),0),0) -> 5694441 | AF59: 56 | AG59: =$AH$1/12*AI58 -> 2828493.4 | AH59: =R59-AG59 -> 619223.86 | AI59: =AI58-Q59-AH59 -> 3.8750738e+08 | AJ59: =AJ58-AH59 -> 6870509.6
B60: Sisa OS saat pensiun | C60: =H117 -> 1.9150035e+08 | D60: fx=H115 | G60: 57 | H60: =H59-I60 -> 3.781146e+08 | I60: =K60-J60 -> 2557072 | J60: =IF(G60<=$C$9,H59*$C$25/12,H59*$C$35/12) -> 3137369 | K60: =IFERROR(IF(G60<=$C$8,IF(G60<=$C$9,$C$6,$C$36),0),0) -> 5694441 | O60: 57 | P60: =P59-Q60 -> 3.7836992e+08 | Q60: =S60-R60 -> 2266954.6 | R60: =IF(O60<=$C$9,P59*$V$5/12,P59*$V$14/12) -> 3427486.4 | S60: =IFERROR(IF(O60<=$C$8,IF(O60<=$C$9,$C$6,$V$15),0),0) -> 5694441 | AF60: 57 | AG60: =$AH$1/12*AI59 -> 2807727.9 | AH60: =R60-AG60 -> 619758.53 | AI60: =AI59-Q60-AH60 -> 3.8462067e+08 | AJ60: =AJ59-AH60 -> 6250751.1
G61: 58 | H61: =H60-I61 -> 3.7553646e+08 | I61: =K61-J61 -> 2578146.5 | J61: =IF(G61<=$C$9,H60*$C$25/12,H60*$C$35/12) -> 3116294.5 | K61: =IFERROR(IF(G61<=$C$8,IF(G61<=$C$9,$C$6,$C$36),0),0) -> 5694441 | O61: 58 | P61: =P60-Q61 -> 3.7608255e+08 | Q61: =S61-R61 -> 2287367.6 | R61: =IF(O61<=$C$9,P60*$V$5/12,P60*$V$14/12) -> 3407073.4 | S61: =IFERROR(IF(O61<=$C$8,IF(O61<=$C$9,$C$6,$V$15),0),0) -> 5694441 | AF61: 58 | AG61: =$AH$1/12*AI60 -> 2786811.9 | AH61: =R61-AG61 -> 620261.5 | AI61: =AI60-Q61-AH61 -> 3.8171304e+08 | AJ61: =AJ60-AH61 -> 5630489.6
B62: Angsuran Pensiun | C62: =-PMT(C43/12,C10,C60,0,0) -> 4466806.6 | D62: =-PMT(C43/12;C10;C60;0;0) | G62: 59 | H62: =H61-I62 -> 3.7293706e+08 | I62: =K62-J62 -> 2599394.7 | J62: =IF(G62<=$C$9,H61*$C$25/12,H61*$C$35/12) -> 3095046.3 | K62: =IFERROR(IF(G62<=$C$8,IF(G62<=$C$9,$C$6,$C$36),0),0) -> 5694441 | O62: 59 | P62: =P61-Q62 -> 3.7377458e+08 | Q62: =S62-R62 -> 2307964.5 | R62: =IF(O62<=$C$9,P61*$V$5/12,P61*$V$14/12) -> 3386476.5 | S62: =IFERROR(IF(O62<=$C$8,IF(O62<=$C$9,$C$6,$V$15),0),0) -> 5694441 | AF62: 59 | AG62: =$AH$1/12*AI61 -> 2765744.3 | AH62: =R62-AG62 -> 620732.19 | AI62: =AI61-Q62-AH62 -> 3.7878434e+08 | AJ62: =AJ61-AH62 -> 5009757.4
C63: **angsuran pensiun telah memenuhi atau dibawah 90% akseptasi Manfaat Pensiun (sesuai) | G63: 60 | H63: =H62-I63 -> 3.7031624e+08 | I63: =K63-J63 -> 2620818.1 | J63: =IF(G63<=$C$9,H62*$C$25/12,H62*$C$35/12) -> 3073622.9 | K63: =IFERROR(IF(G63<=$C$8,IF(G63<=$C$9,$C$6,$C$36),0),0) -> 5694441 | O63: 60 | P63: =P62-Q63 -> 3.7144584e+08 | Q63: =S63-R63 -> 2328746.8 | R63: =IF(O63<=$C$9,P62*$V$5/12,P62*$V$14/12) -> 3365694.2 | S63: =IFERROR(IF(O63<=$C$8,IF(O63<=$C$9,$C$6,$V$15),0),0) -> 5694441 | AF63: 60 | AG63: =$AH$1/12*AI62 -> 2744524.1 | AH63: =R63-AG63 -> 621170.07 | AI63: =AI62-Q63-AH63 -> 3.7583442e+08 | AJ63: =AJ62-AH63 -> 4388587.3
G64: 61 | H64: =H63-I64 -> 3.6767382e+08 | I64: =K64-J64 -> 2642418 | J64: =IF(G64<=$C$9,H63*$C$25/12,H63*$C$35/12) -> 3052023 | K64: =IFERROR(IF(G64<=$C$8,IF(G64<=$C$9,$C$6,$C$36),0),0) -> 5694441 | O64: 61 | P64: =P63-Q64 -> 3.6909612e+08 | Q64: =S64-R64 -> 2349716.3 | R64: =IF(O64<=$C$9,P63*$V$5/12,P63*$V$14/12) -> 3344724.7 | S64: =IFERROR(IF(O64<=$C$8,IF(O64<=$C$9,$C$6,$V$15),0),0) -> 5694441 | AF64: 61 | AG64: =$AH$1/12*AI63 -> 2723150.2 | AH64: =R64-AG64 -> 621574.57 | AI64: =AI63-Q64-AH64 -> 3.7286313e+08 | AJ64: =AJ63-AH64 -> 3767012.8
G65: 62 | H65: =H64-I65 -> 3.6500963e+08 | I65: =K65-J65 -> 2664195.9 | J65: =IF(G65<=$C$9,H64*$C$25/12,H64*$C$35/12) -> 3030245.1 | K65: =IFERROR(IF(G65<=$C$8,IF(G65<=$C$9,$C$6,$C$36),0),0) -> 5694441 | O65: 62 | P65: =P64-Q65 -> 3.6672525e+08 | Q65: =S65-R65 -> 2370874.5 | R65: =IF(O65<=$C$9,P64*$V$5/12,P64*$V$14/12) -> 3323566.5 | S65: =IFERROR(IF(O65<=$C$8,IF(O65<=$C$9,$C$6,$V$15),0),0) -> 5694441 | AF65: 62 | AG65: =$AH$1/12*AI64 -> 2701621.4 | AH65: =R65-AG65 -> 621945.11 | AI65: =AI64-Q65-AH65 -> 3.6987031e+08 | AJ65: =AJ64-AH65 -> 3145067.6
G66: 63 | H66: =H65-I66 -> 3.6232348e+08 | I66: =K66-J66 -> 2686153.3 | J66: =IF(G66<=$C$9,H65*$C$25/12,H65*$C$35/12) -> 3008287.7 | K66: =IFERROR(IF(G66<=$C$8,IF(G66<=$C$9,$C$6,$C$36),0),0) -> 5694441 | O66: 63 | P66: =P65-Q66 -> 3.6433302e+08 | Q66: =S66-R66 -> 2392223.3 | R66: =IF(O66<=$C$9,P65*$V$5/12,P65*$V$14/12) -> 3302217.7 | S66: =IFERROR(IF(O66<=$C$8,IF(O66<=$C$9,$C$6,$V$15),0),0) -> 5694441 | AF66: 63 | AG66: =$AH$1/12*AI65 -> 2679936.5 | AH66: =R66-AG66 -> 622281.12 | AI66: =AI65-Q66-AH66 -> 3.6685581e+08 | AJ66: =AJ65-AH66 -> 2522786.5
B67: Note for PP10 Dekade Berkah | G67: 64 | H67: =H66-I67 -> 3.5961518e+08 | I67: =K67-J67 -> 2708291.7 | J67: =IF(G67<=$C$9,H66*$C$25/12,H66*$C$35/12) -> 2986149.3 | K67: =IFERROR(IF(G67<=$C$8,IF(G67<=$C$9,$C$6,$C$36),0),0) -> 5694441 | O67: 64 | P67: =P66-Q67 -> 3.6191926e+08 | Q67: =S67-R67 -> 2413764.4 | R67: =IF(O67<=$C$9,P66*$V$5/12,P66*$V$14/12) -> 3280676.6 | S67: =IFERROR(IF(O67<=$C$8,IF(O67<=$C$9,$C$6,$V$15),0),0) -> 5694441 | AF67: 64 | AG67: =$AH$1/12*AI66 -> 2658094.6 | AH67: =R67-AG67 -> 622582.01 | AI67: =AI66-Q67-AH67 -> 3.6381946e+08 | AJ67: =AJ66-AH67 -> 1900204.5
A68: 1. | B68: perhitungan sesuai reguler, plafon maks dan penurunan pokok | G68: 65 | H68: =H67-I68 -> 3.5688457e+08 | I68: =K68-J68 -> 2730612.5 | J68: =IF(G68<=$C$9,H67*$C$25/12,H67*$C$35/12) -> 2963828.5 | K68: =IFERROR(IF(G68<=$C$8,IF(G68<=$C$9,$C$6,$C$36),0),0) -> 5694441 | O68: 65 | P68: =P67-Q68 -> 3.5948376e+08 | Q68: =S68-R68 -> 2435499.4 | R68: =IF(O68<=$C$9,P67*$V$5/12,P67*$V$14/12) -> 3258941.6 | S68: =IFERROR(IF(O68<=$C$8,IF(O68<=$C$9,$C$6,$V$15),0),0) -> 5694441 | AF68: 65 | AG68: =$AH$1/12*AI67 -> 2636094.4 | AH68: =R68-AG68 -> 622847.19 | AI68: =AI67-Q68-AH68 -> 3.6076112e+08 | AJ68: =AJ67-AH68 -> 1277357.3
A69: 2. | B69: rate penyesuaian di aktif +0,001 (0,1%) | G69: 66 | H69: =H68-I69 -> 3.5413145e+08 | I69: =K69-J69 -> 2753117.3 | J69: =IF(G69<=$C$9,H68*$C$25/12,H68*$C$35/12) -> 2941323.7 | K69: =IFERROR(IF(G69<=$C$8,IF(G69<=$C$9,$C$6,$C$36),0),0) -> 5694441 | O69: 66 | P69: =P68-Q69 -> 3.5702633e+08 | Q69: =S69-R69 -> 2457430.1 | R69: =IF(O69<=$C$9,P68*$V$5/12,P68*$V$14/12) -> 3237010.9 | S69: =IFERROR(IF(O69<=$C$8,IF(O69<=$C$9,$C$6,$V$15),0),0) -> 5694441 | AF69: 66 | AG69: =$AH$1/12*AI68 -> 2613934.8 | AH69: =R69-AG69 -> 623076.06 | AI69: =AI68-Q69-AH69 -> 3.5768061e+08 | AJ69: =AJ68-AH69 -> 654281.27
A70: 3. | B70: rate adjs. Di pensiun +0,01 (1%) | G70: 67 | H70: =H69-I70 -> 3.5135565e+08 | I70: =K70-J70 -> 2775807.6 | J70: =IF(G70<=$C$9,H69*$C$25/12,H69*$C$35/12) -> 2918633.4 | K70: =IFERROR(IF(G70<=$C$8,IF(G70<=$C$9,$C$6,$C$36),0),0) -> 5694441 | O70: 67 | P70: =P69-Q70 -> 3.5454677e+08 | Q70: =S70-R70 -> 2479558.3 | R70: =IF(O70<=$C$9,P69*$V$5/12,P69*$V$14/12) -> 3214882.7 | S70: =IFERROR(IF(O70<=$C$8,IF(O70<=$C$9,$C$6,$V$15),0),0) -> 5694441 | AF70: 67 | AG70: =$AH$1/12*AI69 -> 2591614.7 | AH70: =R70-AG70 -> 623268.01 | AI70: =AI69-Q70-AH70 -> 3.5457778e+08 | AJ70: =AJ69-AH70 -> 31013.265
A71: 4. | B71: Case Atrib, DSR/DBR maks dikurangin atrib per bulan | G71: 68 | H71: =H70-I71 -> 3.4855696e+08 | I71: =K71-J71 -> 2798684.9 | J71: =IF(G71<=$C$9,H70*$C$25/12,H70*$C$35/12) -> 2895756.1 | K71: =IFERROR(IF(G71<=$C$8,IF(G71<=$C$9,$C$6,$C$36),0),0) -> 5694441 | O71: 68 | P71: =P70-Q71 -> 3.5204488e+08 | Q71: =S71-R71 -> 2501885.8 | R71: =IF(O71<=$C$9,P70*$V$5/12,P70*$V$14/12) -> 3192555.2 | S71: =IFERROR(IF(O71<=$C$8,IF(O71<=$C$9,$C$6,$V$15),0),0) -> 5694441 | AF71: 68 | AG71: =$AH$1/12*AI70 -> 2569132.8 | AH71: =R71-AG71 -> 623422.43 | AI71: =AI70-Q71-AH71 -> 3.5145248e+08 | AJ71: =AJ70-AH71 -> -592409.16
G72: 69 | H72: =H71-I72 -> 3.4573521e+08 | I72: =K72-J72 -> 2821750.7 | J72: =IF(G72<=$C$9,H71*$C$25/12,H71*$C$35/12) -> 2872690.3 | K72: =IFERROR(IF(G72<=$C$8,IF(G72<=$C$9,$C$6,$C$36),0),0) -> 5694441 | O72: 69 | P72: =P71-Q72 -> 3.4952047e+08 | Q72: =S72-R72 -> 2524414.3 | R72: =IF(O72<=$C$9,P71*$V$5/12,P71*$V$14/12) -> 3170026.7 | S72: =IFERROR(IF(O72<=$C$8,IF(O72<=$C$9,$C$6,$V$15),0),0) -> 5694441 | AF72: 69 | AG72: =$AH$1/12*AI71 -> 2546488 | AH72: =R72-AG72 -> 623538.69 | AI72: =AI71-Q72-AH72 -> 3.4830452e+08 | AJ72: =AJ71-AH72 -> -1215947.9
G73: 70 | H73: =H72-I73 -> 3.428902e+08 | I73: =K73-J73 -> 2845006.6 | J73: =IF(G73<=$C$9,H72*$C$25/12,H72*$C$35/12) -> 2849434.4 | K73: =IFERROR(IF(G73<=$C$8,IF(G73<=$C$9,$C$6,$C$36),0),0) -> 5694441 | O73: 70 | P73: =P72-Q73 -> 3.4697333e+08 | Q73: =S73-R73 -> 2547145.6 | R73: =IF(O73<=$C$9,P72*$V$5/12,P72*$V$14/12) -> 3147295.4 | S73: =IFERROR(IF(O73<=$C$8,IF(O73<=$C$9,$C$6,$V$15),0),0) -> 5694441 | AF73: 70 | AG73: =$AH$1/12*AI72 -> 2523679.2 | AH73: =R73-AG73 -> 623616.17 | AI73: =AI72-Q73-AH73 -> 3.4513376e+08 | AJ73: =AJ72-AH73 -> -1839564
G74: 71 | H74: =H73-I74 -> 3.4002175e+08 | I74: =K74-J74 -> 2868454.2 | J74: =IF(G74<=$C$9,H73*$C$25/12,H73*$C$35/12) -> 2825986.8 | K74: =IFERROR(IF(G74<=$C$8,IF(G74<=$C$9,$C$6,$C$36),0),0) -> 5694441 | O74: 71 | P74: =P73-Q74 -> 3.4440324e+08 | Q74: =S74-R74 -> 2570081.7 | R74: =IF(O74<=$C$9,P73*$V$5/12,P73*$V$14/12) -> 3124359.3 | S74: =IFERROR(IF(O74<=$C$8,IF(O74<=$C$9,$C$6,$V$15),0),0) -> 5694441 | AF74: 71 | AG74: =$AH$1/12*AI73 -> 2500705.1 | AH74: =R74-AG74 -> 623654.23 | AI74: =AI73-Q74-AH74 -> 3.4194003e+08 | AJ74: =AJ73-AH74 -> -2463218.3
G75: 72 | H75: =H74-I75 -> 3.3712966e+08 | I75: =K75-J75 -> 2892095.1 | J75: =IF(G75<=$C$9,H74*$C$25/12,H74*$C$35/12) -> 2802345.9 | K75: =IFERROR(IF(G75<=$C$8,IF(G75<=$C$9,$C$6,$C$36),0),0) -> 5694441 | O75: 72 | P75: =P74-Q75 -> 3.4181002e+08 | Q75: =S75-R75 -> 2593224.3 | R75: =IF(O75<=$C$9,P74*$V$5/12,P74*$V$14/12) -> 3101216.7 | S75: =IFERROR(IF(O75<=$C$8,IF(O75<=$C$9,$C$6,$V$15),0),0) -> 5694441 | AF75: 72 | AG75: =$AH$1/12*AI74 -> 2477564.5 | AH75: =R75-AG75 -> 623652.21 | AI75: =AI74-Q75-AH75 -> 3.3872315e+08 | AJ75: =AJ74-AH75 -> -3086870.5
G76: 73 | H76: =H75-I76 -> 3.3421372e+08 | I76: =K76-J76 -> 2915930.8 | J76: =IF(G76<=$C$9,H75*$C$25/12,H75*$C$35/12) -> 2778510.2 | K76: =IFERROR(IF(G76<=$C$8,IF(G76<=$C$9,$C$6,$C$36),0),0) -> 5694441 | O76: 73 | P76: =P75-Q76 -> 3.3919344e+08 | Q76: =S76-R76 -> 2616575.2 | R76: =IF(O76<=$C$9,P75*$V$5/12,P75*$V$14/12) -> 3077865.8 | S76: =IFERROR(IF(O76<=$C$8,IF(O76<=$C$9,$C$6,$V$15),0),0) -> 5694441 | AF76: 73 | AG76: =$AH$1/12*AI75 -> 2454256.3 | AH76: =R76-AG76 -> 623609.48 | AI76: =AI75-Q76-AH76 -> 3.3548296e+08 | AJ76: =AJ75-AH76 -> -3710479.9
G77: 74 | H77: =H76-I77 -> 3.3127376e+08 | I77: =K77-J77 -> 2939962.9 | J77: =IF(G77<=$C$9,H76*$C$25/12,H76*$C$35/12) -> 2754478.1 | K77: =IFERROR(IF(G77<=$C$8,IF(G77<=$C$9,$C$6,$C$36),0),0) -> 5694441 | O77: 74 | P77: =P76-Q77 -> 3.3655331e+08 | Q77: =S77-R77 -> 2640136.5 | R77: =IF(O77<=$C$9,P76*$V$5/12,P76*$V$14/12) -> 3054304.5 | S77: =IFERROR(IF(O77<=$C$8,IF(O77<=$C$9,$C$6,$V$15),0),0) -> 5694441 | AF77: 74 | AG77: =$AH$1/12*AI76 -> 2430779.2 | AH77: =R77-AG77 -> 623525.36 | AI77: =AI76-Q77-AH77 -> 3.322193e+08 | AJ77: =AJ76-AH77 -> -4334005.3
G78: 75 | H78: =H77-I78 -> 3.2830957e+08 | I78: =K78-J78 -> 2964193.1 | J78: =IF(G78<=$C$9,H77*$C$25/12,H77*$C$35/12) -> 2730247.9 | K78: =IFERROR(IF(G78<=$C$8,IF(G78<=$C$9,$C$6,$C$36),0),0) -> 5694441 | O78: 75 | P78: =P77-Q78 -> 3.338894e+08 | Q78: =S78-R78 -> 2663909.9 | R78: =IF(O78<=$C$9,P77*$V$5/12,P77*$V$14/12) -> 3030531.1 | S78: =IFERROR(IF(O78<=$C$8,IF(O78<=$C$9,$C$6,$V$15),0),0) -> 5694441 | AF78: 75 | AG78: =$AH$1/12*AI77 -> 2407131.9 | AH78: =R78-AG78 -> 623399.19 | AI78: =AI77-Q78-AH78 -> 3.2893199e+08 | AJ78: =AJ77-AH78 -> -4957404.5
G79: 76 | H79: =H78-I79 -> 3.2532095e+08 | I79: =K79-J79 -> 2988623 | J79: =IF(G79<=$C$9,H78*$C$25/12,H78*$C$35/12) -> 2705818 | K79: =IFERROR(IF(G79<=$C$8,IF(G79<=$C$9,$C$6,$C$36),0),0) -> 5694441 | O79: 76 | P79: =P78-Q79 -> 3.312015e+08 | Q79: =S79-R79 -> 2687897.3 | R79: =IF(O79<=$C$9,P78*$V$5/12,P78*$V$14/12) -> 3006543.7 | S79: =IFERROR(IF(O79<=$C$8,IF(O79<=$C$9,$C$6,$V$15),0),0) -> 5694441 | AF79: 76 | AG79: =$AH$1/12*AI78 -> 2383313.4 | AH79: =R79-AG79 -> 623230.28 | AI79: =AI78-Q79-AH79 -> 3.2562087e+08 | AJ79: =AJ78-AH79 -> -5580634.8
G80: 77 | H80: =H79-I80 -> 3.2230769e+08 | I80: =K80-J80 -> 3013254.2 | J80: =IF(G80<=$C$9,H79*$C$25/12,H79*$C$35/12) -> 2681186.8 | K80: =IFERROR(IF(G80<=$C$8,IF(G80<=$C$9,$C$6,$C$36),0),0) -> 5694441 | O80: 77 | P80: =P79-Q80 -> 3.284894e+08 | Q80: =S80-R80 -> 2712100.8 | R80: =IF(O80<=$C$9,P79*$V$5/12,P79*$V$14/12) -> 2982340.2 | S80: =IFERROR(IF(O80<=$C$8,IF(O80<=$C$9,$C$6,$V$15),0),0) -> 5694441 | AF80: 77 | AG80: =$AH$1/12*AI79 -> 2359322.2 | AH80: =R80-AG80 -> 623017.96 | AI80: =AI79-Q80-AH80 -> 3.2228575e+08 | AJ80: =AJ79-AH80 -> -6203652.7
G81: 78 | H81: =H80-I81 -> 3.192696e+08 | I81: =K81-J81 -> 3038088.4 | J81: =IF(G81<=$C$9,H80*$C$25/12,H80*$C$35/12) -> 2656352.6 | K81: =IFERROR(IF(G81<=$C$8,IF(G81<=$C$9,$C$6,$C$36),0),0) -> 5694441 | O81: 78 | P81: =P80-Q81 -> 3.2575288e+08 | Q81: =S81-R81 -> 2736522.2 | R81: =IF(O81<=$C$9,P80*$V$5/12,P80*$V$14/12) -> 2957918.8 | S81: =IFERROR(IF(O81<=$C$8,IF(O81<=$C$9,$C$6,$V$15),0),0) -> 5694441 | AF81: 78 | AG81: =$AH$1/12*AI80 -> 2335157.3 | AH81: =R81-AG81 -> 622761.53 | AI81: =AI80-Q81-AH81 -> 3.1892646e+08 | AJ81: =AJ80-AH81 -> -6826414.3
G82: 79 | H82: =H81-I82 -> 3.1620648e+08 | I82: =K82-J82 -> 3063127.4 | J82: =IF(G82<=$C$9,H81*$C$25/12,H81*$C$35/12) -> 2631313.6 | K82: =IFERROR(IF(G82<=$C$8,IF(G82<=$C$9,$C$6,$C$36),0),0) -> 5694441 | O82: 79 | P82: =P81-Q82 -> 3.2299171e+08 | Q82: =S82-R82 -> 2761163.5 | R82: =IF(O82<=$C$9,P81*$V$5/12,P81*$V$14/12) -> 2933277.5 | S82: =IFERROR(IF(O82<=$C$8,IF(O82<=$C$9,$C$6,$V$15),0),0) -> 5694441 | AF82: 79 | AG82: =$AH$1/12*AI81 -> 2310817.2 | AH82: =R82-AG82 -> 622460.28 | AI82: =AI81-Q82-AH82 -> 3.1554284e+08 | AJ82: =AJ81-AH82 -> -7448874.5
G83: 80 | H83: =H82-I83 -> 3.131181e+08 | I83: =K83-J83 -> 3088372.6 | J83: =IF(G83<=$C$9,H82*$C$25/12,H82*$C$35/12) -> 2606068.4 | K83: =IFERROR(IF(G83<=$C$8,IF(G83<=$C$9,$C$6,$C$36),0),0) -> 5694441 | O83: 80 | P83: =P82-Q83 -> 3.2020569e+08 | Q83: =S83-R83 -> 2786026.7 | R83: =IF(O83<=$C$9,P82*$V$5/12,P82*$V$14/12) -> 2908414.3 | S83: =IFERROR(IF(O83<=$C$8,IF(O83<=$C$9,$C$6,$V$15),0),0) -> 5694441 | AF83: 80 | AG83: =$AH$1/12*AI82 -> 2286300.8 | AH83: =R83-AG83 -> 622113.5 | AI83: =AI82-Q83-AH83 -> 3.121347e+08 | AJ83: =AJ82-AH83 -> -8070988
... G183: 180 | H183: =H182-I183 -> -9.2666596e-08 | I183: =K183-J183 -> 3751963.9 | J183: =IF(G183<=$C$9,H182*$C$25/12,H182*$C$35/12) -> 40990.205 | K183: =IFERROR(IF(G183<=$C$8,IF(G183<=$C$9,$C$6,$C$36),0),0) -> 3792954.1 | O183: 180 | P183: =P182-Q183 -> -7.962808e-08 | Q183: =S183-R183 -> 4081278.2 | R183: =IF(O183<=$C$9,P182*$V$5/12,P182*$V$14/12) -> 40598.492 | S183: =IFERROR(IF(O183<=$C$8,IF(O183<=$C$9,$C$6,$V$15),0),0) -> 4121876.7 | AF183: 180 | AG183: =$AH$1/12*AI182 -> -485913.2 | AH183: =R183-AG183 -> 526511.7 | AI183: =AI182-Q183-AH183 -> -71670896 | AJ183: =AJ182-AH183 -> -71670896

Sheet Rincian ke Nsb
B2: ATRIBUSI | H2: ATRIBUSI
B4: PRA PENSIUN DEKADE BERKAH | H4: PRA PENSIUN TRI BERKAH
B6: Nama Nasabah | C6: : | D6: =Akseptasi!C2 -> SITI HAFSAH | H6: Nama Nasabah | I6: : | J6: =Akseptasi!C2 -> SITI HAFSAH
B7: Plafond | C7: : | D7: =Simulasi!B10 -> 480000000 | H7: Plafond | I7: : | J7: =Simulasi!B10 -> 480000000
B8: Jangka Waktu | C8: : | D8: =Simulasi!B11 -> 180 | H8: Jangka Waktu | I8: : | J8: =Simulasi!B11 -> 180
B10: Angsuran saat Aktif PNS | C10: : | D10: =Simulasi!B32 -> 5694441 | E10: ='Jadwal Angsuran Dekade Berkah'!G3 -> 120 | F10: Bulan | H10: Angsuran saat Aktif PNS | I10: : | J10: =Simulasi!B32 -> 5694441 | K10: ='Jadwal Angsuran TriBerkah (Blok'!G3 -> 120 | L10: Bulan
B11: Angsuran saat Pensiun | C11: : | D11: =Simulasi!B33 -> 4121876.7 | E11: ='Jadwal Angsuran Dekade Berkah'!G4 -> 60 | F11: Bulan | H11: Angsuran saat Pensiun | I11: : | J11: =Simulasi!B33 -> 4121876.7 | K11: ='Jadwal Angsuran TriBerkah (Blok'!G4 -> 60 | L11: Bulan
B13: Biaya | H13: Biaya
B14: Administrasi (1%) | C14: : | D14: =1%*D7 -> 4800000 | H14: Administrasi (1%) | I14: : | J14: =1%*J7 -> 4800000
B15: Asuransi | C15: : | D15: 0 | H15: Asuransi | I15: : | J15: 0
B16: Materai | C16: : | D16: 100000 | H16: Materai | I16: : | J16: 100000
B18: Blokir Angsuran | H18: Blokir Angsuran
B19: Blokir 1x Angs Masa Aktif | C19: : | D19: =D10 -> 5694441 | H19: Blokir Angs Aktif + 2x Pensiun | I19: : | J19: =Simulasi!B37 -> blokir sesuai MP
B20: Blokir 2x Angs Masa Pensiun | C20: : | D20: =2*D11 -> 8243753.4
B22: Buka Blokir Yang Lama | C22: : | D22: =[1]Akseptasi!C22 -> 0
B24: Pelunasan Yang Lama | C24: : | D24: =[1]Akseptasi!C23 -> 0
B26: Terima Bersih | C26: : | D26: =D7-D14-D16-D19-D20-D24+D22 -> 4.6116181e+08 | H26: Terima Bersih | I26: : | J26: =J7-J14-J16-J19-J20-J24+J22 -> #VALUE!
B30: Syarat Dokumen Pembiayaan Pra Pen DEKADE BERKAH 10 Tahun (Mrbh atau MMQ) | H30: Syarat Dokumen Pembiayaan Pra Pen DEKADE BERKAH 10 Tahun (Mrbh atau MMQ) | O30: : | P30: YA
B31: Fotocopy KTP Suami dan Istri | H31: Fotocopy KTP Suami dan Istri | O31: : | P31: 27627574
B32: Fotocopy Kartu Keluarga | H32: Fotocopy Kartu Keluarga | O32: : | P32: 0
B33: Fotocopy Akte Nikah | H33: Fotocopy Akte Nikah | O33: : | P33: 0
B34: Fotocopy NPWP | H34: Fotocopy NPWP
B35: Asli SK PNS | H35: Asli SK PNS
B36: Asli SK Golongan terakhir | H36: Asli SK Golongan terakhir
B37: Fotocopy Rek Pensiun BSI | H37: Fotocopy Rek Pensiun BSI
B38: Amprah Gaji & Amprah Tunjangan 3 Bulan Terakhir (Stempel TTD) | H38: Amprah Gaji & Amprah Tunjangan 3 Bulan Terakhir (Stempel TTD)
B39: Rekening Koran atau Print Buku Tabungan Gaji 3 Bulan Terakhir | H39: Rekening Koran atau Print Buku Tabungan Gaji 3 Bulan Terakhir
B40: Fotocopy Surat Tanah/Rumah atas nama Nasabah/Pasangan (Jika Top Up atau Take Over) | H40: Fotocopy Surat Tanah/Rumah atas nama Nasabah/Pasangan (Jika Top Up atau Take Over)

Sheet Jadwal Angsuran Dekade Berkah
B1: Data Pembiayaan
B2: Produk | C2: : | D2: =Simulasi!B3 -> Prapen 10 Tahun | E2: Jangka waktu | F2: : | G2: =Simulasi!B11 -> 180 | H2: Price Aktif | I2: : | J2: =Simulasi!B34 -> 0.10805531
B3: Angsuran Aktif | C3: : | D3: =Simulasi!B32 -> 5694441 | E3: Tenor Aktif | F3: : | G3: ='Rumus Plafond + Atrib PP10 (2)'!C9 -> 120 | H3: Price Pensiun | I3: : | J3: =Simulasi!B35 -> 0.11936993
B4: Angsuran Pensiun | C4: : | D4: =Simulasi!B33 -> 4121876.7 | E4: Tenor Pensiun | F4: : | G4: ='Rumus Plafond + Atrib PP10 (2)'!C10 -> 60
C5: = | D5: INPUT
A6: Akad MMQ | O6: Akad Murabahah
B7: Harga/NilaiObjekAkad | C7: : | D7: 350000000 | E7: 1
B8: HishshahBANK | C8: : | D8: ='Rumus Plafond + Atrib PP10 (2)'!P3 -> 480000000 | E8: =D8/D7 -> 1.3714286
B9: HishshahNASABAH | C9: : | D9: =D7-D8 -> -130000000 | E9: =D9/D7 -> -0.37142857
B10: NisbahAwalBANK | C10: : | D10: =AVERAGE(E16:E195) -> 0.46263774
B11: NisbahAwalNASABAH | C11: : | D11: =AVERAGE(F16:F195) -> 0.53736226
B12: JangkaWaktu | C12: : | D12: =Simulasi!B11&" bulan" -> 180 bulan
R14: *untuk keperluan upload jadwal angsuran
A15: Ke- | B15: Tanggal | C15: Outstanding (Rp) | D15: Biaya Sewa/Ujrah Per Bulan (Rp) | E15: Nisbah Bank(%) | F15: Nisbah Nasabah (%) | G15: BagiHasil Bank (Rp) | H15: BagiHasil Nasabah (Rp) | I15: Hishshah Bank(%) | J15: Hishshah Nasabah (%) | K15: Biaya Sewa/ Ujrah Per Bulan(Rp) | O15: Angsuran ke | P15: Tanggal | Q15: Total Angsuran | R15: Margin | S15: Pokok | T15: Sisa OS
A16: ='Rumus Plafond + Atrib PP10 (2)'!O4 -> 1 | B16: =DATE(YEAR(Simulasi!B5),MONTH(Simulasi!B5)+1,1) -> 46327 | C16: =IFERROR('Rumus Plafond + Atrib PP10 (2)'!P4,"") -> 4.7862777e+08 | D16: =IFERROR('Rumus Plafond + Atrib PP10 (2)'!R4,"") -> 4322212.6 | E16: =IFERROR(G16/K16,"") -> 0.75902316 | F16: =IFERROR(H16/K16,"") -> 0.24097684 | G16: =IFERROR('Rumus Plafond + Atrib PP10 (2)'!R4,"") -> 4322212.6 | H16: =IFERROR('Rumus Plafond + Atrib PP10 (2)'!Q4,"") -> 1372228.4 | I16: =IFERROR(C16/$D$7,"") -> 1.3675079 | J16: =IFERROR(($D$7-C16)/$D$7,"") -> -0.36750792 | K16: =IFERROR('Rumus Plafond + Atrib PP10 (2)'!S4,"") -> 5694441 | O16: =A16 -> 1 | P16: =B16 -> 46327 | Q16: =K16 -> 5694441 | R16: =G16 -> 4322212.6 | S16: =H16 -> 1372228.4 | T16: =C16 -> 4.7862777e+08
A17: ='Rumus Plafond + Atrib PP10 (2)'!O5 -> 2 | B17: =IF(A17<=Simulasi!$B$11,DATE(YEAR(B16),MONTH(B16)+1,1),"") -> 46357 | C17: =IF(A17<=Simulasi!$B$11,'Rumus Plafond + Atrib PP10 (2)'!P5,"") -> 4.7724319e+08 | D17: =IFERROR('Rumus Plafond + Atrib PP10 (2)'!R5,"") -> 4309856.2 | E17: =IFERROR(G17/K17,"") -> 0.75685326 | F17: =IFERROR(H17/K17,"") -> 0.24314674 | G17: =IFERROR('Rumus Plafond + Atrib PP10 (2)'!R5,"") -> 4309856.2 | H17: =IFERROR('Rumus Plafond + Atrib PP10 (2)'!Q5,"") -> 1384584.8 | I17: =IFERROR(C17/$D$7,"") -> 1.363552 | J17: =IFERROR(($D$7-C17)/$D$7,"") -> -0.36355196 | K17: =IFERROR('Rumus Plafond + Atrib PP10 (2)'!S5,"") -> 5694441 | O17: =A17 -> 2 | P17: =B17 -> 46357 | Q17: =K17 -> 5694441 | R17: =G17 -> 4309856.2 | S17: =H17 -> 1384584.8 | T17: =C17 -> 4.7724319e+08
A18: ='Rumus Plafond + Atrib PP10 (2)'!O6 -> 3 | B18: =IF(A18<=Simulasi!$B$11,DATE(YEAR(B17),MONTH(B17)+1,1),"") -> 46388 | C18: =IF(A18<=Simulasi!$B$11,'Rumus Plafond + Atrib PP10 (2)'!P6,"") -> 4.7584613e+08 | D18: =IFERROR('Rumus Plafond + Atrib PP10 (2)'!R6,"") -> 4297388.6 | E18: =IFERROR(G18/K18,"") -> 0.75466381 | F18: =IFERROR(H18/K18,"") -> 0.24533619 | G18: =IFERROR('Rumus Plafond + Atrib PP10 (2)'!R6,"") -> 4297388.6 | H18: =IFERROR('Rumus Plafond + Atrib PP10 (2)'!Q6,"") -> 1397052.4 | I18: =IFERROR(C18/$D$7,"") -> 1.3595604 | J18: =IFERROR(($D$7-C18)/$D$7,"") -> -0.35956038 | K18: =IFERROR('Rumus Plafond + Atrib PP10 (2)'!S6,"") -> 5694441 | O18: =A18 -> 3 | P18: =B18 -> 46388 | Q18: =K18 -> 5694441 | R18: =G18 -> 4297388.6 | S18: =H18 -> 1397052.4 | T18: =C18 -> 4.7584613e+08
A19: ='Rumus Plafond + Atrib PP10 (2)'!O7 -> 4 | B19: =IF(A19<=Simulasi!$B$11,DATE(YEAR(B18),MONTH(B18)+1,1),"") -> 46419 | C19: =IF(A19<=Simulasi!$B$11,'Rumus Plafond + Atrib PP10 (2)'!P7,"") -> 4.744365e+08 | D19: =IFERROR('Rumus Plafond + Atrib PP10 (2)'!R7,"") -> 4284808.7 | E19: =IFERROR(G19/K19,"") -> 0.75245466 | F19: =IFERROR(H19/K19,"") -> 0.24754534 | G19: =IFERROR('Rumus Plafond + Atrib PP10 (2)'!R7,"") -> 4284808.7 | H19: =IFERROR('Rumus Plafond + Atrib PP10 (2)'!Q7,"") -> 1409632.3 | I19: =IFERROR(C19/$D$7,"") -> 1.3555329 | J19: =IFERROR(($D$7-C19)/$D$7,"") -> -0.35553286 | K19: =IFERROR('Rumus Plafond + Atrib PP10 (2)'!S7,"") -> 5694441 | O19: =A19 -> 4 | P19: =B19 -> 46419 | Q19: =K19 -> 5694441 | R19: =G19 -> 4284808.7 | S19: =H19 -> 1409632.3 | T19: =C19 -> 4.744365e+08
A20: ='Rumus Plafond + Atrib PP10 (2)'!O8 -> 5 | B20: =IF(A20<=Simulasi!$B$11,DATE(YEAR(B19),MONTH(B19)+1,1),"") -> 46447 | C20: =IF(A20<=Simulasi!$B$11,'Rumus Plafond + Atrib PP10 (2)'!P8,"") -> 4.7301418e+08 | D20: =IFERROR('Rumus Plafond + Atrib PP10 (2)'!R8,"") -> 4272115.5 | E20: =IFERROR(G20/K20,"") -> 0.75022561 | F20: =IFERROR(H20/K20,"") -> 0.24977439 | G20: =IFERROR('Rumus Plafond + Atrib PP10 (2)'!R8,"") -> 4272115.5 | H20: =IFERROR('Rumus Plafond + Atrib PP10 (2)'!Q8,"") -> 1422325.5 | I20: =IFERROR(C20/$D$7,"") -> 1.3514691 | J20: =IFERROR(($D$7-C20)/$D$7,"") -> -0.35146908 | K20: =IFERROR('Rumus Plafond + Atrib PP10 (2)'!S8,"") -> 5694441 | O20: =A20 -> 5 | P20: =B20 -> 46447 | Q20: =K20 -> 5694441 | R20: =G20 -> 4272115.5 | S20: =H20 -> 1422325.5 | T20: =C20 -> 4.7301418e+08
A21: ='Rumus Plafond + Atrib PP10 (2)'!O9 -> 6 | B21: =IF(A21<=Simulasi!$B$11,DATE(YEAR(B20),MONTH(B20)+1,1),"") -> 46478 | C21: =IF(A21<=Simulasi!$B$11,'Rumus Plafond + Atrib PP10 (2)'!P9,"") -> 4.7157904e+08 | D21: =IFERROR('Rumus Plafond + Atrib PP10 (2)'!R9,"") -> 4259308 | E21: =IFERROR(G21/K21,"") -> 0.74797649 | F21: =IFERROR(H21/K21,"") -> 0.25202351 | G21: =IFERROR('Rumus Plafond + Atrib PP10 (2)'!R9,"") -> 4259308 | H21: =IFERROR('Rumus Plafond + Atrib PP10 (2)'!Q9,"") -> 1435133 | I21: =IFERROR(C21/$D$7,"") -> 1.3473687 | J21: =IFERROR(($D$7-C21)/$D$7,"") -> -0.3473687 | K21: =IFERROR('Rumus Plafond + Atrib PP10 (2)'!S9,"") -> 5694441 | O21: =A21 -> 6 | P21: =B21 -> 46478 | Q21: =K21 -> 5694441 | R21: =G21 -> 4259308 | S21: =H21 -> 1435133 | T21: =C21 -> 4.7157904e+08
A22: ='Rumus Plafond + Atrib PP10 (2)'!O10 -> 7 | B22: =IF(A22<=Simulasi!$B$11,DATE(YEAR(B21),MONTH(B21)+1,1),"") -> 46508 | C22: =IF(A22<=Simulasi!$B$11,'Rumus Plafond + Atrib PP10 (2)'!P10,"") -> 4.7013099e+08 | D22: =IFERROR('Rumus Plafond + Atrib PP10 (2)'!R10,"") -> 4246385.2 | E22: =IFERROR(G22/K22,"") -> 0.74570711 | F22: =IFERROR(H22/K22,"") -> 0.25429289 | G22: =IFERROR('Rumus Plafond + Atrib PP10 (2)'!R10,"") -> 4246385.2 | H22: =IFERROR('Rumus Plafond + Atrib PP10 (2)'!Q10,"") -> 1448055.8 | I22: =IFERROR(C22/$D$7,"") -> 1.3432314 | J22: =IFERROR(($D$7-C22)/$D$7,"") -> -0.34323139 | K22: =IFERROR('Rumus Plafond + Atrib PP10 (2)'!S10,"") -> 5694441 | O22: =A22 -> 7 | P22: =B22 -> 46508 | Q22: =K22 -> 5694441 | R22: =G22 -> 4246385.2 | S22: =H22 -> 1448055.8 | T22: =C22 -> 4.7013099e+08
A23: ='Rumus Plafond + Atrib PP10 (2)'!O11 -> 8 | B23: =IF(A23<=Simulasi!$B$11,DATE(YEAR(B22),MONTH(B22)+1,1),"") -> 46539 | C23: =IF(A23<=Simulasi!$B$11,'Rumus Plafond + Atrib PP10 (2)'!P11,"") -> 4.6866989e+08 | D23: =IFERROR('Rumus Plafond + Atrib PP10 (2)'!R11,"") -> 4233346 | E23: =IFERROR(G23/K23,"") -> 0.74341731 | F23: =IFERROR(H23/K23,"") -> 0.25658269 | G23: =IFERROR('Rumus Plafond + Atrib PP10 (2)'!R11,"") -> 4233346 | H23: =IFERROR('Rumus Plafond + Atrib PP10 (2)'!Q11,"") -> 1461095 | I23: =IFERROR(C23/$D$7,"") -> 1.3390568 | J23: =IFERROR(($D$7-C23)/$D$7,"") -> -0.33905684 | K23: =IFERROR('Rumus Plafond + Atrib PP10 (2)'!S11,"") -> 5694441 | O23: =A23 -> 8 | P23: =B23 -> 46539 | Q23: =K23 -> 5694441 | R23: =G23 -> 4233346 | S23: =H23 -> 1461095 | T23: =C23 -> 4.6866989e+08
A24: ='Rumus Plafond + Atrib PP10 (2)'!O12 -> 9 | B24: =IF(A24<=Simulasi!$B$11,DATE(YEAR(B23),MONTH(B23)+1,1),"") -> 46569 | C24: =IF(A24<=Simulasi!$B$11,'Rumus Plafond + Atrib PP10 (2)'!P12,"") -> 4.6719564e+08 | D24: =IFERROR('Rumus Plafond + Atrib PP10 (2)'!R12,"") -> 4220189.4 | E24: =IFERROR(G24/K24,"") -> 0.74110688 | F24: =IFERROR(H24/K24,"") -> 0.25889312 | G24: =IFERROR('Rumus Plafond + Atrib PP10 (2)'!R12,"") -> 4220189.4 | H24: =IFERROR('Rumus Plafond + Atrib PP10 (2)'!Q12,"") -> 1474251.6 | I24: =IFERROR(C24/$D$7,"") -> 1.3348447 | J24: =IFERROR(($D$7-C24)/$D$7,"") -> -0.33484469 | K24: =IFERROR('Rumus Plafond + Atrib PP10 (2)'!S12,"") -> 5694441 | O24: =A24 -> 9 | P24: =B24 -> 46569 | Q24: =K24 -> 5694441 | R24: =G24 -> 4220189.4 | S24: =H24 -> 1474251.6 | T24: =C24 -> 4.6719564e+08
A25: ='Rumus Plafond + Atrib PP10 (2)'!O13 -> 10 | B25: =IF(A25<=Simulasi!$B$11,DATE(YEAR(B24),MONTH(B24)+1,1),"") -> 46600 | C25: =IF(A25<=Simulasi!$B$11,'Rumus Plafond + Atrib PP10 (2)'!P13,"") -> 4.6570811e+08 | D25: =IFERROR('Rumus Plafond + Atrib PP10 (2)'!R13,"") -> 4206914.3 | E25: =IFERROR(G25/K25,"") -> 0.73877565 | F25: =IFERROR(H25/K25,"") -> 0.26122435 | G25: =IFERROR('Rumus Plafond + Atrib PP10 (2)'!R13,"") -> 4206914.3 | H25: =IFERROR('Rumus Plafond + Atrib PP10 (2)'!Q13,"") -> 1487526.7 | I25: =IFERROR(C25/$D$7,"") -> 1.3305946 | J25: =IFERROR(($D$7-C25)/$D$7,"") -> -0.33059461 | K25: =IFERROR('Rumus Plafond + Atrib PP10 (2)'!S13,"") -> 5694441 | O25: =A25 -> 10 | P25: =B25 -> 46600 | Q25: =K25 -> 5694441 | R25: =G25 -> 4206914.3 | S25: =H25 -> 1487526.7 | T25: =C25 -> 4.6570811e+08
A26: ='Rumus Plafond + Atrib PP10 (2)'!O14 -> 11 | B26: =IF(A26<=Simulasi!$B$11,DATE(YEAR(B25),MONTH(B25)+1,1),"") -> 46631 | C26: =IF(A26<=Simulasi!$B$11,'Rumus Plafond + Atrib PP10 (2)'!P14,"") -> 4.6420719e+08 | D26: =IFERROR('Rumus Plafond + Atrib PP10 (2)'!R14,"") -> 4193519.7 | E26: =IFERROR(G26/K26,"") -> 0.73642342 | F26: =IFERROR(H26/K26,"") -> 0.26357658 | G26: =IFERROR('Rumus Plafond + Atrib PP10 (2)'!R14,"") -> 4193519.7 | H26: =IFERROR('Rumus Plafond + Atrib PP10 (2)'!Q14,"") -> 1500921.3 | I26: =IFERROR(C26/$D$7,"") -> 1.3263063 | J26: =IFERROR(($D$7-C26)/$D$7,"") -> -0.32630627 | K26: =IFERROR('Rumus Plafond + Atrib PP10 (2)'!S14,"") -> 5694441 | O26: =A26 -> 11 | P26: =B26 -> 46631 | Q26: =K26 -> 5694441 | R26: =G26 -> 4193519.7 | S26: =H26 -> 1500921.3 | T26: =C26 -> 4.6420719e+08
A27: ='Rumus Plafond + Atrib PP10 (2)'!O15 -> 12 | B27: =IF(A27<=Simulasi!$B$11,DATE(YEAR(B26),MONTH(B26)+1,1),"") -> 46661 | C27: =IF(A27<=Simulasi!$B$11,'Rumus Plafond + Atrib PP10 (2)'!P15,"") -> 4.6269276e+08 | D27: =IFERROR('Rumus Plafond + Atrib PP10 (2)'!R15,"") -> 4180004.5 | E27: =IFERROR(G27/K27,"") -> 0.73405002 | F27: =IFERROR(H27/K27,"") -> 0.26594998 | G27: =IFERROR('Rumus Plafond + Atrib PP10 (2)'!R15,"") -> 4180004.5 | H27: =IFERROR('Rumus Plafond + Atrib PP10 (2)'!Q15,"") -> 1514436.5 | I27: =IFERROR(C27/$D$7,"") -> 1.3219793 | J27: =IFERROR(($D$7-C27)/$D$7,"") -> -0.3219793 | K27: =IFERROR('Rumus Plafond + Atrib PP10 (2)'!S15,"") -> 5694441 | O27: =A27 -> 12 | P27: =B27 -> 46661 | Q27: =K27 -> 5694441 | R27: =G27 -> 4180004.5 | S27: =H27 -> 1514436.5 | T27: =C27 -> 4.6269276e+08
A28: ='Rumus Plafond + Atrib PP10 (2)'!O16 -> 13 | B28: =IF(A28<=Simulasi!$B$11,DATE(YEAR(B27),MONTH(B27)+1,1),"") -> 46692 | C28: =IF(A28<=Simulasi!$B$11,'Rumus Plafond + Atrib PP10 (2)'!P16,"") -> 4.6116468e+08 | D28: =IFERROR('Rumus Plafond + Atrib PP10 (2)'!R16,"") -> 4166367.6 | E28: =IFERROR(G28/K28,"") -> 0.73165525 | F28: =IFERROR(H28/K28,"") -> 0.26834475 | G28: =IFERROR('Rumus Plafond + Atrib PP10 (2)'!R16,"") -> 4166367.6 | H28: =IFERROR('Rumus Plafond + Atrib PP10 (2)'!Q16,"") -> 1528073.4 | I28: =IFERROR(C28/$D$7,"") -> 1.3176134 | J28: =IFERROR(($D$7-C28)/$D$7,"") -> -0.31761338 | K28: =IFERROR('Rumus Plafond + Atrib PP10 (2)'!S16,"") -> 5694441 | O28: =A28 -> 13 | P28: =B28 -> 46692 | Q28: =K28 -> 5694441 | R28: =G28 -> 4166367.6 | S28: =H28 -> 1528073.4 | T28: =C28 -> 4.6116468e+08
... A195: ='Rumus Plafond + Atrib PP10 (2)'!O183 -> 180 | B195: =IF(A195<=Simulasi!$B$11,DATE(YEAR(B194),MONTH(B194)+1,1),"") -> 51775 | C195: =IF(A195<=Simulasi!$B$11,'Rumus Plafond + Atrib PP10 (2)'!P183,"") -> -7.962808e-08 | D195: =IFERROR('Rumus Plafond + Atrib PP10 (2)'!R183,"") -> 40598.492 | E195: =IFERROR(G195/K195,"") -> 0.0098495164 | F195: =IFERROR(H195/K195,"") -> 0.99015048 | G195: =IFERROR('Rumus Plafond + Atrib PP10 (2)'!R183,"") -> 40598.492 | H195: =IFERROR('Rumus Plafond + Atrib PP10 (2)'!Q183,"") -> 4081278.2 | I195: =IFERROR(C195/$D$7,"") -> -2.275088e-16 | J195: =IFERROR(($D$7-C195)/$D$7,"") -> 1 | K195: =IFERROR('Rumus Plafond + Atrib PP10 (2)'!S183,"") -> 4121876.7 | O195: =A195 -> 180 | P195: =B195 -> 51775 | Q195: =K195 -> 4121876.7 | R195: =G195 -> 40598.492 | S195: =H195 -> 4081278.2 | T195: =C195 -> -7.962808e-08

Sheet Jadwal Angsuran TriBerkah (Blok
B1: Data Pembiayaan
B2: Produk | C2: : | D2: =Simulasi!B3 -> Prapen 10 Tahun | E2: Jangka waktu | F2: : | G2: =Simulasi!B11 -> 180 | H2: Price Aktif | I2: : | J2: =Simulasi!B34 -> 0.10805531
B3: Angsuran Aktif | C3: : | D3: =Simulasi!B32 -> 5694441 | E3: Tenor Aktif | F3: : | G3: ='Rumus Plafond + Atrib PP10 (2)'!C9 -> 120 | H3: Price Pensiun | I3: : | J3: =Simulasi!B35 -> 0.11936993
B4: Angsuran Pensiun | C4: : | D4: =Simulasi!B33 -> 4121876.7 | E4: Tenor Pensiun | F4: : | G4: ='Rumus Plafond + Atrib PP10 (2)'!C10 -> 60
C5: = | D5: INPUT
A6: Akad MMQ
B7: Harga/NilaiObjekAkad | C7: : | D7: 350000000 | E7: 1
B8: HishshahBANK | C8: : | D8: ='Rumus Plafond + Atrib PP3'!P3 -> 178000000 | E8: =D8/D7 -> 0.50857143
B9: HishshahNASABAH | C9: : | D9: =D7-D8 -> 172000000 | E9: =D9/D7 -> 0.49142857
B10: NisbahAwalBANK | C10: : | D10: =AVERAGE(E16:E195) -> 0.75388634
B11: NisbahAwalNASABAH | C11: : | D11: =AVERAGE(F16:F195) -> 0.24611366
B12: JangkaWaktu | C12: : | D12: =Simulasi!B11&" bulan" -> 180 bulan
A15: Ke- | B15: Tanggal | C15: Outstanding (Rp) | D15: Biaya Sewa/Ujrah Per Bulan (Rp) | E15: Nisbah Bank(%) | F15: Nisbah Nasabah (%) | G15: BagiHasil Bank (Rp) | H15: BagiHasil Nasabah (Rp) | I15: Hishshah Bank(%) | J15: Hishshah Nasabah (%) | K15: Biaya Sewa/ Ujrah Per Bulan(Rp)
A16: ='Rumus Plafond + Atrib PP10 (2)'!O4 -> 1 | B16: =DATE(YEAR(Simulasi!B5),MONTH(Simulasi!B5)+1,1) -> 46327 | C16: ='Rumus Plafond + Atrib PP3'!P4 -> 177990000 | D16: =IFERROR('Rumus Plafond + Atrib PP3'!R4,"") -> 1594295.9 | E16: =IFERROR(G16/K16,"") -> 0.99376674 | F16: =IFERROR(H16/K16,"") -> 0.006233264 | G16: =IFERROR('Rumus Plafond + Atrib PP3'!R4,"") -> 1594295.9 | H16: =IFERROR('Rumus Plafond + Atrib PP3'!Q4,"") -> 10000 | I16: =IFERROR(C16/$D$7,"") -> 0.50854286 | J16: =IFERROR(($D$7-C16)/$D$7,"") -> 0.49145714 | K16: =IFERROR('Rumus Plafond + Atrib PP3'!S4,"") -> 1604295.9
A17: ='Rumus Plafond + Atrib PP10 (2)'!O5 -> 2 | B17: =IF(A17<=Simulasi!$B$11,DATE(YEAR(B16),MONTH(B16)+1,1),"") -> 46357 | C17: =IF(A17<=Simulasi!$B$11,'Rumus Plafond + Atrib PP3'!P5,"") -> 1.7797991e+08 | D17: =IFERROR('Rumus Plafond + Atrib PP3'!R5,"") -> 1594206.4 | E17: =IFERROR(G17/K17,"") -> 0.99371091 | F17: =IFERROR(H17/K17,"") -> 0.0062890936 | G17: =IFERROR('Rumus Plafond + Atrib PP3'!R5,"") -> 1594206.4 | H17: =IFERROR('Rumus Plafond + Atrib PP3'!Q5,"") -> 10089.567 | I17: =IFERROR(C17/$D$7,"") -> 0.50851403 | J17: =IFERROR(($D$7-C17)/$D$7,"") -> 0.49148597 | K17: =IFERROR('Rumus Plafond + Atrib PP3'!S5,"") -> 1604295.9
A18: ='Rumus Plafond + Atrib PP10 (2)'!O6 -> 3 | B18: =IF(A18<=Simulasi!$B$11,DATE(YEAR(B17),MONTH(B17)+1,1),"") -> 46388 | C18: =IF(A18<=Simulasi!$B$11,'Rumus Plafond + Atrib PP3'!P6,"") -> 1.7796973e+08 | D18: =IFERROR('Rumus Plafond + Atrib PP3'!R6,"") -> 1594116 | E18: =IFERROR(G18/K18,"") -> 0.99365458 | F18: =IFERROR(H18/K18,"") -> 0.0063454232 | G18: =IFERROR('Rumus Plafond + Atrib PP3'!R6,"") -> 1594116 | H18: =IFERROR('Rumus Plafond + Atrib PP3'!Q6,"") -> 10179.937 | I18: =IFERROR(C18/$D$7,"") -> 0.50848494 | J18: =IFERROR(($D$7-C18)/$D$7,"") -> 0.49151506 | K18: =IFERROR('Rumus Plafond + Atrib PP3'!S6,"") -> 1604295.9
A19: ='Rumus Plafond + Atrib PP10 (2)'!O7 -> 4 | B19: =IF(A19<=Simulasi!$B$11,DATE(YEAR(B18),MONTH(B18)+1,1),"") -> 46419 | C19: =IF(A19<=Simulasi!$B$11,'Rumus Plafond + Atrib PP3'!P7,"") -> 1.7795946e+08 | D19: =IFERROR('Rumus Plafond + Atrib PP3'!R7,"") -> 1594024.8 | E19: =IFERROR(G19/K19,"") -> 0.99359774 | F19: =IFERROR(H19/K19,"") -> 0.0064022574 | G19: =IFERROR('Rumus Plafond + Atrib PP3'!R7,"") -> 1594024.8 | H19: =IFERROR('Rumus Plafond + Atrib PP3'!Q7,"") -> 10271.115 | I19: =IFERROR(C19/$D$7,"") -> 0.5084556 | J19: =IFERROR(($D$7-C19)/$D$7,"") -> 0.4915444 | K19: =IFERROR('Rumus Plafond + Atrib PP3'!S7,"") -> 1604295.9
A20: ='Rumus Plafond + Atrib PP10 (2)'!O8 -> 5 | B20: =IF(A20<=Simulasi!$B$11,DATE(YEAR(B19),MONTH(B19)+1,1),"") -> 46447 | C20: =IF(A20<=Simulasi!$B$11,'Rumus Plafond + Atrib PP3'!P8,"") -> 1.779491e+08 | D20: =IFERROR('Rumus Plafond + Atrib PP3'!R8,"") -> 1593932.8 | E20: =IFERROR(G20/K20,"") -> 0.9935404 | F20: =IFERROR(H20/K20,"") -> 0.0064596006 | G20: =IFERROR('Rumus Plafond + Atrib PP3'!R8,"") -> 1593932.8 | H20: =IFERROR('Rumus Plafond + Atrib PP3'!Q8,"") -> 10363.111 | I20: =IFERROR(C20/$D$7,"") -> 0.50842599 | J20: =IFERROR(($D$7-C20)/$D$7,"") -> 0.49157401 | K20: =IFERROR('Rumus Plafond + Atrib PP3'!S8,"") -> 1604295.9
A21: ='Rumus Plafond + Atrib PP10 (2)'!O9 -> 6 | B21: =IF(A21<=Simulasi!$B$11,DATE(YEAR(B20),MONTH(B20)+1,1),"") -> 46478 | C21: =IF(A21<=Simulasi!$B$11,'Rumus Plafond + Atrib PP3'!P9,"") -> 1.7793864e+08 | D21: =IFERROR('Rumus Plafond + Atrib PP3'!R9,"") -> 1593840 | E21: =IFERROR(G21/K21,"") -> 0.99348254 | F21: =IFERROR(H21/K21,"") -> 0.0065174574 | G21: =IFERROR('Rumus Plafond + Atrib PP3'!R9,"") -> 1593840 | H21: =IFERROR('Rumus Plafond + Atrib PP3'!Q9,"") -> 10455.93 | I21: =IFERROR(C21/$D$7,"") -> 0.50839612 | J21: =IFERROR(($D$7-C21)/$D$7,"") -> 0.49160388 | K21: =IFERROR('Rumus Plafond + Atrib PP3'!S9,"") -> 1604295.9
A22: ='Rumus Plafond + Atrib PP10 (2)'!O10 -> 7 | B22: =IF(A22<=Simulasi!$B$11,DATE(YEAR(B21),MONTH(B21)+1,1),"") -> 46508 | C22: =IF(A22<=Simulasi!$B$11,'Rumus Plafond + Atrib PP3'!P10,"") -> 1.7792809e+08 | D22: =IFERROR('Rumus Plafond + Atrib PP3'!R10,"") -> 1593746.3 | E22: =IFERROR(G22/K22,"") -> 0.99342417 | F22: =IFERROR(H22/K22,"") -> 0.0065758324 | G22: =IFERROR('Rumus Plafond + Atrib PP3'!R10,"") -> 1593746.3 | H22: =IFERROR('Rumus Plafond + Atrib PP3'!Q10,"") -> 10549.581 | I22: =IFERROR(C22/$D$7,"") -> 0.50836597 | J22: =IFERROR(($D$7-C22)/$D$7,"") -> 0.49163403 | K22: =IFERROR('Rumus Plafond + Atrib PP3'!S10,"") -> 1604295.9
A23: ='Rumus Plafond + Atrib PP10 (2)'!O11 -> 8 | B23: =IF(A23<=Simulasi!$B$11,DATE(YEAR(B22),MONTH(B22)+1,1),"") -> 46539 | C23: =IF(A23<=Simulasi!$B$11,'Rumus Plafond + Atrib PP3'!P11,"") -> 1.7791745e+08 | D23: =IFERROR('Rumus Plafond + Atrib PP3'!R11,"") -> 1593651.9 | E23: =IFERROR(G23/K23,"") -> 0.99336527 | F23: =IFERROR(H23/K23,"") -> 0.0066347303 | G23: =IFERROR('Rumus Plafond + Atrib PP3'!R11,"") -> 1593651.9 | H23: =IFERROR('Rumus Plafond + Atrib PP3'!Q11,"") -> 10644.071 | I23: =IFERROR(C23/$D$7,"") -> 0.50833556 | J23: =IFERROR(($D$7-C23)/$D$7,"") -> 0.49166444 | K23: =IFERROR('Rumus Plafond + Atrib PP3'!S11,"") -> 1604295.9
A24: ='Rumus Plafond + Atrib PP10 (2)'!O12 -> 9 | B24: =IF(A24<=Simulasi!$B$11,DATE(YEAR(B23),MONTH(B23)+1,1),"") -> 46569 | C24: =IF(A24<=Simulasi!$B$11,'Rumus Plafond + Atrib PP3'!P12,"") -> 1.7790671e+08 | D24: =IFERROR('Rumus Plafond + Atrib PP3'!R12,"") -> 1593556.5 | E24: =IFERROR(G24/K24,"") -> 0.99330584 | F24: =IFERROR(H24/K24,"") -> 0.0066941557 | G24: =IFERROR('Rumus Plafond + Atrib PP3'!R12,"") -> 1593556.5 | H24: =IFERROR('Rumus Plafond + Atrib PP3'!Q12,"") -> 10739.407 | I24: =IFERROR(C24/$D$7,"") -> 0.50830488 | J24: =IFERROR(($D$7-C24)/$D$7,"") -> 0.49169512 | K24: =IFERROR('Rumus Plafond + Atrib PP3'!S12,"") -> 1604295.9
A25: ='Rumus Plafond + Atrib PP10 (2)'!O13 -> 10 | B25: =IF(A25<=Simulasi!$B$11,DATE(YEAR(B24),MONTH(B24)+1,1),"") -> 46600 | C25: =IF(A25<=Simulasi!$B$11,'Rumus Plafond + Atrib PP3'!P13,"") -> 1.7789587e+08 | D25: =IFERROR('Rumus Plafond + Atrib PP3'!R13,"") -> 1593460.3 | E25: =IFERROR(G25/K25,"") -> 0.99324589 | F25: =IFERROR(H25/K25,"") -> 0.0067541134 | G25: =IFERROR('Rumus Plafond + Atrib PP3'!R13,"") -> 1593460.3 | H25: =IFERROR('Rumus Plafond + Atrib PP3'!Q13,"") -> 10835.597 | I25: =IFERROR(C25/$D$7,"") -> 0.50827392 | J25: =IFERROR(($D$7-C25)/$D$7,"") -> 0.49172608 | K25: =IFERROR('Rumus Plafond + Atrib PP3'!S13,"") -> 1604295.9
A26: ='Rumus Plafond + Atrib PP10 (2)'!O14 -> 11 | B26: =IF(A26<=Simulasi!$B$11,DATE(YEAR(B25),MONTH(B25)+1,1),"") -> 46631 | C26: =IF(A26<=Simulasi!$B$11,'Rumus Plafond + Atrib PP3'!P14,"") -> 1.7788494e+08 | D26: =IFERROR('Rumus Plafond + Atrib PP3'!R14,"") -> 1593363.3 | E26: =IFERROR(G26/K26,"") -> 0.99318539 | F26: =IFERROR(H26/K26,"") -> 0.0068146081 | G26: =IFERROR('Rumus Plafond + Atrib PP3'!R14,"") -> 1593363.3 | H26: =IFERROR('Rumus Plafond + Atrib PP3'!Q14,"") -> 10932.648 | I26: =IFERROR(C26/$D$7,"") -> 0.50824268 | J26: =IFERROR(($D$7-C26)/$D$7,"") -> 0.49175732 | K26: =IFERROR('Rumus Plafond + Atrib PP3'!S14,"") -> 1604295.9
A27: ='Rumus Plafond + Atrib PP10 (2)'!O15 -> 12 | B27: =IF(A27<=Simulasi!$B$11,DATE(YEAR(B26),MONTH(B26)+1,1),"") -> 46661 | C27: =IF(A27<=Simulasi!$B$11,'Rumus Plafond + Atrib PP3'!P15,"") -> 1.7787391e+08 | D27: =IFERROR('Rumus Plafond + Atrib PP3'!R15,"") -> 1593265.4 | E27: =IFERROR(G27/K27,"") -> 0.99312436 | F27: =IFERROR(H27/K27,"") -> 0.0068756446 | G27: =IFERROR('Rumus Plafond + Atrib PP3'!R15,"") -> 1593265.4 | H27: =IFERROR('Rumus Plafond + Atrib PP3'!Q15,"") -> 11030.569 | I27: =IFERROR(C27/$D$7,"") -> 0.50821117 | J27: =IFERROR(($D$7-C27)/$D$7,"") -> 0.49178883 | K27: =IFERROR('Rumus Plafond + Atrib PP3'!S15,"") -> 1604295.9
A28: ='Rumus Plafond + Atrib PP10 (2)'!O16 -> 13 | B28: =IF(A28<=Simulasi!$B$11,DATE(YEAR(B27),MONTH(B27)+1,1),"") -> 46692 | C28: =IF(A28<=Simulasi!$B$11,'Rumus Plafond + Atrib PP3'!P16,"") -> 1.7786278e+08 | D28: =IFERROR('Rumus Plafond + Atrib PP3'!R16,"") -> 1593166.6 | E28: =IFERROR(G28/K28,"") -> 0.99306277 | F28: =IFERROR(H28/K28,"") -> 0.0069372278 | G28: =IFERROR('Rumus Plafond + Atrib PP3'!R16,"") -> 1593166.6 | H28: =IFERROR('Rumus Plafond + Atrib PP3'!Q16,"") -> 11129.366 | I28: =IFERROR(C28/$D$7,"") -> 0.50817937 | J28: =IFERROR(($D$7-C28)/$D$7,"") -> 0.49182063 | K28: =IFERROR('Rumus Plafond + Atrib PP3'!S16,"") -> 1604295.9
... A195: ='Rumus Plafond + Atrib PP10 (2)'!O183 -> 180 | B195: =IF(A195<=Simulasi!$B$11,DATE(YEAR(B194),MONTH(B194)+1,1),"") -> 51775 | C195: =IF(A195<=Simulasi!$B$11,'Rumus Plafond + Atrib PP3'!P183,"") -> 0 | D195: =IFERROR('Rumus Plafond + Atrib PP3'!R183,"") -> 47233.161 | E195: =IFERROR(G195/K195,"") -> 0.011540267 | F195: =IFERROR(H195/K195,"") -> 0.98845973 | G195: =IFERROR('Rumus Plafond + Atrib PP3'!R183,"") -> 47233.161 | H195: =IFERROR('Rumus Plafond + Atrib PP3'!Q183,"") -> 4045666.9 | I195: =IFERROR(C195/$D$7,"") -> 0 | J195: =IFERROR(($D$7-C195)/$D$7,"") -> 1 | K195: =IFERROR('Rumus Plafond + Atrib PP3'!S183,"") -> 4092900
A196: ='Rumus Plafond + Atrib PP3'!O184 -> 181 | B196: =IF(A196<=Simulasi!$B$11,DATE(YEAR(B195),MONTH(B195)+1,1),"") | C196: =IF(A196<=Simulasi!$B$11,'Rumus Plafond + Atrib PP3'!P184,"") | D196: =IFERROR('Rumus Plafond + Atrib PP3'!R184,"") -> 0 | E196: =IFERROR(G196/K196,"") | F196: =IFERROR(H196/K196,"") | G196: =IFERROR('Rumus Plafond + Atrib PP3'!R184,"") -> 0 | H196: =IFERROR('Rumus Plafond + Atrib PP3'!Q184,"") -> 0 | I196: =IFERROR(C196/$D$7,"") | J196: =IFERROR(($D$7-C196)/$D$7,"") | K196: =IFERROR('Rumus Plafond + Atrib PP3'!S184,"") -> 0
A197: ='Rumus Plafond + Atrib PP3'!O185 -> 182 | B197: =IF(A197<=Simulasi!$B$11,DATE(YEAR(B196),MONTH(B196)+1,1),"") | C197: =IF(A197<=Simulasi!$B$11,'Rumus Plafond + Atrib PP3'!P185,"") | D197: =IFERROR('Rumus Plafond + Atrib PP3'!R185,"") -> 0 | E197: =IFERROR(G197/K197,"") | F197: =IFERROR(H197/K197,"") | G197: =IFERROR('Rumus Plafond + Atrib PP3'!R185,"") -> 0 | H197: =IFERROR('Rumus Plafond + Atrib PP3'!Q185,"") -> 0 | I197: =IFERROR(C197/$D$7,"") | J197: =IFERROR(($D$7-C197)/$D$7,"") | K197: =IFERROR('Rumus Plafond + Atrib PP3'!S185,"") -> 0
A198: ='Rumus Plafond + Atrib PP3'!O186 -> 183 | B198: =IF(A198<=Simulasi!$B$11,DATE(YEAR(B197),MONTH(B197)+1,1),"") | C198: =IF(A198<=Simulasi!$B$11,'Rumus Plafond + Atrib PP3'!P186,"") | D198: =IFERROR('Rumus Plafond + Atrib PP3'!R186,"") -> 0 | E198: =IFERROR(G198/K198,"") | F198: =IFERROR(H198/K198,"") | G198: =IFERROR('Rumus Plafond + Atrib PP3'!R186,"") -> 0 | H198: =IFERROR('Rumus Plafond + Atrib PP3'!Q186,"") -> 0 | I198: =IFERROR(C198/$D$7,"") | J198: =IFERROR(($D$7-C198)/$D$7,"") | K198: =IFERROR('Rumus Plafond + Atrib PP3'!S186,"") -> 0
A199: ='Rumus Plafond + Atrib PP3'!O187 -> 184 | B199: =IF(A199<=Simulasi!$B$11,DATE(YEAR(B198),MONTH(B198)+1,1),"") | C199: =IF(A199<=Simulasi!$B$11,'Rumus Plafond + Atrib PP3'!P187,"") | D199: =IFERROR('Rumus Plafond + Atrib PP3'!R187,"") -> 0 | E199: =IFERROR(G199/K199,"") | F199: =IFERROR(H199/K199,"") | G199: =IFERROR('Rumus Plafond + Atrib PP3'!R187,"") -> 0 | H199: =IFERROR('Rumus Plafond + Atrib PP3'!Q187,"") -> 0 | I199: =IFERROR(C199/$D$7,"") | J199: =IFERROR(($D$7-C199)/$D$7,"") | K199: =IFERROR('Rumus Plafond + Atrib PP3'!S187,"") -> 0
A200: ='Rumus Plafond + Atrib PP3'!O188 -> 185 | B200: =IF(A200<=Simulasi!$B$11,DATE(YEAR(B199),MONTH(B199)+1,1),"") | C200: =IF(A200<=Simulasi!$B$11,'Rumus Plafond + Atrib PP3'!P188,"") | D200: =IFERROR('Rumus Plafond + Atrib PP3'!R188,"") -> 0 | E200: =IFERROR(G200/K200,"") | F200: =IFERROR(H200/K200,"") | G200: =IFERROR('Rumus Plafond + Atrib PP3'!R188,"") -> 0 | H200: =IFERROR('Rumus Plafond + Atrib PP3'!Q188,"") -> 0 | I200: =IFERROR(C200/$D$7,"") | J200: =IFERROR(($D$7-C200)/$D$7,"") | K200: =IFERROR('Rumus Plafond + Atrib PP3'!S188,"") -> 0
A201: ='Rumus Plafond + Atrib PP3'!O189 -> 186 | B201: =IF(A201<=Simulasi!$B$11,DATE(YEAR(B200),MONTH(B200)+1,1),"") | C201: =IF(A201<=Simulasi!$B$11,'Rumus Plafond + Atrib PP3'!P189,"") | D201: =IFERROR('Rumus Plafond + Atrib PP3'!R189,"") -> 0 | E201: =IFERROR(G201/K201,"") | F201: =IFERROR(H201/K201,"") | G201: =IFERROR('Rumus Plafond + Atrib PP3'!R189,"") -> 0 | H201: =IFERROR('Rumus Plafond + Atrib PP3'!Q189,"") -> 0 | I201: =IFERROR(C201/$D$7,"") | J201: =IFERROR(($D$7-C201)/$D$7,"") | K201: =IFERROR('Rumus Plafond + Atrib PP3'!S189,"") -> 0
A202: ='Rumus Plafond + Atrib PP3'!O190 -> 187 | B202: =IF(A202<=Simulasi!$B$11,DATE(YEAR(B201),MONTH(B201)+1,1),"") | C202: =IF(A202<=Simulasi!$B$11,'Rumus Plafond + Atrib PP3'!P190,"") | D202: =IFERROR('Rumus Plafond + Atrib PP3'!R190,"") -> 0 | E202: =IFERROR(G202/K202,"") | F202: =IFERROR(H202/K202,"") | G202: =IFERROR('Rumus Plafond + Atrib PP3'!R190,"") -> 0 | H202: =IFERROR('Rumus Plafond + Atrib PP3'!Q190,"") -> 0 | I202: =IFERROR(C202/$D$7,"") | J202: =IFERROR(($D$7-C202)/$D$7,"") | K202: =IFERROR('Rumus Plafond + Atrib PP3'!S190,"") -> 0
A203: ='Rumus Plafond + Atrib PP3'!O191 -> 188 | B203: =IF(A203<=Simulasi!$B$11,DATE(YEAR(B202),MONTH(B202)+1,1),"") | C203: =IF(A203<=Simulasi!$B$11,'Rumus Plafond + Atrib PP3'!P191,"") | D203: =IFERROR('Rumus Plafond + Atrib PP3'!R191,"") -> 0 | E203: =IFERROR(G203/K203,"") | F203: =IFERROR(H203/K203,"") | G203: =IFERROR('Rumus Plafond + Atrib PP3'!R191,"") -> 0 | H203: =IFERROR('Rumus Plafond + Atrib PP3'!Q191,"") -> 0 | I203: =IFERROR(C203/$D$7,"") | J203: =IFERROR(($D$7-C203)/$D$7,"") | K203: =IFERROR('Rumus Plafond + Atrib PP3'!S191,"") -> 0
A204: ='Rumus Plafond + Atrib PP3'!O192 -> 189 | B204: =IF(A204<=Simulasi!$B$11,DATE(YEAR(B203),MONTH(B203)+1,1),"") | C204: =IF(A204<=Simulasi!$B$11,'Rumus Plafond + Atrib PP3'!P192,"") | D204: =IFERROR('Rumus Plafond + Atrib PP3'!R192,"") -> 0 | E204: =IFERROR(G204/K204,"") | F204: =IFERROR(H204/K204,"") | G204: =IFERROR('Rumus Plafond + Atrib PP3'!R192,"") -> 0 | H204: =IFERROR('Rumus Plafond + Atrib PP3'!Q192,"") -> 0 | I204: =IFERROR(C204/$D$7,"") | J204: =IFERROR(($D$7-C204)/$D$7,"") | K204: =IFERROR('Rumus Plafond + Atrib PP3'!S192,"") -> 0
A205: ='Rumus Plafond + Atrib PP3'!O193 -> 190 | B205: =IF(A205<=Simulasi!$B$11,DATE(YEAR(B204),MONTH(B204)+1,1),"") | C205: =IF(A205<=Simulasi!$B$11,'Rumus Plafond + Atrib PP3'!P193,"") | D205: =IFERROR('Rumus Plafond + Atrib PP3'!R193,"") -> 0 | E205: =IFERROR(G205/K205,"") | F205: =IFERROR(H205/K205,"") | G205: =IFERROR('Rumus Plafond + Atrib PP3'!R193,"") -> 0 | H205: =IFERROR('Rumus Plafond + Atrib PP3'!Q193,"") -> 0 | I205: =IFERROR(C205/$D$7,"") | J205: =IFERROR(($D$7-C205)/$D$7,"") | K205: =IFERROR('Rumus Plafond + Atrib PP3'!S193,"") -> 0
A206: ='Rumus Plafond + Atrib PP3'!O194 -> 191 | B206: =IF(A206<=Simulasi!$B$11,DATE(YEAR(B205),MONTH(B205)+1,1),"") | C206: =IF(A206<=Simulasi!$B$11,'Rumus Plafond + Atrib PP3'!P194,"") | D206: =IFERROR('Rumus Plafond + Atrib PP3'!R194,"") -> 0 | E206: =IFERROR(G206/K206,"") | F206: =IFERROR(H206/K206,"") | G206: =IFERROR('Rumus Plafond + Atrib PP3'!R194,"") -> 0 | H206: =IFERROR('Rumus Plafond + Atrib PP3'!Q194,"") -> 0 | I206: =IFERROR(C206/$D$7,"") | J206: =IFERROR(($D$7-C206)/$D$7,"") | K206: =IFERROR('Rumus Plafond + Atrib PP3'!S194,"") -> 0
A207: ='Rumus Plafond + Atrib PP3'!O195 -> 192 | B207: =IF(A207<=Simulasi!$B$11,DATE(YEAR(B206),MONTH(B206)+1,1),"") | C207: =IF(A207<=Simulasi!$B$11,'Rumus Plafond + Atrib PP3'!P195,"") | D207: =IFERROR('Rumus Plafond + Atrib PP3'!R195,"") -> 0 | E207: =IFERROR(G207/K207,"") | F207: =IFERROR(H207/K207,"") | G207: =IFERROR('Rumus Plafond + Atrib PP3'!R195,"") -> 0 | H207: =IFERROR('Rumus Plafond + Atrib PP3'!Q195,"") -> 0 | I207: =IFERROR(C207/$D$7,"") | J207: =IFERROR(($D$7-C207)/$D$7,"") | K207: =IFERROR('Rumus Plafond + Atrib PP3'!S195,"") -> 0
... A255: ='Rumus Plafond + Atrib PP3'!O243 -> 240 | B255: =IF(A255<=Simulasi!$B$11,DATE(YEAR(B254),MONTH(B254)+1,1),"") | C255: =IF(A255<=Simulasi!$B$11,'Rumus Plafond + Atrib PP3'!P243,"") | D255: =IFERROR('Rumus Plafond + Atrib PP3'!R243,"") -> 0 | E255: =IFERROR(G255/K255,"") | F255: =IFERROR(H255/K255,"") | G255: =IFERROR('Rumus Plafond + Atrib PP3'!R243,"") -> 0 | H255: =IFERROR('Rumus Plafond + Atrib PP3'!Q243,"") -> 0 | I255: =IFERROR(C255/$D$7,"") | J255: =IFERROR(($D$7-C255)/$D$7,"") | K255: =IFERROR('Rumus Plafond + Atrib PP3'!S243,"") -> 0

Sheet Rumus Plafond + Atrib PP3
B1: DATA DIKETAHUI PP3th-Non Payroll | I1: fx=C43-J3 | J1: fx=L3-K3 | K1: fx=$C$53/12*C43 | L1: fx=$C$54 | O1: Jika plafon lebih besar, maka bisa digunakan untuk menghitung angsuran
B2: Gaji Aktif | C2: ='Rumus Plafond + Atrib PP10 (2)'!C2 -> 8134916 | H2: tenor ke- | I2: pokok | J2: angsuran pokok | K2: angsuran margin | L2: total angsuran | O2: tenor ke- | P2: pokok/plafon disetujui | Q2: angsuran pokok | R2: angsuran margin | S2: total angsuran | U2: Kalkulasi Angsuran Aktif
B3: Manf Pensiun | C3: ='Rumus Plafond + Atrib PP10 (2)'!C3 -> 4600000 | H3: 1 | I3: =C44-J3 -> 7.1273706e+08 | J3: =L3-K3 -> -4737060.9 | K3: =$C$54/12*C44 -> 6341356.8 | L3: =$C$55 -> 1604295.9 | O3: 0 | P3: =IF(Simulasi!C14="1",MIN(C14,C20),MIN(C14,C46)) -> 178000000 | U3: Angsuran Pokok | V3: 10000
B4: DBR Aktif | C4: ='Rumus Plafond + Atrib PP10 (2)'!C4 -> 70% | I4: fx=I3-J5 | J4: fx=L5-K5 | K4: fx=$C$53/12*I3 | L4: fx=L3 | O4: 1 | P4: =P3-Q4 -> 177990000 | Q4: =S4-R4 -> 10000 | R4: =IF(O4<=$C$9,P3*$V$6/12,P3*$V$16/12) -> 1594295.9 | S4: =IFERROR(IF(O4<=$C$8,IF(O4<=$C$9,$V$7,$V$17),0),0) -> 1604295.9 | U4: Margin | V4: =C11/12*P3 -> 1372083.3
B5: DSR Pensiun | C5: ='Rumus Plafond + Atrib PP10 (2)'!C5 -> 90% | H5: 2 | I5: =I3-J5 -> 7.1751655e+08 | J5: =L5-K5 -> -4779489.4 | K5: =$C$54/12*I3 -> 6383785.4 | L5: =L3 -> 1604295.9 | O5: 2 | P5: =P4-Q5 -> 1.7797991e+08 | Q5: =S5-R5 -> 10089.567 | R5: =IF(O5<=$C$9,P4*$V$6/12,P4*$V$16/12) -> 1594206.4 | S5: =IFERROR(IF(O5<=$C$8,IF(O5<=$C$9,$V$7,$V$17),0),0) -> 1604295.9 | U5: Atrib per bln | V5: =C13/C8 -> 222212.59
B6: Akseptasi Aktif | C6: =VLOOKUP(Simulasi!C4,Simulasi!$F$4:$G$6,2,FALSE) -> 5694441.2 | D6: fx=C2*C4 | H6: 3 | I6: =I5-J6 -> 7.2233885e+08 | J6: =L6-K6 -> -4822298 | K6: =$C$54/12*I5 -> 6426593.9 | L6: =L5 -> 1604295.9 | O6: 3 | P6: =P5-Q6 -> 1.7796973e+08 | Q6: =S6-R6 -> 10179.937 | R6: =IF(O6<=$C$9,P5*$V$6/12,P5*$V$16/12) -> 1594116 | S6: =IFERROR(IF(O6<=$C$8,IF(O6<=$C$9,$V$7,$V$17),0),0) -> 1604295.9 | U6: Rate | V6: =(V4+V5)/P3*12 -> 0.10748062
B7: Akseptasi Pensiun | C7: =C3*C5 -> 4140000 | D7: fx=C3*C5 | H7: 4 | I7: =I6-J7 -> 7.2720434e+08 | J7: =L7-K7 -> -4865489.9 | K7: =$C$54/12*I6 -> 6469785.9 | L7: =L6 -> 1604295.9 | O7: 4 | P7: =P6-Q7 -> 1.7795946e+08 | Q7: =S7-R7 -> 10271.115 | R7: =IF(O7<=$C$9,P6*$V$6/12,P6*$V$16/12) -> 1594024.8 | S7: =IFERROR(IF(O7<=$C$8,IF(O7<=$C$9,$V$7,$V$17),0),0) -> 1604295.9 | U7: Angsuran Pokok Aktif | V7: =SUM(V3:V5) -> 1604295.9
B8: Tenor | C8: ='Rumus Plafond + Atrib PP10 (2)'!C8 -> 180 | H8: 5 | I8: =I7-J8 -> 7.3211341e+08 | J8: =L8-K8 -> -4909068.8 | K8: =$C$54/12*I7 -> 6513364.7 | L8: =L7 -> 1604295.9 | O8: 5 | P8: =P7-Q8 -> 1.779491e+08 | Q8: =S8-R8 -> 10363.111 | R8: =IF(O8<=$C$9,P7*$V$6/12,P7*$V$16/12) -> 1593932.8 | S8: =IFERROR(IF(O8<=$C$8,IF(O8<=$C$9,$V$7,$V$17),0),0) -> 1604295.9
B9: Tenor Aktif | C9: ='Rumus Plafond + Atrib PP10 (2)'!C9 -> 120 | H9: 6 | I9: =I8-J9 -> 7.3706644e+08 | J9: =L9-K9 -> -4953037.9 | K9: =$C$54/12*I8 -> 6557333.8 | L9: =L8 -> 1604295.9 | O9: 6 | P9: =P8-Q9 -> 1.7793864e+08 | Q9: =S9-R9 -> 10455.93 | R9: =IF(O9<=$C$9,P8*$V$6/12,P8*$V$16/12) -> 1593840 | S9: =IFERROR(IF(O9<=$C$8,IF(O9<=$C$9,$V$7,$V$17),0),0) -> 1604295.9 | U9: Kalkulasi Angsuran Pensiun
B10: Tenor Pensiun | C10: =C8-C9 -> 60 | H10: 7 | I10: =I9-J10 -> 7.4206385e+08 | J10: =L10-K10 -> -4997400.9 | K10: =$C$54/12*I9 -> 6601696.8 | L10: =L9 -> 1604295.9 | O10: 7 | P10: =P9-Q10 -> 1.7792809e+08 | Q10: =S10-R10 -> 10549.581 | R10: =IF(O10<=$C$9,P9*$V$6/12,P9*$V$16/12) -> 1593746.3 | S10: =IFERROR(IF(O10<=$C$8,IF(O10<=$C$9,$V$7,$V$17),0),0) -> 1604295.9 | U10: Sisa OS Pensiun | V10: =VLOOKUP(C9,O4:P183,2,FALSE) -> 1.7586145e+08
B11: rate aktif | C11: =Simulasi!B12 -> 0.0925 | H11: 8 | I11: =I10-J11 -> 7.4710601e+08 | J11: =L11-K11 -> -5042161.2 | K11: =$C$54/12*I10 -> 6646457.1 | L11: =L10 -> 1604295.9 | O11: 8 | P11: =P10-Q11 -> 1.7791745e+08 | Q11: =S11-R11 -> 10644.071 | R11: =IF(O11<=$C$9,P10*$V$6/12,P10*$V$16/12) -> 1593651.9 | S11: =IFERROR(IF(O11<=$C$8,IF(O11<=$C$9,$V$7,$V$17),0),0) -> 1604295.9 | U11: Atribusi per bulan | V11: =C13/C8 -> 222212.59
B12: rate pen | C12: =Simulasi!B13 -> 0.105 | H12: 9 | I12: =I11-J12 -> 7.5219333e+08 | J12: =L12-K12 -> -5087322.4 | K12: =$C$54/12*I11 -> 6691618.3 | L12: =L11 -> 1604295.9 | O12: 9 | P12: =P11-Q12 -> 1.7790671e+08 | Q12: =S12-R12 -> 10739.407 | R12: =IF(O12<=$C$9,P11*$V$6/12,P11*$V$16/12) -> 1593556.5 | S12: =IFERROR(IF(O12<=$C$8,IF(O12<=$C$9,$V$7,$V$17),0),0) -> 1604295.9 | U12: Rate Awal | V12: =C12 -> 0.105
B13: Atribusi | C13: =IF(Simulasi!$C$14="2",Simulasi!B21,0) -> 39998267 | H13: 10 | I13: =I12-J13 -> 7.5732622e+08 | J13: =L13-K13 -> -5132888.1 | K13: =$C$54/12*I12 -> 6737184.1 | L13: =L12 -> 1604295.9 | O13: 10 | P13: =P12-Q13 -> 1.7789587e+08 | Q13: =S13-R13 -> 10835.597 | R13: =IF(O13<=$C$9,P12*$V$6/12,P12*$V$16/12) -> 1593460.3 | S13: =IFERROR(IF(O13<=$C$8,IF(O13<=$C$9,$V$7,$V$17),0),0) -> 1604295.9 | U13: Periode pensiun | V13: =C10 -> 60
B14: Plafon Pengajuan | C14: =Simulasi!B10 -> 480000000 | O14: 11 | P14: =P13-Q14 -> 1.7788494e+08 | Q14: =S14-R14 -> 10932.648 | R14: =IF(O14<=$C$9,P13*$V$6/12,P13*$V$16/12) -> 1593363.3 | S14: =IFERROR(IF(O14<=$C$8,IF(O14<=$C$9,$V$7,$V$17),0),0) -> 1604295.9 | U14: Angsuran | V14: =PMT(V12/12,V13,-V10,0,0) -> 3779948.4 | W14: 5007084.3
H15: 11 | I15: =I13-J15 -> 7.6250508e+08 | J15: =L15-K15 -> -5178862 | K15: =$C$54/12*I13 -> 6783157.9 | L15: =L13 -> 1604295.9 | O15: 12 | P15: =P14-Q15 -> 1.7787391e+08 | Q15: =S15-R15 -> 11030.569 | R15: =IF(O15<=$C$9,P14*$V$6/12,P14*$V$16/12) -> 1593265.4 | S15: =IFERROR(IF(O15<=$C$8,IF(O15<=$C$9,$V$7,$V$17),0),0) -> 1604295.9 | U15: Final | V15: =V11+V14 -> 4002161
A16: 1 | B16: SKEMA NO ATRIB Perhitungan plafon maksimal dilakukan dengan menghitung plafon maksimal saat Aktif dan plafond maksimal saat Pensiun, kemudian dibandingkan dan mengambil plafond yang paling kecil sebagai rekomendasi plafon maksimal. | H16: 12 | I16: =I15-J16 -> 7.6773033e+08 | J16: =L16-K16 -> -5225247.6 | K16: =$C$54/12*I15 -> 6829543.5 | L16: =L15 -> 1604295.9 | O16: 13 | P16: =P15-Q16 -> 1.7786278e+08 | Q16: =S16-R16 -> 11129.366 | R16: =IF(O16<=$C$9,P15*$V$6/12,P15*$V$16/12) -> 1593166.6 | S16: =IFERROR(IF(O16<=$C$8,IF(O16<=$C$9,$V$7,$V$17),0),0) -> 1604295.9 | U16: Rate Atrib | V16: =(IF(V11>0,ROUND(RATE(V13,V15,-V10,0,0,0.01)*12*10000, )/10000,RATE(V13,V15,-V10,0,0,0.01)*12)+IF(C13>0,0.01,0)) -> 0.1401
H17: 13 | I17: =I16-J17 -> 7.7300238e+08 | J17: =L17-K17 -> -5272048.6 | K17: =$C$54/12*I16 -> 6876344.6 | L17: =L16 -> 1604295.9 | O17: 14 | P17: =P16-Q17 -> 1.7785155e+08 | Q17: =S17-R17 -> 11229.049 | R17: =IF(O17<=$C$9,P16*$V$6/12,P16*$V$16/12) -> 1593066.9 | S17: =IFERROR(IF(O17<=$C$8,IF(O17<=$C$9,$V$7,$V$17),0),0) -> 1604295.9 | U17: Angsuran Final Pen | V17: =PMT(V16/12,V13,-V10,0,0) -> 4092900
H18: 14 | I18: =I17-J18 -> 7.7832164e+08 | J18: =L18-K18 -> -5319268.9 | K18: =$C$54/12*I17 -> 6923564.8 | L18: =L17 -> 1604295.9 | O18: 15 | P18: =P17-Q18 -> 1.7784022e+08 | Q18: =S18-R18 -> 11329.624 | R18: =IF(O18<=$C$9,P17*$V$6/12,P17*$V$16/12) -> 1592966.3 | S18: =IFERROR(IF(O18<=$C$8,IF(O18<=$C$9,$V$7,$V$17),0),0) -> 1604295.9
H19: 15 | I19: =I18-J19 -> 7.8368856e+08 | J19: =L19-K19 -> -5366912.1 | K19: =$C$54/12*I18 -> 6971208 | L19: =L18 -> 1604295.9 | O19: 16 | P19: =P18-Q19 -> 1.7782879e+08 | Q19: =S19-R19 -> 11431.101 | R19: =IF(O19<=$C$9,P18*$V$6/12,P18*$V$16/12) -> 1592864.8 | S19: =IFERROR(IF(O19<=$C$8,IF(O19<=$C$9,$V$7,$V$17),0),0) -> 1604295.9 | U19: Cek sisa OS | V19: =VLOOKUP(C8,O4:P183,2,FALSE) -> 0
B20: Plafon Maksimal Pensiun | C20: =ROUND(-PV(C12/12,C10,C7, ,0)/10^6, )*10^6 -> 193000000 | D20: fx=ROUNDDOWN(-PV(C12/12;C10;C7;;0)/10^6;)*10^6 | H20: 16 | I20: =I19-J20 -> 7.8910354e+08 | J20: =L20-K20 -> -5414982 | K20: =$C$54/12*I19 -> 7019277.9 | L20: =L19 -> 1604295.9 | O20: 17 | P20: =P19-Q20 -> 1.7781726e+08 | Q20: =S20-R20 -> 11533.486 | R20: =IF(O20<=$C$9,P19*$V$6/12,P19*$V$16/12) -> 1592762.4 | S20: =IFERROR(IF(O20<=$C$8,IF(O20<=$C$9,$V$7,$V$17),0),0) -> 1604295.9
H21: 17 | I21: =I20-J21 -> 7.9456702e+08 | J21: =L21-K21 -> -5463482.5 | K21: =$C$54/12*I20 -> 7067778.4 | L21: =L20 -> 1604295.9 | O21: 18 | P21: =P20-Q21 -> 1.7780562e+08 | Q21: =S21-R21 -> 11636.788 | R21: =IF(O21<=$C$9,P20*$V$6/12,P20*$V$16/12) -> 1592659.1 | S21: =IFERROR(IF(O21<=$C$8,IF(O21<=$C$9,$V$7,$V$17),0),0) -> 1604295.9
A22: 2 | B22: Mencari Plafond maksimal saat Aktif | H22: 18 | I22: =I21-J22 -> 8.0007944e+08 | J22: =L22-K22 -> -5512417.4 | K22: =$C$54/12*I21 -> 7116713.3 | L22: =L21 -> 1604295.9 | O22: 19 | P22: =P21-Q22 -> 1.7779388e+08 | Q22: =S22-R22 -> 11741.015 | R22: =IF(O22<=$C$9,P21*$V$6/12,P21*$V$16/12) -> 1592554.9 | S22: =IFERROR(IF(O22<=$C$8,IF(O22<=$C$9,$V$7,$V$17),0),0) -> 1604295.9
B23: Menghitung Margin Maksimal dengan pokok 10.000 | H23: 19 | I23: =I22-J23 -> 8.0564123e+08 | J23: =L23-K23 -> -5561790.5 | K23: =$C$54/12*I22 -> 7166086.5 | L23: =L22 -> 1604295.9 | O23: 20 | P23: =P22-Q23 -> 1.7778203e+08 | Q23: =S23-R23 -> 11846.176 | R23: =IF(O23<=$C$9,P22*$V$6/12,P22*$V$16/12) -> 1592449.8 | S23: =IFERROR(IF(O23<=$C$8,IF(O23<=$C$9,$V$7,$V$17),0),0) -> 1604295.9
B24: Angsuran Maksimal Aktif | C24: =C6 -> 5694441.2 | D24: fx=C6 | H24: 20 | I24: =I23-J24 -> 8.1125284e+08 | J24: =L24-K24 -> -5611605.9 | K24: =$C$54/12*I23 -> 7215901.9 | L24: =L23 -> 1604295.9 | O24: 21 | P24: =P23-Q24 -> 1.7777008e+08 | Q24: =S24-R24 -> 11952.279 | R24: =IF(O24<=$C$9,P23*$V$6/12,P23*$V$16/12) -> 1592343.6 | S24: =IFERROR(IF(O24<=$C$8,IF(O24<=$C$9,$V$7,$V$17),0),0) -> 1604295.9
B25: Angsuran Pokok | C25: 10000 | H25: 21 | I25: =I24-J25 -> 8.169147e+08 | J25: =L25-K25 -> -5661867.5 | K25: =$C$54/12*I24 -> 7266163.4 | L25: =L24 -> 1604295.9 | O25: 22 | P25: =P24-Q25 -> 1.7775802e+08 | Q25: =S25-R25 -> 12059.333 | R25: =IF(O25<=$C$9,P24*$V$6/12,P24*$V$16/12) -> 1592236.6 | S25: =IFERROR(IF(O25<=$C$8,IF(O25<=$C$9,$V$7,$V$17),0),0) -> 1604295.9
B26: Angsuran Margin (maksimal) | C26: =C24-C25 -> 5684441.2 | D26: fx=C23-C24 | H26: 22 | I26: =I25-J26 -> 8.2262728e+08 | J26: =L26-K26 -> -5712579.3 | K26: =$C$54/12*I25 -> 7316875.2 | L26: =L25 -> 1604295.9 | O26: 23 | P26: =P25-Q26 -> 1.7774585e+08 | Q26: =S26-R26 -> 12167.345 | R26: =IF(O26<=$C$9,P25*$V$6/12,P25*$V$16/12) -> 1592128.6 | S26: =IFERROR(IF(O26<=$C$8,IF(O26<=$C$9,$V$7,$V$17),0),0) -> 1604295.9
B27: Plafon Maksimal Aktif | C27: =IF(ROUNDDOWN(C26/(C11/12)/10^6, )*10^6>800000000,800000000,ROUNDDOWN(C26/(C11/12)/10^6, )*10^6) -> 737000000 | D27: fx=ROUNDDOWN(C25/(C11/12)/10^6;)*10^6 | O27: 24 | P27: =P26-Q27 -> 1.7773358e+08 | Q27: =S27-R27 -> 12276.324 | R27: =IF(O27<=$C$9,P26*$V$6/12,P26*$V$16/12) -> 1592019.6 | S27: =IFERROR(IF(O27<=$C$8,IF(O27<=$C$9,$V$7,$V$17),0),0) -> 1604295.9
H28: Perhitungan jadwal Angsuran Pensiun | O28: 25 | P28: =P27-Q28 -> 1.7772119e+08 | Q28: =S28-R28 -> 12386.28 | R28: =IF(O28<=$C$9,P27*$V$6/12,P27*$V$16/12) -> 1591909.6 | S28: =IFERROR(IF(O28<=$C$8,IF(O28<=$C$9,$V$7,$V$17),0),0) -> 1604295.9
B29: Plafond maksimal adalah plafond minimal yang dipilih dari perbandingan plafond Aktif maupun Pensiun, sehingga diperoleh plafond rekomendasi yaitu Plafond Maksimal saat Pensiun | I29: fx=I25-J29 | J29: fx=L29-K29 | K29: fx=$C$62/12*I25 | L29: fx=$C$63 | O29: 26 | P29: =P28-Q29 -> 1.7770869e+08 | Q29: =S29-R29 -> 12497.22 | R29: =IF(O29<=$C$9,P28*$V$6/12,P28*$V$16/12) -> 1591798.7 | S29: =IFERROR(IF(O29<=$C$8,IF(O29<=$C$9,$V$7,$V$17),0),0) -> 1604295.9
H30: 23 | I30: =I26-J30 -> 8.1229588e+08 | J30: =L30-K30 -> 10331404 | K30: =$C$63/12*I26 -> 7575026.2 | L30: =$C$64 -> 17906430 | O30: 27 | P30: =P29-Q30 -> 1.7769608e+08 | Q30: =S30-R30 -> 12609.154 | R30: =IF(O30<=$C$9,P29*$V$6/12,P29*$V$16/12) -> 1591686.8 | S30: =IFERROR(IF(O30<=$C$8,IF(O30<=$C$9,$V$7,$V$17),0),0) -> 1604295.9
B31: Plafon rekomendasi | C31: =MIN(C20,C27) -> 193000000 | D31: fx=MIN(C19;C26) | H31: 24 | I31: =I30-J31 -> 8.0186934e+08 | J31: =L31-K31 -> 10426539 | K31: =$C$63/12*I30 -> 7479891.2 | L31: =L30 -> 17906430 | O31: 28 | P31: =P30-Q31 -> 1.7768336e+08 | Q31: =S31-R31 -> 12722.091 | R31: =IF(O31<=$C$9,P30*$V$6/12,P30*$V$16/12) -> 1591573.8 | S31: =IFERROR(IF(O31<=$C$8,IF(O31<=$C$9,$V$7,$V$17),0),0) -> 1604295.9
H32: 25 | I32: =I31-J32 -> 7.9134679e+08 | J32: =L32-K32 -> 10522550 | K32: =$C$63/12*I31 -> 7383880.2 | L32: =L31 -> 17906430 | O32: 29 | P32: =P31-Q32 -> 1.7767053e+08 | Q32: =S32-R32 -> 12836.039 | R32: =IF(O32<=$C$9,P31*$V$6/12,P31*$V$16/12) -> 1591459.9 | S32: =IFERROR(IF(O32<=$C$8,IF(O32<=$C$9,$V$7,$V$17),0),0) -> 1604295.9
A33: 3 | B33: SKEMA ATRIBUSI | H33: 26 | I33: =I32-J33 -> 7.8072735e+08 | J33: =L33-K33 -> 10619445 | K33: =$C$63/12*I32 -> 7286985 | L33: =L32 -> 17906430 | O33: 30 | P33: =P32-Q33 -> 1.7765757e+08 | Q33: =S33-R33 -> 12951.008 | R33: =IF(O33<=$C$9,P32*$V$6/12,P32*$V$16/12) -> 1591344.9 | S33: =IFERROR(IF(O33<=$C$8,IF(O33<=$C$9,$V$7,$V$17),0),0) -> 1604295.9
B34: Atribusi | C34: =C13 -> 39998267 | D34: fx=C13 | H34: 27 | I34: =I33-J34 -> 7.7001011e+08 | J34: =L34-K34 -> 10717232 | K34: =$C$63/12*I33 -> 7189197.6 | L34: =L33 -> 17906430 | O34: 31 | P34: =P33-Q34 -> 1.7764451e+08 | Q34: =S34-R34 -> 13067.006 | R34: =IF(O34<=$C$9,P33*$V$6/12,P33*$V$16/12) -> 1591228.9 | S34: =IFERROR(IF(O34<=$C$8,IF(O34<=$C$9,$V$7,$V$17),0),0) -> 1604295.9
B35: Atribusi per Bulan | C35: =C34/C8 -> 222212.59 | D35: fx=C33/C8 | H35: 28 | I35: =I34-J35 -> 7.5919419e+08 | J35: =L35-K35 -> 10815920 | K35: =$C$63/12*I34 -> 7090509.8 | L35: =L34 -> 17906430 | O35: 32 | P35: =P34-Q35 -> 1.7763132e+08 | Q35: =S35-R35 -> 13184.044 | R35: =IF(O35<=$C$9,P34*$V$6/12,P34*$V$16/12) -> 1591111.9 | S35: =IFERROR(IF(O35<=$C$8,IF(O35<=$C$9,$V$7,$V$17),0),0) -> 1604295.9
B36: Plafon Maksimal Pensiun | C36: =ROUNDDOWN(-PV((C12+0.01)/12,C10,C7-C35, ,0)/10^6, )*10^6 -> 178000000 | D36: fx=ROUNDDOWN(-PV(C12/12;C10;C7-C34;;0)/10^6;)*10^6 | H36: 29 | I36: =I35-J36 -> 7.4827868e+08 | J36: =L36-K36 -> 10915517 | K36: =$C$63/12*I35 -> 6990913.2 | L36: =L35 -> 17906430 | O36: 33 | P36: =P35-Q36 -> 1.7761802e+08 | Q36: =S36-R36 -> 13302.13 | R36: =IF(O36<=$C$9,P35*$V$6/12,P35*$V$16/12) -> 1590993.8 | S36: =IFERROR(IF(O36<=$C$8,IF(O36<=$C$9,$V$7,$V$17),0),0) -> 1604295.9
H37: 30 | I37: =I36-J37 -> 7.3726265e+08 | J37: =L37-K37 -> 11016030 | K37: =$C$63/12*I36 -> 6890399.5 | L37: =L36 -> 17906430 | O37: 34 | P37: =P36-Q37 -> 1.776046e+08 | Q37: =S37-R37 -> 13421.273 | R37: =IF(O37<=$C$9,P36*$V$6/12,P36*$V$16/12) -> 1590874.7 | S37: =IFERROR(IF(O37<=$C$8,IF(O37<=$C$9,$V$7,$V$17),0),0) -> 1604295.9
A38: 4 | B38: Mencari Plafond maksimal saat Aktif | H38: 31 | I38: =I37-J38 -> 7.2614518e+08 | J38: =L38-K38 -> 11117470 | K38: =$C$63/12*I37 -> 6788960.2 | L38: =L37 -> 17906430 | O38: 35 | P38: =P37-Q38 -> 1.7759106e+08 | Q38: =S38-R38 -> 13541.484 | R38: =IF(O38<=$C$9,P37*$V$6/12,P37*$V$16/12) -> 1590754.4 | S38: =IFERROR(IF(O38<=$C$8,IF(O38<=$C$9,$V$7,$V$17),0),0) -> 1604295.9
B39: Menghitung Margin Maksimal dengan pokok 10.000 | H39: 32 | I39: =I38-J39 -> 7.1492533e+08 | J39: =L39-K39 -> 11219843 | K39: =$C$63/12*I38 -> 6686586.8 | L39: =L38 -> 17906430 | O39: 36 | P39: =P38-Q39 -> 1.775774e+08 | Q39: =S39-R39 -> 13662.771 | R39: =IF(O39<=$C$9,P38*$V$6/12,P38*$V$16/12) -> 1590633.2 | S39: =IFERROR(IF(O39<=$C$8,IF(O39<=$C$9,$V$7,$V$17),0),0) -> 1604295.9
B40: Angsuran Maksimal Aktif | C40: =C6 -> 5694441.2 | D40: fx=C6 | H40: 33 | I40: =I39-J40 -> 7.0360217e+08 | J40: =L40-K40 -> 11323159 | K40: =$C$63/12*I39 -> 6583270.8 | L40: =L39 -> 17906430 | O40: 37 | P40: =P39-Q40 -> 1.7756361e+08 | Q40: =S40-R40 -> 13785.144 | R40: =IF(O40<=$C$9,P39*$V$6/12,P39*$V$16/12) -> 1590510.8 | S40: =IFERROR(IF(O40<=$C$8,IF(O40<=$C$9,$V$7,$V$17),0),0) -> 1604295.9
B41: Angsuran Pokok | C41: 10000 | H41: 34 | I41: =I40-J41 -> 6.9217475e+08 | J41: =L41-K41 -> 11427426 | K41: =$C$63/12*I40 -> 6479003.4 | L41: =L40 -> 17906430 | O41: 38 | P41: =P40-Q41 -> 1.775497e+08 | Q41: =S41-R41 -> 13908.614 | R41: =IF(O41<=$C$9,P40*$V$6/12,P40*$V$16/12) -> 1590387.3 | S41: =IFERROR(IF(O41<=$C$8,IF(O41<=$C$9,$V$7,$V$17),0),0) -> 1604295.9
B42: Atribusi per Bulan | C42: =C35 -> 222212.59 | D42: fx=C34 | H42: 35 | I42: =I41-J42 -> 6.8064209e+08 | J42: =L42-K42 -> 11532654 | K42: =$C$63/12*I41 -> 6373775.8 | L42: =L41 -> 17906430 | O42: 39 | P42: =P41-Q42 -> 1.7753567e+08 | Q42: =S42-R42 -> 14033.19 | R42: =IF(O42<=$C$9,P41*$V$6/12,P41*$V$16/12) -> 1590262.7 | S42: =IFERROR(IF(O42<=$C$8,IF(O42<=$C$9,$V$7,$V$17),0),0) -> 1604295.9
B43: Angsuran Margin (maksimal) | C43: =C40-C41-C42 -> 5462228.6 | D43: fx=C39-C40-C41 | H43: 36 | I43: =I42-J43 -> 6.6900324e+08 | J43: =L43-K43 -> 11638851 | K43: =$C$63/12*I42 -> 6267579.3 | L43: =L42 -> 17906430 | O43: 40 | P43: =P42-Q43 -> 1.7752151e+08 | Q43: =S43-R43 -> 14158.881 | R43: =IF(O43<=$C$9,P42*$V$6/12,P42*$V$16/12) -> 1590137 | S43: =IFERROR(IF(O43<=$C$8,IF(O43<=$C$9,$V$7,$V$17),0),0) -> 1604295.9
B44: Plafon Maksimal Aktif | C44: =ROUNDDOWN(C43/(C11/12)/10^6,0)*10^6 -> 708000000 | D44: fx=ROUNDDOWN(C42/(C11/12)/10^6;0)*10^6 | H44: 37 | I44: =I43-J44 -> 6.5725722e+08 | J44: =L44-K44 -> 11746025 | K44: =$C$63/12*I43 -> 6160404.9 | L44: =L43 -> 17906430 | O44: 41 | P44: =P43-Q44 -> 1.7750722e+08 | Q44: =S44-R44 -> 14285.698 | R44: =IF(O44<=$C$9,P43*$V$6/12,P43*$V$16/12) -> 1590010.2 | S44: =IFERROR(IF(O44<=$C$8,IF(O44<=$C$9,$V$7,$V$17),0),0) -> 1604295.9
H45: 38 | I45: =I44-J45 -> 6.4540303e+08 | J45: =L45-K45 -> 11854186 | K45: =$C$63/12*I44 -> 6052243.6 | L45: =L44 -> 17906430 | O45: 42 | P45: =P44-Q45 -> 1.7749281e+08 | Q45: =S45-R45 -> 14413.651 | R45: =IF(O45<=$C$9,P44*$V$6/12,P44*$V$16/12) -> 1589882.3 | S45: =IFERROR(IF(O45<=$C$8,IF(O45<=$C$9,$V$7,$V$17),0),0) -> 1604295.9
B46: Plafon Rekomendasi Maksimal | C46: =MIN(C36,C44) -> 178000000 | D46: fx=MIN(C35;C43) | H46: 39 | I46: =I45-J46 -> 6.3343969e+08 | J46: =L46-K46 -> 11963344 | K46: =$C$63/12*I45 -> 5943086.3 | L46: =L45 -> 17906430 | O46: 43 | P46: =P45-Q46 -> 1.7747827e+08 | Q46: =S46-R46 -> 14542.75 | R46: =IF(O46<=$C$9,P45*$V$6/12,P45*$V$16/12) -> 1589753.2 | S46: =IFERROR(IF(O46<=$C$8,IF(O46<=$C$9,$V$7,$V$17),0),0) -> 1604295.9
H47: 40 | I47: =I46-J47 -> 6.2136618e+08 | J47: =L47-K47 -> 12073506 | K47: =$C$63/12*I46 -> 5832923.8 | L47: =L46 -> 17906430 | O47: 44 | P47: =P46-Q47 -> 1.774636e+08 | Q47: =S47-R47 -> 14673.005 | R47: =IF(O47<=$C$9,P46*$V$6/12,P46*$V$16/12) -> 1589622.9 | S47: =IFERROR(IF(O47<=$C$8,IF(O47<=$C$9,$V$7,$V$17),0),0) -> 1604295.9
A48: 5 | B48: Menghitung Rate Atribusi Aktif | H48: 41 | I48: =I47-J48 -> 6.091815e+08 | J48: =L48-K48 -> 12184683 | K48: =$C$63/12*I47 -> 5721746.9 | L48: =L47 -> 17906430 | O48: 45 | P48: =P47-Q48 -> 1.7744879e+08 | Q48: =S48-R48 -> 14804.427 | R48: =IF(O48<=$C$9,P47*$V$6/12,P47*$V$16/12) -> 1589491.5 | S48: =IFERROR(IF(O48<=$C$8,IF(O48<=$C$9,$V$7,$V$17),0),0) -> 1604295.9
B49: Margin Aktif | C49: =C11/12*C46 -> 1372083.3 | D49: fx=C11/12*C45 | H49: 42 | I49: =I48-J49 -> 5.9688462e+08 | J49: =L49-K49 -> 12296883 | K49: =$C$63/12*I48 -> 5609546.3 | L49: =L48 -> 17906430 | O49: 46 | P49: =P48-Q49 -> 1.7743385e+08 | Q49: =S49-R49 -> 14937.026 | R49: =IF(O49<=$C$9,P48*$V$6/12,P48*$V$16/12) -> 1589358.9 | S49: =IFERROR(IF(O49<=$C$8,IF(O49<=$C$9,$V$7,$V$17),0),0) -> 1604295.9
B50: Angsuran Pokok Aktif | C50: 10000 | H50: 43 | I50: =I49-J50 -> 5.844745e+08 | J50: =L50-K50 -> 12410117 | K50: =$C$63/12*I49 -> 5496312.5 | L50: =L49 -> 17906430 | O50: 47 | P50: =P49-Q50 -> 1.7741878e+08 | Q50: =S50-R50 -> 15070.813 | R50: =IF(O50<=$C$9,P49*$V$6/12,P49*$V$16/12) -> 1589225.1 | S50: =IFERROR(IF(O50<=$C$8,IF(O50<=$C$9,$V$7,$V$17),0),0) -> 1604295.9
B51: Angsuran (Margin+Pokok) | C51: =C49+C50 -> 1382083.3 | D51: fx=C48+C49 | H51: 44 | I51: =I50-J51 -> 5.7195011e+08 | J51: =L51-K51 -> 12524394 | K51: =$C$63/12*I50 -> 5382036 | L51: =L50 -> 17906430 | O51: 48 | P51: =P50-Q51 -> 1.7740358e+08 | Q51: =S51-R51 -> 15205.798 | R51: =IF(O51<=$C$9,P50*$V$6/12,P50*$V$16/12) -> 1589090.1 | S51: =IFERROR(IF(O51<=$C$8,IF(O51<=$C$9,$V$7,$V$17),0),0) -> 1604295.9
B52: Atribusi per Bulan | C52: =C42 -> 222212.59 | D52: fx=C41 | H52: 45 | I52: =I51-J52 -> 5.5931038e+08 | J52: =L52-K52 -> 12639723 | K52: =$C$63/12*I51 -> 5266707.2 | L52: =L51 -> 17906430 | O52: 49 | P52: =P51-Q52 -> 1.7738824e+08 | Q52: =S52-R52 -> 15341.992 | R52: =IF(O52<=$C$9,P51*$V$6/12,P51*$V$16/12) -> 1588953.9 | S52: =IFERROR(IF(O52<=$C$8,IF(O52<=$C$9,$V$7,$V$17),0),0) -> 1604295.9
B53: Angsuran (Margin+Atribusi) | C53: =C49+C52 -> 1594295.9 | D53: fx=C48+C51 | H53: 46 | I53: =I52-J53 -> 5.4655427e+08 | J53: =L53-K53 -> 12756113 | K53: =$C$63/12*I52 -> 5150316.4 | L53: =L52 -> 17906430 | O53: 50 | P53: =P52-Q53 -> 1.7737276e+08 | Q53: =S53-R53 -> 15479.406 | R53: =IF(O53<=$C$9,P52*$V$6/12,P52*$V$16/12) -> 1588816.5 | S53: =IFERROR(IF(O53<=$C$8,IF(O53<=$C$9,$V$7,$V$17),0),0) -> 1604295.9
B54: Rate Atribusi Aktif | C54: =C53/C46*12 -> 0.10748062 | D54: fx=C52/C45*12 | H54: 47 | I54: =I53-J54 -> 5.3368069e+08 | J54: =L54-K54 -> 12873576 | K54: =$C$63/12*I53 -> 5032853.9 | L54: =L53 -> 17906430 | O54: 51 | P54: =P53-Q54 -> 1.7735714e+08 | Q54: =S54-R54 -> 15618.051 | R54: =IF(O54<=$C$9,P53*$V$6/12,P53*$V$16/12) -> 1588677.9 | S54: =IFERROR(IF(O54<=$C$8,IF(O54<=$C$9,$V$7,$V$17),0),0) -> 1604295.9
B55: Total Angsuran saat Aktif | C55: =C53+C50 -> 1604295.9 | D55: fx=C52+C49 | H55: 48 | I55: =I54-J55 -> 5.2068857e+08 | J55: =L55-K55 -> 12992120 | K55: =$C$63/12*I54 -> 4914309.7 | L55: =L54 -> 17906430 | O55: 52 | P55: =P54-Q55 -> 1.7734138e+08 | Q55: =S55-R55 -> 15757.937 | R55: =IF(O55<=$C$9,P54*$V$6/12,P54*$V$16/12) -> 1588538 | S55: =IFERROR(IF(O55<=$C$8,IF(O55<=$C$9,$V$7,$V$17),0),0) -> 1604295.9
H56: 49 | I56: =I55-J56 -> 5.0757682e+08 | J56: =L56-K56 -> 13111756 | K56: =$C$63/12*I55 -> 4794673.9 | L56: =L55 -> 17906430 | O56: 53 | P56: =P55-Q56 -> 1.7732548e+08 | Q56: =S56-R56 -> 15899.077 | R56: =IF(O56<=$C$9,P55*$V$6/12,P55*$V$16/12) -> 1588396.9 | S56: =IFERROR(IF(O56<=$C$8,IF(O56<=$C$9,$V$7,$V$17),0),0) -> 1604295.9
A57: 6 | B57: Menghitung Rate Atribusi Pensiun | H57: 50 | I57: =I56-J57 -> 4.9434432e+08 | J57: =L57-K57 -> 13232493 | K57: =$C$63/12*I56 -> 4673936.5 | L57: =L56 -> 17906430 | O57: 54 | P57: =P56-Q57 -> 1.7730944e+08 | Q57: =S57-R57 -> 16041.48 | R57: =IF(O57<=$C$9,P56*$V$6/12,P56*$V$16/12) -> 1588254.4 | S57: =IFERROR(IF(O57<=$C$8,IF(O57<=$C$9,$V$7,$V$17),0),0) -> 1604295.9
B58: Membuat simulasi jadwal angsuran aktif untuk mengetahui sisa OS saat pensiun --> | H58: 51 | I58: =I57-J58 -> 4.8098998e+08 | J58: =L58-K58 -> 13354342 | K58: =$C$63/12*I57 -> 4552087.3 | L58: =L57 -> 17906430 | O58: 55 | P58: =P57-Q58 -> 1.7729325e+08 | Q58: =S58-R58 -> 16185.159 | R58: =IF(O58<=$C$9,P57*$V$6/12,P57*$V$16/12) -> 1588110.8 | S58: =IFERROR(IF(O58<=$C$8,IF(O58<=$C$9,$V$7,$V$17),0),0) -> 1604295.9
B59: Sisa OS saat pensiun | C59: =I26 -> 8.2262728e+08 | D59: fx=I57 | H59: 52 | I59: =I58-J59 -> 4.6751267e+08 | J59: =L59-K59 -> 13477314 | K59: =$C$63/12*I58 -> 4429116.1 | L59: =L58 -> 17906430 | O59: 56 | P59: =P58-Q59 -> 1.7727692e+08 | Q59: =S59-R59 -> 16330.125 | R59: =IF(O59<=$C$9,P58*$V$6/12,P58*$V$16/12) -> 1587965.8 | S59: =IFERROR(IF(O59<=$C$8,IF(O59<=$C$9,$V$7,$V$17),0),0) -> 1604295.9
B60: Angsuran Pensiun | C60: =-PMT(C12/12,C10,C59,0,0) -> 17681469 | D60: fx=-PMT(C12/12;C10;C58;0;0) | H60: 53 | I60: =I59-J60 -> 4.5391125e+08 | J60: =L60-K60 -> 13601417 | K60: =$C$63/12*I59 -> 4305012.5 | L60: =L59 -> 17906430 | O60: 57 | P60: =P59-Q60 -> 1.7726045e+08 | Q60: =S60-R60 -> 16476.39 | R60: =IF(O60<=$C$9,P59*$V$6/12,P59*$V$16/12) -> 1587819.5 | S60: =IFERROR(IF(O60<=$C$8,IF(O60<=$C$9,$V$7,$V$17),0),0) -> 1604295.9
B61: Atribusi per Bulan | C61: =C52 -> 222212.59 | D61: fx=C51 | H61: 54 | I61: =I60-J61 -> 4.4018459e+08 | J61: =L61-K61 -> 13726664 | K61: =$C$63/12*I60 -> 4179766.1 | L61: =L60 -> 17906430 | O61: 58 | P61: =P60-Q61 -> 1.7724382e+08 | Q61: =S61-R61 -> 16623.964 | R61: =IF(O61<=$C$9,P60*$V$6/12,P60*$V$16/12) -> 1587672 | S61: =IFERROR(IF(O61<=$C$8,IF(O61<=$C$9,$V$7,$V$17),0),0) -> 1604295.9
B62: Angsuran (pensiun+atrib) | C62: =C60+C61 -> 17903681 | D62: fx=C59+C60 | H62: 55 | I62: =I61-J62 -> 4.2633152e+08 | J62: =L62-K62 -> 13853063 | K62: =$C$63/12*I61 -> 4053366.4 | L62: =L61 -> 17906430 | O62: 59 | P62: =P61-Q62 -> 1.7722705e+08 | Q62: =S62-R62 -> 16772.86 | R62: =IF(O62<=$C$9,P61*$V$6/12,P61*$V$16/12) -> 1587523.1 | S62: =IFERROR(IF(O62<=$C$8,IF(O62<=$C$9,$V$7,$V$17),0),0) -> 1604295.9
B63: Rate Atribusi Pensiun | C63: =ROUNDUP(RATE(C10,C62,-C59,0,0)*12,4) -> 0.1105 | D63: fx=ROUNDUP(RATE(C10;C61;-C58;0;0)*12;4) | H63: 56 | I63: =I62-J63 -> 4.123509e+08 | J63: =L63-K63 -> 13980627 | K63: =$C$63/12*I62 -> 3925802.8 | L63: =L62 -> 17906430 | O63: 60 | P63: =P62-Q63 -> 1.7721013e+08 | Q63: =S63-R63 -> 16923.09 | R63: =IF(O63<=$C$9,P62*$V$6/12,P62*$V$16/12) -> 1587372.8 | S63: =IFERROR(IF(O63<=$C$8,IF(O63<=$C$9,$V$7,$V$17),0),0) -> 1604295.9
B64: Total Angsuran saat Pensiun | C64: =-PMT(C63/12,C10,C59,0,0) -> 17906430 | D64: fx=-PMT(C62/12;C10;C58;0;0) | H64: 57 | I64: =I63-J64 -> 3.9824153e+08 | J64: =L64-K64 -> 14109365 | K64: =$C$63/12*I63 -> 3797064.5 | L64: =L63 -> 17906430 | O64: 61 | P64: =P63-Q64 -> 1.7719305e+08 | Q64: =S64-R64 -> 17074.665 | R64: =IF(O64<=$C$9,P63*$V$6/12,P63*$V$16/12) -> 1587221.3 | S64: =IFERROR(IF(O64<=$C$8,IF(O64<=$C$9,$V$7,$V$17),0),0) -> 1604295.9
H65: 58 | I65: =I64-J65 -> 3.8400224e+08 | J65: =L65-K65 -> 14239289 | K65: =$C$63/12*I64 -> 3667140.8 | L65: =L64 -> 17906430 | O65: 62 | P65: =P64-Q65 -> 1.7717583e+08 | Q65: =S65-R65 -> 17227.598 | R65: =IF(O65<=$C$9,P64*$V$6/12,P64*$V$16/12) -> 1587068.3 | S65: =IFERROR(IF(O65<=$C$8,IF(O65<=$C$9,$V$7,$V$17),0),0) -> 1604295.9
H66: 59 | I66: =I65-J66 -> 3.6963183e+08 | J66: =L66-K66 -> 14370409 | K66: =$C$63/12*I65 -> 3536020.6 | L66: =L65 -> 17906430 | O66: 63 | P66: =P65-Q66 -> 1.7715844e+08 | Q66: =S66-R66 -> 17381.901 | R66: =IF(O66<=$C$9,P65*$V$6/12,P65*$V$16/12) -> 1586914 | S66: =IFERROR(IF(O66<=$C$8,IF(O66<=$C$9,$V$7,$V$17),0),0) -> 1604295.9
H67: 60 | I67: =I66-J67 -> 3.551291e+08 | J67: =L67-K67 -> 14502737 | K67: =$C$63/12*I66 -> 3403693.1 | L67: =L66 -> 17906430 | O67: 64 | P67: =P66-Q67 -> 1.7714091e+08 | Q67: =S67-R67 -> 17537.586 | R67: =IF(O67<=$C$9,P66*$V$6/12,P66*$V$16/12) -> 1586758.3 | S67: =IFERROR(IF(O67<=$C$8,IF(O67<=$C$9,$V$7,$V$17),0),0) -> 1604295.9
B68: Note utk PP3 | H68: 61 | I68: =I67-J68 -> 3.4049281e+08 | J68: =L68-K68 -> 14636283 | K68: =$C$63/12*I67 -> 3270147.1 | L68: =L67 -> 17906430 | O68: 65 | P68: =P67-Q68 -> 1.7712321e+08 | Q68: =S68-R68 -> 17694.665 | R68: =IF(O68<=$C$9,P67*$V$6/12,P67*$V$16/12) -> 1586601.3 | S68: =IFERROR(IF(O68<=$C$8,IF(O68<=$C$9,$V$7,$V$17),0),0) -> 1604295.9
A69: 1. | B69: Perhitungan sesuai reguler dengan adjustment rate | H69: 62 | I69: =I68-J69 -> 3.2572176e+08 | J69: =L69-K69 -> 14771058 | K69: =$C$63/12*I68 -> 3135371.3 | L69: =L68 -> 17906430 | O69: 66 | P69: =P68-Q69 -> 1.7710536e+08 | Q69: =S69-R69 -> 17853.151 | R69: =IF(O69<=$C$9,P68*$V$6/12,P68*$V$16/12) -> 1586442.8 | S69: =IFERROR(IF(O69<=$C$8,IF(O69<=$C$9,$V$7,$V$17),0),0) -> 1604295.9
A70: 2. | B70: Adj rate Aktif gak ada | H70: 63 | I70: =I69-J70 -> 3.1081468e+08 | J70: =L70-K70 -> 14907075 | K70: =$C$63/12*I69 -> 2999354.5 | L70: =L69 -> 17906430 | O70: 67 | P70: =P69-Q70 -> 1.7708734e+08 | Q70: =S70-R70 -> 18013.057 | R70: =IF(O70<=$C$9,P69*$V$6/12,P69*$V$16/12) -> 1586282.9 | S70: =IFERROR(IF(O70<=$C$8,IF(O70<=$C$9,$V$7,$V$17),0),0) -> 1604295.9
A71: 3. | B71: Adj rate pensiun +0,01 (1%) | H71: 64 | I71: =I70-J71 -> 2.9577034e+08 | J71: =L71-K71 -> 15044345 | K71: =$C$63/12*I70 -> 2862085.2 | L71: =L70 -> 17906430 | O71: 68 | P71: =P70-Q71 -> 1.7706917e+08 | Q71: =S71-R71 -> 18174.395 | R71: =IF(O71<=$C$9,P70*$V$6/12,P70*$V$16/12) -> 1586121.5 | S71: =IFERROR(IF(O71<=$C$8,IF(O71<=$C$9,$V$7,$V$17),0),0) -> 1604295.9
A72: 4. | B72: ada adjustment aktif -2 bulan | H72: 65 | I72: =I71-J72 -> 2.8058746e+08 | J72: =L72-K72 -> 15182878 | K72: =$C$63/12*I71 -> 2723551.8 | L72: =L71 -> 17906430 | O72: 69 | P72: =P71-Q72 -> 1.7705083e+08 | Q72: =S72-R72 -> 18337.178 | R72: =IF(O72<=$C$9,P71*$V$6/12,P71*$V$16/12) -> 1585958.8 | S72: =IFERROR(IF(O72<=$C$8,IF(O72<=$C$9,$V$7,$V$17),0),0) -> 1604295.9
H73: 66 | I73: =I72-J73 -> 2.6526477e+08 | J73: =L73-K73 -> 15322687 | K73: =$C$63/12*I72 -> 2583742.8 | L73: =L72 -> 17906430 | O73: 70 | P73: =P72-Q73 -> 1.7703233e+08 | Q73: =S73-R73 -> 18501.419 | R73: =IF(O73<=$C$9,P72*$V$6/12,P72*$V$16/12) -> 1585794.5 | S73: =IFERROR(IF(O73<=$C$8,IF(O73<=$C$9,$V$7,$V$17),0),0) -> 1604295.9
H74: 67 | I74: =I73-J74 -> 2.4980099e+08 | J74: =L74-K74 -> 15463783 | K74: =$C$63/12*I73 -> 2442646.4 | L74: =L73 -> 17906430 | O74: 71 | P74: =P73-Q74 -> 1.7701366e+08 | Q74: =S74-R74 -> 18667.131 | R74: =IF(O74<=$C$9,P73*$V$6/12,P73*$V$16/12) -> 1585628.8 | S74: =IFERROR(IF(O74<=$C$8,IF(O74<=$C$9,$V$7,$V$17),0),0) -> 1604295.9
H75: 68 | I75: =I74-J75 -> 2.3419481e+08 | J75: =L75-K75 -> 15606179 | K75: =$C$63/12*I74 -> 2300250.8 | L75: =L74 -> 17906430 | O75: 72 | P75: =P74-Q75 -> 1.7699483e+08 | Q75: =S75-R75 -> 18834.327 | R75: =IF(O75<=$C$9,P74*$V$6/12,P74*$V$16/12) -> 1585461.6 | S75: =IFERROR(IF(O75<=$C$8,IF(O75<=$C$9,$V$7,$V$17),0),0) -> 1604295.9
H76: 69 | I76: =I75-J76 -> 2.1844492e+08 | J76: =L76-K76 -> 15749886 | K76: =$C$63/12*I75 -> 2156543.9 | L76: =L75 -> 17906430 | O76: 73 | P76: =P75-Q76 -> 1.7697583e+08 | Q76: =S76-R76 -> 19003.021 | R76: =IF(O76<=$C$9,P75*$V$6/12,P75*$V$16/12) -> 1585292.9 | S76: =IFERROR(IF(O76<=$C$8,IF(O76<=$C$9,$V$7,$V$17),0),0) -> 1604295.9
H77: 70 | I77: =I76-J77 -> 2.0255001e+08 | J77: =L77-K77 -> 15894916 | K77: =$C$63/12*I76 -> 2011513.7 | L77: =L76 -> 17906430 | O77: 74 | P77: =P76-Q77 -> 1.7695665e+08 | Q77: =S77-R77 -> 19173.225 | R77: =IF(O77<=$C$9,P76*$V$6/12,P76*$V$16/12) -> 1585122.7 | S77: =IFERROR(IF(O77<=$C$8,IF(O77<=$C$9,$V$7,$V$17),0),0) -> 1604295.9
H78: 71 | I78: =I77-J78 -> 1.8650872e+08 | J78: =L78-K78 -> 16041282 | K78: =$C$63/12*I77 -> 1865148 | L78: =L77 -> 17906430 | O78: 75 | P78: =P77-Q78 -> 1.7693731e+08 | Q78: =S78-R78 -> 19344.955 | R78: =IF(O78<=$C$9,P77*$V$6/12,P77*$V$16/12) -> 1584951 | S78: =IFERROR(IF(O78<=$C$8,IF(O78<=$C$9,$V$7,$V$17),0),0) -> 1604295.9
H79: 72 | I79: =I78-J79 -> 1.7031973e+08 | J79: =L79-K79 -> 16188995 | K79: =$C$63/12*I78 -> 1717434.5 | L79: =L78 -> 17906430 | O79: 76 | P79: =P78-Q79 -> 1.7691779e+08 | Q79: =S79-R79 -> 19518.222 | R79: =IF(O79<=$C$9,P78*$V$6/12,P78*$V$16/12) -> 1584777.7 | S79: =IFERROR(IF(O79<=$C$8,IF(O79<=$C$9,$V$7,$V$17),0),0) -> 1604295.9
H80: 73 | I80: =I79-J80 -> 1.5398166e+08 | J80: =L80-K80 -> 16338069 | K80: =$C$63/12*I79 -> 1568360.8 | L80: =L79 -> 17906430 | O80: 77 | P80: =P79-Q80 -> 1.768981e+08 | Q80: =S80-R80 -> 19693.041 | R80: =IF(O80<=$C$9,P79*$V$6/12,P79*$V$16/12) -> 1584602.9 | S80: =IFERROR(IF(O80<=$C$8,IF(O80<=$C$9,$V$7,$V$17),0),0) -> 1604295.9
H81: 74 | I81: =I80-J81 -> 1.3749314e+08 | J81: =L81-K81 -> 16488515 | K81: =$C$63/12*I80 -> 1417914.5 | L81: =L80 -> 17906430 | O81: 78 | P81: =P80-Q81 -> 1.7687823e+08 | Q81: =S81-R81 -> 19869.426 | R81: =IF(O81<=$C$9,P80*$V$6/12,P80*$V$16/12) -> 1584426.5 | S81: =IFERROR(IF(O81<=$C$8,IF(O81<=$C$9,$V$7,$V$17),0),0) -> 1604295.9
H82: 75 | I82: =I81-J82 -> 1.208528e+08 | J82: =L82-K82 -> 16640347 | K82: =$C$63/12*I81 -> 1266082.7 | L82: =L81 -> 17906430 | O82: 79 | P82: =P81-Q82 -> 1.7685818e+08 | Q82: =S82-R82 -> 20047.391 | R82: =IF(O82<=$C$9,P81*$V$6/12,P81*$V$16/12) -> 1584248.5 | S82: =IFERROR(IF(O82<=$C$8,IF(O82<=$C$9,$V$7,$V$17),0),0) -> 1604295.9
H83: 76 | I83: =I82-J83 -> 1.0405922e+08 | J83: =L83-K83 -> 16793577 | K83: =$C$63/12*I82 -> 1112852.8 | L83: =L82 -> 17906430 | O83: 80 | P83: =P82-Q83 -> 1.7683795e+08 | Q83: =S83-R83 -> 20226.95 | R83: =IF(O83<=$C$9,P82*$V$6/12,P82*$V$16/12) -> 1584069 | S83: =IFERROR(IF(O83<=$C$8,IF(O83<=$C$9,$V$7,$V$17),0),0) -> 1604295.9
H84: 77 | I84: =I83-J84 -> 87111003 | J84: =L84-K84 -> 16948218 | K84: =$C$63/12*I83 -> 958211.99 | L84: =L83 -> 17906430 | O84: 81 | P84: =P83-Q84 -> 1.7681755e+08 | Q84: =S84-R84 -> 20408.117 | R84: =IF(O84<=$C$9,P83*$V$6/12,P83*$V$16/12) -> 1583887.8 | S84: =IFERROR(IF(O84<=$C$8,IF(O84<=$C$9,$V$7,$V$17),0),0) -> 1604295.9
... H243: 236 | I243: =I242-J243 -> -6.0330695e+09 | J243: =L243-K243 -> 72790664 | K243: =$C$63/12*I242 -> -54884234 | L243: =L242 -> 17906430 | O243: 240 | P243: =P242-Q243 -> 0 | Q243: =S243-R243 -> 0 | R243: =IF(O243<=$C$9,P242*$V$6/12,P242*$V$16/12) -> 0 | S243: =IFERROR(IF(O243<=$C$8,IF(O243<=$C$9,$V$7,$V$17),0),0) -> 0
H244: 237 | I244: =I243-J244 -> -6.1065305e+09 | J244: =L244-K244 -> 73460945 | K244: =$C$63/12*I243 -> -55554515 | L244: =L243 -> 17906430
H245: 238 | I245: =I244-J245 -> -6.1806679e+09 | J245: =L245-K245 -> 74137398 | K245: =$C$63/12*I244 -> -56230968 | L245: =L244 -> 17906430
H246: 239 | I246: =I245-J246 -> -6.2554879e+09 | J246: =L246-K246 -> 74820080 | K246: =$C$63/12*I245 -> -56913650 | L246: =L245 -> 17906430
H247: 240 | J247: =L247-K247 -> 75509048 | K247: =$C$63/12*I246 -> -57602618 | L247: =L246 -> 17906430

Sheet Sheet1
B2: tanpa atrib | C2: atrib | D2: plafon atr
B3: 540 | C3: 39 | D3: 500
C5: 39 | D5: 519
